Workbook
Name hoy: TODAY()
Name hoy: TODAY()
Name hoy: TODAY()
Name Inicio_del_proyecto: 'Proyecto Datos (Actual)'!$E$3
Name Inicio_del_proyecto: 'Proyecto Datos (OKR´s)'!$K$3
Name Inicio_del_proyecto: 'Proyecto Datos'!$E$3
Name Semana_para_mostrar: 'Proyecto Datos (Actual)'!$E$4
Name Semana_para_mostrar: 'Proyecto Datos (OKR´s)'!$K$4
Name Semana_para_mostrar: 'Proyecto Datos'!$E$4
Name task_end: 'Proyecto Datos'!$F1
Name task_end: 'Proyecto Datos (Actual)'!$F1
Name task_end: 'Proyecto Datos (OKR´s)'!$L1
Name task_progress: 'Proyecto Datos'!$D1
Name task_progress: 'Proyecto Datos (Actual)'!$D1
Name task_progress: 'Proyecto Datos (OKR´s)'!$J1
Name task_start: 'Proyecto Datos'!$E1
Name task_start: 'Proyecto Datos (Actual)'!$E1
Name task_start: 'Proyecto Datos (OKR´s)'!$K1

Sheet Proyecto Datos (OKR´s)
A1: Cree una programación para un proyecto en esta hoja de cálculo. Escriba el título de este proyecto en la celda B1. Para obtener información sobre cómo usar esta hoja de cálculo, incluidas las instrucciones para lectores de pantalla y el nombre del autor de este libro, vea la hoja de cálculo Información. Desplácese hacia abajo por la columna A para escuchar más instrucciones. | G1: Proyecto Datos Op. Complejas
A2: Escriba el nombre de la compañía en la celda B2. | G2: IHSA S.A.
A3: Escriba el nombre del responsable del proyecto en la celda B3. Escriba la fecha de comienzo del proyecto en la celda E3. Inicio del proyecto: la etiqueta se encuentra en la celda C3. | G3: Santiago Alonso | I3: Inicio del proyecto: | K3: 45958
A4: La semana que se muestra en la celda E4 representa la semana inicial para mostrar en la programación del proyecto en la celda I4. La fecha de inicio del proyecto se considera la semana 1. Para cambiar semana que se muestra, simplemente escriba un número de semana nuevo en la celda E4. La fecha de inicio de cada semana, comenzando por la semana mostrada en la celda E4, comienza en la celda I4 y se calcula automáticamente. Hay 8 semanas representadas en esta vista desde la celda I4 hasta la celda BF4. No debería modificar estas celdas. La etiqueta de la semana para mostrar se encuentra en la celda C4. | I4: Semana para mostrar: | K4: 32 | O4: =O5 -> 46174 | V4: =V5 -> 46181 | AC4: =AC5 -> 46188 | AJ4: =AJ5 -> 46195 | AQ4: =AQ5 -> 46202 | AX4: =AX5 -> 46209 | BE4: =BE5 -> 46216 | BL4: =BL5 -> 46223
A5: Las celdas I5 a BL5 contienen el número de días de la semana representado en el bloque de celdas encima de cada celda de fecha y se calculan automáticamente. No debería modificar estas celdas. La fecha actual está rodeada con una línea roja (hex. AD3815) desde la fecha actual en la fila 5 hasta toda la columna de fechas y el fin de la programación del proyecto. | O5: =Inicio_del_proyecto-WEEKDAY(Inicio_del_proyecto,1)+2+7*(Semana_para_mostrar-1) -> 46174 | P5: =O5+1 -> 46175 | Q5: =P5+1 -> 46176 | R5: =Q5+1 -> 46177 | S5: =R5+1 -> 46178 | T5: =S5+1 -> 46179 | U5: =T5+1 -> 46180 | V5: =U5+1 -> 46181 | W5: =V5+1 -> 46182 | ... BR5: =BQ5+1 -> 46229
A6: Esta fila contiene los encabezados de la programación del proyecto posterior debajo de estos. Navegue desde la celda B6 a BL 6 para escuchar el contenido. La primera letra de cada día de la semana de la fecha encima de ese encabezado empieza en la celda I6 y continúa hasta la celda BL6. Todo el gráficos de escala de tiempo del proyecto está generados automáticamente en función de las fechas de inicio y finalización especificadas, con formatos condicionales. No modifique el contenido de las celdas en las columnas después de la columna I comenzando por la celda I7. | B6: Fecha Reunón Programada | C6: Comentarios | D6: Periodicidad | E6: Sprint | F6: Fecha | G6: TAREA | H6: Ponderación OKR | I6: ASIGNADO A | J6: PROGRESO | K6: INICIO | L6: FIN | N6: DÍAS | O6: =LEFT(TEXT(O5,"ddd"),1) -> l | P6: =LEFT(TEXT(P5,"ddd"),1) -> m | Q6: =LEFT(TEXT(Q5,"ddd"),1) -> m | R6: =LEFT(TEXT(R5,"ddd"),1) -> j | S6: =LEFT(TEXT(S5,"ddd"),1) -> v | T6: =LEFT(TEXT(T5,"ddd"),1) -> s | U6: =LEFT(TEXT(U5,"ddd"),1) -> d | V6: =LEFT(TEXT(V5,"ddd"),1) -> l | ... BR6: =LEFT(TEXT(BR5,"ddd"),1) -> d
A7: La celda B8 contiene el título de ejemplo de la Fase 1. Escriba un nuevo título en la celda B8. Escriba un nombre para asignar la fase, si se aplica para el proyecto, en la celda C8. Escriba el progreso de la fase completa, si se aplica para el proyecto, en la celda D8. Escriba las fechas de inicio y finalización de la fase completa, si se aplica para el proyecto, en las celdas E8 y F8. El gráfico de Gantt rellena automáticamente las fechas adecuadas y aplica un sombreado según el progreso especificado. Para eliminar la fase y trabajar solo con las tareas, elimine esta fila. | G7: 1- GOC: Módulo de Datos para Procesos de Certificación (Inteligencia Comercial) | H7: 0.4 | J7: =+AVERAGE(J8:J8) -> 0.2 | K7: Días Transcurridos= | L7: =TODAY()-MIN(K8)-139 -> 95
A8: La celda B9 contiene la tarea de ejemplo "Tarea 1". Escriba un nuevo nombre de tarea en la celda B9. Escriba una persona a la que asignar la tarea en la celda C9. Escriba el progreso de la tarea en la celda D9. Aparece una barra de progreso en la celda y se sombrea según el número de la celda. Por ejemplo, un progreso del 50 por ciento aplicaría sombreado a la mitad de la celda. Escriba la fecha de inicio de la tarea en la celda E9. Escriba la fecha de finalización de la tarea en la celda F9. Aparece una barra de estado con sombreado para las fechas especificadas en bloques comenzando desde la celda I9 hasta la BL9. | C8: Ok registro global Personas y Móviles (Habilitado/ Inhabilitado/ Dado de baja) + Vencimientos; Próximo: Diagrama (30/6 fecha estimada); Se avanzó con módulo diagrama. | D8: Mensual | E8: 1 | F8: 46203 | G8: Disponibilidad de información centralizada en GOC (aguarda desarrollo) | I8: Lucila Pronzato | J8: 0.2 | K8: =Inicio_del_proyecto -> 45958 | L8: =IF(F8="",WORKDAY(L7,5),F8) -> 46203 | N8: =IF(OR(ISBLANK(task_start),ISBLANK(task_end)),"",task_end-task_start+1) -> 246
A9: La celda a la derecha contiene el título de ejemplo de la Fase 2. Puede crear una nueva fase en cualquier momento en la columna B. Esta programación de proyecto no necesita fases. Para quitar la fase, basta con eliminar la fila. Para crear un bloque de fase nuevo en esta fila, escriba un nuevo título en la celda a la derecha. Para continuar agregando tareas a la fase anterior, escriba una nueva fila encima de esta y rellene los datos de la tarea como se explica en la celda A9. Actualice los detalles de la fase en la celda a la derecha como se explica en la celda A8. Continúe navegando por las celdas de la columna A para obtener más información. Si no ha agregado nuevas filas en esta hoja de cálculo, verá que se han creado automáticamente 2 bloques de fase de ejemplo adicionales en las celdas B20 y B26. En caso contrario, desplácese por las celdas de la columna A para buscar los bloques adicionales. Repita las instrucciones de las celdas A8 y A9 cuando lo necesite. | G9: 2- Cotizador de Operaciones Complejas | H9: 0.35 | J9: =+AVERAGE(J10:J19) -> 0.58 | K9: =+$K$7 -> Días Transcurridos= | L9: =TODAY()-MIN(K10:K21)-139 -> 95
D10: Quincenal | E10: 1 | F10: 46192 | G10: Crear estructura de Cotizador en base a modelo armado (migra a CLAUDE) | I10: Santiago Alonso | J10: 1 | K10: 45958 | L10: =IF(F10="",WORKDAY(L9,5),F10) -> 46192 | N10: =IF(OR(ISBLANK(task_start),ISBLANK(task_end)),"",task_end-task_start+1) -> 235
B11: Martes 16/06 | C11: Reunión con Danna Mar 16/06; dependo de tiempos de Danna. Se avanzó pero falta ya que estamos realizando una automatización linea por linea. | D11: =+$D$10 -> Quincenal | E11: 1 | F11: 46192 | G11: Automatización Archivo Sueldos FATSA + Procedimientos | I11: Santiago Alonso | J11: 0.75 | K11: 45958 | L11: =IF(F11="",WORKDAY(L10,5),F11) -> 46192 | N11: =IF(OR(ISBLANK(task_start),ISBLANK(task_end)),"",task_end-task_start+1) -> 235
D12: =+$D$10 -> Quincenal | E12: 1 | F12: 46192 | G12: Automatización Archivo Sueldos Petro + Procedimientos | I12: Santiago Alonso | J12: 0.75 | K12: 45978 | L12: =IF(F12="",WORKDAY(L11,5),F12) -> 46192 | N12: =IF(OR(ISBLANK(task_start),ISBLANK(task_end)),"",task_end-task_start+1) -> 215
C13: pedir últimos a Carlos Hernández; no llegué | D13: =+$D$10 -> Quincenal | E13: 1 | F13: 46192 | G13: Relevamiento Últimos Sueldos de referencia Monotributistas | I13: Santiago Alonso | J13: 0.5 | K13: 46345 | L13: =IF(F13="",WORKDAY(L12,5),F13) -> 46192
D14: =+$D$10 -> Quincenal | G14: Estandarización cotizaciones COMPRAS (costos x provincia) - aguardo información | I14: Santiago Alonso | J14: 0.2 | K14: 45959 | L14: =IF(F14="",WORKDAY(L13,5),F14) -> 46199 | N14: =IF(OR(ISBLANK(task_start),ISBLANK(task_end)),"",task_end-task_start+1) -> 241
C15: Avance Nico Sifuentes; sólo pendiente procedimiento. | D15: =+$D$10 -> Quincenal | E15: 1 | F15: 46192 | G15: Asociar Archivo Móviles y Tráilers (Nico Sifuentes) + procedimiento | I15: Santiago Alonso | J15: 0.95 | K15: 45992 | L15: =IF(F15="",WORKDAY(L14,5),F15) -> 46192 | N15: =IF(OR(ISBLANK(task_start),ISBLANK(task_end)),"",task_end-task_start+1) -> 201
B16: Jueves 11/06 | C16: Reunión jue 11/6 - Avance Seba Oliver; sólo pendiente procedimiento. | D16: =+$D$10 -> Quincenal | E16: 1 | F16: 46192 | G16: Asociar Archivo Masters de Medicación (Seba Oliver) + Capacitaciones + procedimiento | I16: Santiago Alonso | J16: 0.65 | K16: 45992 | L16: =IF(F16="",WORKDAY(L15,5),F16) -> 46192 | N16: =IF(OR(ISBLANK(task_start),ISBLANK(task_end)),"",task_end-task_start+1) -> 201
C17: Revisar con Fran | D17: =+$D$10 -> Quincenal | G17: Asociar Gastos de Estructura (% de incidencia) | I17: Santiago Alonso | J17: 0 | K17: =+L14+1 -> 46200 | L17: =IF(F17="",WORKDAY(MAX(L10:L16),5),F17) -> 46206 | N17: =IF(OR(ISBLANK(task_start),ISBLANK(task_end)),"",task_end-task_start+1) -> 7
D18: =+$D$10 -> Quincenal | G18: Armado de solicitudes extra x Módulos (Ej: Med. Laboral) | I18: Santiago Alonso | J18: 0 | K18: =+L12+1 -> 46193 | L18: =IF(F18="",WORKDAY(MAX(L11:L17),5),F18) -> 46213 | N18: =IF(OR(ISBLANK(task_start),ISBLANK(task_end)),"",task_end-task_start+1) -> 21
B19: Martes 09/06 | C19: mar 9/6 Reunión Torres, Huilen (Equipo IA) - Definir con Nico Vazquez. En reunión se definió que una vez finalizado el proyecto, el backend, seguridad y deploy lo continúan en IT. | D19: =+$D$10 -> Quincenal | E19: 1 | F19: 46192 | G19: Relevamiento área de IA - Repositorio (GitHub o AWS S3) + Seguridad | I19: Santiago Alonso | J19: 1 | K19: 46182 | L19: =IF(F19="",WORKDAY(MAX(L10:L18),5),F19) -> 46192 | N19: =IF(OR(ISBLANK(task_start),ISBLANK(task_end)),"",task_end-task_start+1) -> 11
D20: =+$D$10 -> Quincenal | G20: Crear Backend ETL - ver con Claude Code | I20: Santiago Alonso | J20: 0 | K20: =+L19+1 -> 46193 | L20: =IF(F20="",WORKDAY(MAX(L13:L19),5),F20) -> 46220 | N20: =IF(OR(ISBLANK(task_start),ISBLANK(task_end)),"",task_end-task_start+1) -> 28
D21: =+$D$10 -> Quincenal | G21: Deployar (URL Web) | I21: Santiago Alonso | J21: 0 | K21: =+L20+1 -> 46221 | L21: =IF(F21="",WORKDAY(MAX(L14:L20),5),F21) -> 46227 | N21: =IF(OR(ISBLANK(task_start),ISBLANK(task_end)),"",task_end-task_start+1) -> 7
A22: Bloque de título fase de ejemplo | G22: 3- Tablero BI OPEX - Real vs BO | H22: 0.25 | J22: =+AVERAGE(J23:J26) -> 0.875 | K22: =+$K$7 -> Días Transcurridos= | L22: =TODAY()-MIN(K23:K26) -> 15
A23: Las filas de la 10 a la 13 repiten el patrón de la fila 9. Repita las instrucciones de la celda A9 para todas las filas de tareas en esta hoja de cálculo. Sobrescriba los datos de ejemplo. Un ejemplo de otra fase empieza en la celda A14. Continue escribiendo tareas en las celdas de la A10 a la A13 o vaya a la celda A14 para obtener más información. | D23: Semanal | E23: 1 | F23: 46192 | G23: Armado de Procedimiento | I23: Santiago Alonso | J23: 0.9 | K23: 46182 | L23: =IF(F23="",WORKDAY(L22,5),F23) -> 46192 | N23: =IF(OR(ISBLANK(task_start),ISBLANK(task_end)),"",task_end-task_start+1) -> 11
A24: Las filas de la 10 a la 13 repiten el patrón de la fila 9. Repita las instrucciones de la celda A9 para todas las filas de tareas en esta hoja de cálculo. Sobrescriba los datos de ejemplo. Un ejemplo de otra fase empieza en la celda A14. Continue escribiendo tareas en las celdas de la A10 a la A13 o vaya a la celda A14 para obtener más información. | D24: =+$D$23 -> Semanal | E24: 1 | F24: 46192 | G24: Revisión de Gráfico en cascada: por desvío y desagregación por categorías. | I24: Santiago Alonso | J24: 0.9 | K24: 46177 | L24: =IF(F24="",WORKDAY(MAX(L23:L26),5),F24) -> 46192 | N24: =IF(OR(ISBLANK(task_start),ISBLANK(task_end)),"",task_end-task_start+1) -> 16
A25: Las filas de la 10 a la 13 repiten el patrón de la fila 9. Repita las instrucciones de la celda A9 para todas las filas de tareas en esta hoja de cálculo. Sobrescriba los datos de ejemplo. Un ejemplo de otra fase empieza en la celda A14. Continue escribiendo tareas en las celdas de la A10 a la A13 o vaya a la celda A14 para obtener más información. | D25: =+$D$23 -> Semanal | E25: 1 | F25: 46185 | G25: Revisión de viabilidad de incorporación datos Redash (input ZReal con clasificaciones automaticas por CECO - Directas e Indirectas) | I25: Santiago Alonso | J25: 0.9 | K25: 46177 | L25: =IF(F25="",WORKDAY(MAX($L$23:$L$26),5),F25) -> 46185 | N25: =IF(OR(ISBLANK(task_start),ISBLANK(task_end)),"",task_end-task_start+1) -> 9
A26: Las filas de la 10 a la 13 repiten el patrón de la fila 9. Repita las instrucciones de la celda A9 para todas las filas de tareas en esta hoja de cálculo. Sobrescriba los datos de ejemplo. Un ejemplo de otra fase empieza en la celda A14. Continue escribiendo tareas en las celdas de la A10 a la A13 o vaya a la celda A14 para obtener más información. | G26: Revisión y Publicación de Tablero | I26: Santiago Alonso | J26: 0.8 | K26: 46185 | L26: =IF(F26="",WORKDAY(MAX($L$23:$L$25),5),F26) -> 46199 | N26: =IF(OR(ISBLANK(task_start),ISBLANK(task_end)),"",task_end-task_start+1) -> 15
A27: Bloque de título fase de ejemplo | G27: 4- Tablero BI DEUDA | J27: =+AVERAGE(J39:J49) -> 0.37575758 | K27: =+$K$7 -> Días Transcurridos= | L27: =TODAY()-MIN(K28:K35)-139 -> 61
A28: Las filas de la 10 a la 13 repiten el patrón de la fila 9. Repita las instrucciones de la celda A9 para todas las filas de tareas en esta hoja de cálculo. Sobrescriba los datos de ejemplo. Un ejemplo de otra fase empieza en la celda A14. Continue escribiendo tareas en las celdas de la A10 a la A13 o vaya a la celda A14 para obtener más información. | D28: Semanal | E28: 1 | F28: 46185 | G28: Procedimiento | I28: Santiago Alonso | J28: 0.9 | K28: 46181 | L28: =IF(F28="",WORKDAY(L27,5),F28) -> 46185 | N28: =IF(OR(ISBLANK(task_start),ISBLANK(task_end)),"",task_end-task_start+1) -> 5
A29: Las filas de la 10 a la 13 repiten el patrón de la fila 9. Repita las instrucciones de la celda A9 para todas las filas de tareas en esta hoja de cálculo. Sobrescriba los datos de ejemplo. Un ejemplo de otra fase empieza en la celda A14. Continue escribiendo tareas en las celdas de la A10 a la A13 o vaya a la celda A14 para obtener más información. | D29: =+$D$28 -> Semanal | E29: 1 | F29: 46185 | G29: Aging - desde SharePoint | I29: Santiago Alonso | J29: 0.9 | K29: 45992 | L29: =IF(F29="",WORKDAY(L28,5),F29) -> 46185 | N29: =IF(OR(ISBLANK(task_start),ISBLANK(task_end)),"",task_end-task_start+1) -> 194
A30: Las filas de la 10 a la 13 repiten el patrón de la fila 9. Repita las instrucciones de la celda A9 para todas las filas de tareas en esta hoja de cálculo. Sobrescriba los datos de ejemplo. Un ejemplo de otra fase empieza en la celda A14. Continue escribiendo tareas en las celdas de la A10 a la A13 o vaya a la celda A14 para obtener más información. | D30: =+$D$28 -> Semanal | E30: 1 | F30: 46185 | G30: Dias en Calle - desde SharePoint | I30: Santiago Alonso | J30: 0.9 | K30: 45992 | L30: =IF(F30="",WORKDAY(L29,5),F30) -> 46185 | N30: =IF(OR(ISBLANK(task_start),ISBLANK(task_end)),"",task_end-task_start+1) -> 194
A31: Las filas de la 10 a la 13 repiten el patrón de la fila 9. Repita las instrucciones de la celda A9 para todas las filas de tareas en esta hoja de cálculo. Sobrescriba los datos de ejemplo. Un ejemplo de otra fase empieza en la celda A14. Continue escribiendo tareas en las celdas de la A10 a la A13 o vaya a la celda A14 para obtener más información. | D31: =+$D$28 -> Semanal | E31: 1 | F31: 46185 | G31: Input de datos desde Provisión mensual | I31: Santiago Alonso | J31: 0.9 | K31: 46023 | L31: =IF(F31="",WORKDAY(L30,5),F31) -> 46185 | N31: =IF(OR(ISBLANK(task_start),ISBLANK(task_end)),"",task_end-task_start+1) -> 163
D32: =+$D$28 -> Semanal | G32: Analizar viabilidad de input Redash: Importe Provisionado (Datalake --> Clik Sense) | I32: Santiago Alonso | J32: 0.6 | K32: 46188 | L32: =IF(F32="",WORKDAY(L30,5),F32) -> 46192 | N32: =IF(OR(ISBLANK(task_start),ISBLANK(task_end)),"",task_end-task_start+1) -> 5
D33: =+$D$28 -> Semanal | G33: Analizar viabilidad de input Redash: Importe Facturado (Datalake --> Clik Sense "Venta Bruta") | I33: Santiago Alonso | J33: 0.6 | K33: 46192 | L33: =IF(F33="",WORKDAY(L32,5),F33) -> 46199 | N33: =IF(OR(ISBLANK(task_start),ISBLANK(task_end)),"",task_end-task_start+1) -> 8
D34: =+$D$28 -> Semanal | G34: Creación detalle deuda Vista - Replicar Excel Deuda | I34: Santiago Alonso | J34: 0.5 | K34: 46188 | L34: =IF(F34="",WORKDAY(L32,5),F34) -> 46199 | N34: =IF(OR(ISBLANK(task_start),ISBLANK(task_end)),"",task_end-task_start+1) -> 12
D35: =+$D$28 -> Semanal | G35: Creación detalle deuda YPF (ídem Excel) | I35: Santiago Alonso | J35: 0.5 | K35: 46192 | L35: =IF(F35="",WORKDAY(L33,5),F35) -> 46206 | N35: =IF(OR(ISBLANK(task_start),ISBLANK(task_end)),"",task_end-task_start+1) -> 15
A36: Bloque de título fase de ejemplo | G36: 5- Tablero Control General - Op. Complejas | J36: =+AVERAGE(J46:J56) -> 0.16666667 | K36: =+$K$7 -> Días Transcurridos= | L36: =+TODAY()-MIN($K$37:$K$47)-139 -> 61
C37: No llegué por nuevas solicitudes: Tablero Forecast + Reuniones por tarifas YPF + Contratos SF | D37: Semanal | E37: 1 | F37: 46185 | G37: Planilla Activos Unificados - Estandarizar + Procedimiento | I37: Santiago Alonso | J37: 0.2 | K37: 45992 | L37: =IF(F37="",WORKDAY(L36,5),F37) -> 46185 | N37: =IF(OR(ISBLANK(task_start),ISBLANK(task_end)),"",task_end-task_start+1) -> 194
A38: Las filas de la 10 a la 13 repiten el patrón de la fila 9. Repita las instrucciones de la celda A9 para todas las filas de tareas en esta hoja de cálculo. Sobrescriba los datos de ejemplo. Un ejemplo de otra fase empieza en la celda A14. Continue escribiendo tareas en las celdas de la A10 a la A13 o vaya a la celda A14 para obtener más información. | D38: =+$D$37 -> Semanal | E38: 1 | F38: 46185 | G38: Planilla DTM Estandarizada+ Procedimiento | I38: Santiago Alonso | J38: 0.9 | K38: 46023 | L38: =IF(F38="",WORKDAY(L37,5),F38) -> 46185 | N38: =IF(OR(ISBLANK(task_start),ISBLANK(task_end)),"",task_end-task_start+1) -> 163
D39: =+$D$37 -> Semanal | E39: 1 | F39: 46185 | G39: Planilla Aeroevaciaciones + Procedimiento | I39: Santiago Alonso | J39: 0.95 | K39: 45992 | L39: =IF(F39="",WORKDAY(L38,5),F39) -> 46185 | N39: =IF(OR(ISBLANK(task_start),ISBLANK(task_end)),"",task_end-task_start+1) -> 194
D40: =+$D$37 -> Semanal | E40: 1 | F40: 46185 | G40: Resumen Clientes Petróleo | I40: Santiago Alonso | J40: 0.7 | K40: 46357 | L40: =IF(F40="",WORKDAY(L39,5),F40) -> 46185 | N40: =IF(OR(ISBLANK(task_start),ISBLANK(task_end)),"",task_end-task_start+1) -> -171
D41: =+$D$37 -> Semanal | E41: 1 | F41: 46185 | G41: Resumen Clientes Minería | I41: Santiago Alonso | J41: 0.5 | K41: 46188 | L41: =IF(F41="",WORKDAY(L40,5),F41) -> 46185 | N41: =IF(OR(ISBLANK(task_start),ISBLANK(task_end)),"",task_end-task_start+1) -> -2
D42: =+$D$37 -> Semanal | E42: 1 | F42: 46185 | G42: Resumen Clientes Op. Dedicadas | I42: Santiago Alonso | J42: 0.4 | K42: 46188 | L42: =IF(F42="",WORKDAY(L41,5),F42) -> 46185 | N42: =IF(OR(ISBLANK(task_start),ISBLANK(task_end)),"",task_end-task_start+1) -> -2
D43: =+$D$37 -> Semanal | G43: Locaciones Geográficas Pozos Petro (ver datos Secretaria de Energía) | I43: Santiago Alonso | J43: 0.1 | K43: 46188 | L43: =IF(F43="",WORKDAY(L42,5),F43) -> 46192
D44: =+$D$37 -> Semanal | G44: Locaciones Geográficas Minería | I44: Santiago Alonso | J44: 0 | K44: 46195 | L44: =IF(F44="",WORKDAY(L43,5),F44) -> 46199
D45: =+$D$37 -> Semanal | G45: Locaciones Geográficas Op. Dedicadas | I45: Santiago Alonso | J45: 0 | K45: 46202 | L45: =IF(F45="",WORKDAY(L44,5),F45) -> 46206
D46: =+$D$37 -> Semanal | E46: 1 | F46: 46185 | G46: Detalle Responsables (Comerciales + Analistas) | I46: Santiago Alonso | J46: 0.5 | K46: =+L45+1 -> 46207 | L46: =IF(F46="",WORKDAY(L45,5),F46) -> 46185
D47: =+$D$37 -> Semanal | E47: 1 | F47: 46185 | G47: Armado de Dashboard + Diseño | I47: Santiago Alonso | J47: 0.5 | K47: =+L46+1 -> 46186 | L47: =IF(F47="",WORKDAY(L46,5),F47) -> 46185 | N47: =IF(OR(ISBLANK(task_start),ISBLANK(task_end)),"",task_end-task_start+1) -> 0
A48: Bloque de título fase de ejemplo | G48: 6- Automatización de procesos: certificación, provisión,polinómicas | H48: 0.25 | J48: =+AVERAGE(J49:J51) -> 0.13333333 | K48: =+$K$7 -> Días Transcurridos= | L48: =+TODAY()-MIN($K$49:$K$51)-139 -> 95
D49: Mensual | G49: Polinómicas y tarifario automático | I49: Santiago Alonso | J49: 0.35 | K49: 45958 | L49: 46213 | N49: =IF(OR(ISBLANK(task_start),ISBLANK(task_end)),"",task_end-task_start+1) -> 256
D50: =+$D$49 -> Mensual | G50: Certificados automáticos (ver si utilizar scripts) | I50: Santiago Alonso | J50: 0.05 | K50: 46209 | L50: =IF(F50="",WORKDAY(L49,5),F50) -> 46220 | N50: =IF(OR(ISBLANK(task_start),ISBLANK(task_end)),"",task_end-task_start+1) -> 12
D51: =+$D$49 -> Mensual | G51: Provisión Automática | I51: Santiago Alonso/ Julio Tinelli | J51: 0 | K51: 46216 | L51: =IF(F51="",WORKDAY(L50,5),F51) -> 46227 | N51: =IF(OR(ISBLANK(task_start),ISBLANK(task_end)),"",task_end-task_start+1) -> 12
A52: Bloque de título fase de ejemplo | G52: 7- Incorporación de Operaciones Complejas en sistemas de la compañía: Salesforce, SAP, etc. | H52: 0.1 | J52: =+AVERAGE(J53:J55) -> 0.033333333 | K52: =+$K$7 -> Días Transcurridos= | L52: =+TODAY()-MIN($K$53:$K$55)-139 -> 95
D53: Mensual | G53: Eliminar contratos obsoletos | I53: Santiago Alonso/ Danna Basso/ Lucía Paciello | J53: 0.1 | K53: 45958 | L53: 46213 | N53: =IF(OR(ISBLANK(task_start),ISBLANK(task_end)),"",task_end-task_start+1) -> 256
D54: =+$D$53 -> Mensual | G54: Estandarizar materíales de contratos - ver si se puede realizarmasivo (Matias Viera - SF) | I54: Santiago Alonso/ Danna Basso/ Lucía Paciello | J54: 0 | K54: 46216 | L54: =IF(F54="",WORKDAY(L53,5),F54) -> 46220 | N54: =IF(OR(ISBLANK(task_start),ISBLANK(task_end)),"",task_end-task_start+1) -> 5
D55: =+$D$53 -> Mensual | G55: Relevar conveniencia de creación de Boom´s para materiales que hacen alusión a US | I55: Santiago Alonso/ Danna Basso/ Lucía Paciello | J55: 0 | K55: 46223 | L55: =IF(F55="",WORKDAY(L54,5),F55) -> 46227 | N55: =IF(OR(ISBLANK(task_start),ISBLANK(task_end)),"",task_end-task_start+1) -> 5
H56: =+SUBTOTAL(9,H7:H55) -> 1.35
G79: Resumen Clientes Op. Dedicadas
G80: Armado de Dashboard

Sheet Proyecto Datos (Actual)
A1: Cree una programación para un proyecto en esta hoja de cálculo. Escriba el título de este proyecto en la celda B1. Para obtener información sobre cómo usar esta hoja de cálculo, incluidas las instrucciones para lectores de pantalla y el nombre del autor de este libro, vea la hoja de cálculo Información. Desplácese hacia abajo por la columna A para escuchar más instrucciones. | B1: Proyecto Datos Op. Complejas
A2: Escriba el nombre de la compañía en la celda B2. | B2: IHSA S.A.
A3: Escriba el nombre del responsable del proyecto en la celda B3. Escriba la fecha de comienzo del proyecto en la celda E3. Inicio del proyecto: la etiqueta se encuentra en la celda C3. | B3: Santiago Alonso | C3: Inicio del proyecto: | E3: 45958
A4: La semana que se muestra en la celda E4 representa la semana inicial para mostrar en la programación del proyecto en la celda I4. La fecha de inicio del proyecto se considera la semana 1. Para cambiar semana que se muestra, simplemente escriba un número de semana nuevo en la celda E4. La fecha de inicio de cada semana, comenzando por la semana mostrada en la celda E4, comienza en la celda I4 y se calcula automáticamente. Hay 8 semanas representadas en esta vista desde la celda I4 hasta la celda BF4. No debería modificar estas celdas. La etiqueta de la semana para mostrar se encuentra en la celda C4. | C4: Semana para mostrar: | E4: 25 | I4: =I5 -> 46125 | P4: =P5 -> 46132 | W4: =W5 -> 46139 | AD4: =AD5 -> 46146 | AK4: =AK5 -> 46153 | AR4: =AR5 -> 46160 | AY4: =AY5 -> 46167 | BF4: =BF5 -> 46174
A5: Las celdas I5 a BL5 contienen el número de días de la semana representado en el bloque de celdas encima de cada celda de fecha y se calculan automáticamente. No debería modificar estas celdas. La fecha actual está rodeada con una línea roja (hex. AD3815) desde la fecha actual en la fila 5 hasta toda la columna de fechas y el fin de la programación del proyecto. | I5: =Inicio_del_proyecto-WEEKDAY(Inicio_del_proyecto,1)+2+7*(Semana_para_mostrar-1) -> 46125 | J5: =I5+1 -> 46126 | K5: =J5+1 -> 46127 | L5: =K5+1 -> 46128 | M5: =L5+1 -> 46129 | N5: =M5+1 -> 46130 | O5: =N5+1 -> 46131 | P5: =O5+1 -> 46132 | Q5: =P5+1 -> 46133 | ... BL5: =BK5+1 -> 46180
A6: Esta fila contiene los encabezados de la programación del proyecto posterior debajo de estos. Navegue desde la celda B6 a BL 6 para escuchar el contenido. La primera letra de cada día de la semana de la fecha encima de ese encabezado empieza en la celda I6 y continúa hasta la celda BL6. Todo el gráficos de escala de tiempo del proyecto está generados automáticamente en función de las fechas de inicio y finalización especificadas, con formatos condicionales. No modifique el contenido de las celdas en las columnas después de la columna I comenzando por la celda I7. | B6: TAREA | C6: ASIGNADO A | D6: PROGRESO | E6: INICIO | F6: FIN | H6: DÍAS | I6: =LEFT(TEXT(I5,"ddd"),1) -> l | J6: =LEFT(TEXT(J5,"ddd"),1) -> m | K6: =LEFT(TEXT(K5,"ddd"),1) -> m | L6: =LEFT(TEXT(L5,"ddd"),1) -> j | M6: =LEFT(TEXT(M5,"ddd"),1) -> v | N6: =LEFT(TEXT(N5,"ddd"),1) -> s | O6: =LEFT(TEXT(O5,"ddd"),1) -> d | P6: =LEFT(TEXT(P5,"ddd"),1) -> l | ... BL6: =LEFT(TEXT(BL5,"ddd"),1) -> d
A7: No elimine esta fila. Esta fila está oculta para conservar una fórmula que se usa para resaltar el día actual dentro de la programación del proyecto. | H7: =IF(OR(ISBLANK(task_start),ISBLANK(task_end)),"",task_end-task_start+1)
A8: La celda B8 contiene el título de ejemplo de la Fase 1. Escriba un nuevo título en la celda B8. Escriba un nombre para asignar la fase, si se aplica para el proyecto, en la celda C8. Escriba el progreso de la fase completa, si se aplica para el proyecto, en la celda D8. Escriba las fechas de inicio y finalización de la fase completa, si se aplica para el proyecto, en las celdas E8 y F8. El gráfico de Gantt rellena automáticamente las fechas adecuadas y aplica un sombreado según el progreso especificado. Para eliminar la fase y trabajar solo con las tareas, elimine esta fila. | B8: 1- Automatización de Tareas | D8: =+AVERAGE(D9:D15) -> 0.26428571 | F8: =+F15-E11+1 -> 212
A9: La celda B9 contiene la tarea de ejemplo "Tarea 1". Escriba un nuevo nombre de tarea en la celda B9. Escriba una persona a la que asignar la tarea en la celda C9. Escriba el progreso de la tarea en la celda D9. Aparece una barra de progreso en la celda y se sombrea según el número de la celda. Por ejemplo, un progreso del 50 por ciento aplicaría sombreado a la mitad de la celda. Escriba la fecha de inicio de la tarea en la celda E9. Escriba la fecha de finalización de la tarea en la celda F9. Aparece una barra de estado con sombreado para las fechas especificadas en bloques comenzando desde la celda I9 hasta la BL9. | B9: Carpeta almacenamiento en Sharepoint p/ Datalake | C9: Julio Tinelli | D9: 0.9 | E9: =Inicio_del_proyecto -> 45958 | F9: 46173 | H9: =IF(OR(ISBLANK(task_start),ISBLANK(task_end)),"",task_end-task_start+1) -> 216
A10: La celda B9 contiene la tarea de ejemplo "Tarea 1". Escriba un nuevo nombre de tarea en la celda B9. Escriba una persona a la que asignar la tarea en la celda C9. Escriba el progreso de la tarea en la celda D9. Aparece una barra de progreso en la celda y se sombrea según el número de la celda. Por ejemplo, un progreso del 50 por ciento aplicaría sombreado a la mitad de la celda. Escriba la fecha de inicio de la tarea en la celda E9. Escriba la fecha de finalización de la tarea en la celda F9. Aparece una barra de estado con sombreado para las fechas especificadas en bloques comenzando desde la celda I9 hasta la BL9. | B10: Polinómicas + Tarifario + Ev. Parámetros Precios | C10: Santiago Alonso | D10: 0.7 | E10: 45962 | F10: 46203 | H10: =IF(OR(ISBLANK(task_start),ISBLANK(task_end)),"",task_end-task_start+1) -> 242
B11: Obtener información detallada de DTM x Service Desk | C11: Santiago Alonso | D11: 0.25 | E11: 46023 | F11: 46203
B12: Días en Calle Calculado | C12: Santiago Alonso | D12: 0 | E12: =+F11+1 -> 46204 | F12: 46295 | H12: =IF(OR(ISBLANK(task_start),ISBLANK(task_end)),"",task_end-task_start+1) -> 92
B13: Aging Calculado | C13: Santiago Alonso | D13: 0 | E13: =+F12+1 -> 46296 | F13: =+WORKDAY(E13,4) -> 46302 | H13: =IF(OR(ISBLANK(task_start),ISBLANK(task_end)),"",task_end-task_start+1) -> 7
B14: Automatización de Provisión | C14: Santiago Alonso | D14: 0 | E14: =+F13+1 -> 46303 | F14: =+WORKDAY(E14,7) -> 46314
B15: Automatización de Certificaciones Mensuales | C15: Santiago Alonso | D15: 0 | E15: 46160 | F15: 46234
A16: La celda a la derecha contiene el título de ejemplo de la Fase 2. Puede crear una nueva fase en cualquier momento en la columna B. Esta programación de proyecto no necesita fases. Para quitar la fase, basta con eliminar la fila. Para crear un bloque de fase nuevo en esta fila, escriba un nuevo título en la celda a la derecha. Para continuar agregando tareas a la fase anterior, escriba una nueva fila encima de esta y rellene los datos de la tarea como se explica en la celda A9. Actualice los detalles de la fase en la celda a la derecha como se explica en la celda A8. Continúe navegando por las celdas de la columna A para obtener más información. Si no ha agregado nuevas filas en esta hoja de cálculo, verá que se han creado automáticamente 2 bloques de fase de ejemplo adicionales en las celdas B20 y B26. En caso contrario, desplácese por las celdas de la columna A para buscar los bloques adicionales. Repita las instrucciones de las celdas A8 y A9 cuando lo necesite. | B16: 2- Cotizador Automático (Neuquén) | D16: =+AVERAGE(D17:D24) -> 0.41875 | F16: =+F24-E17+1 -> 36
B17: Crear estructura de Cotizador en base a modelo armado (migra a CLAUDE) | C17: Santiago Alonso | D17: 0.9 | E17: 45958 | F17: 46173 | H17: =IF(OR(ISBLANK(task_start),ISBLANK(task_end)),"",task_end-task_start+1) -> 216
B18: Automatización Archivo Sueldos FATSA (PENDIENTE REVISIÓN GENERAL) | C18: Santiago Alonso | D18: 0.85 | E18: 45958 | F18: 45991 | H18: =IF(OR(ISBLANK(task_start),ISBLANK(task_end)),"",task_end-task_start+1) -> 34
B19: Automatización Archivo Sueldos Petro (PENDIENTE REVISIÓN GENERAL) | C19: Santiago Alonso | D19: 0.9 | E19: 45978 | F19: =+WORKDAY(E19,2) -> 45980 | H19: =IF(OR(ISBLANK(task_start),ISBLANK(task_end)),"",task_end-task_start+1) -> 3
B20: Estandarización cotizaciones COMPRAS (costos x provincia) | C20: Santiago Alonso | D20: 0.2 | E20: 45959 | F20: =+WORKDAY(E20,10) -> 45973 | H20: =IF(OR(ISBLANK(task_start),ISBLANK(task_end)),"",task_end-task_start+1) -> 15
B21: Asociar Archivo Móviles y Tráilers (Nico Sifuentes) | C21: Santiago Alonso | D21: 0.5 | E21: 45992 | F21: 46000 | H21: =IF(OR(ISBLANK(task_start),ISBLANK(task_end)),"",task_end-task_start+1) -> 9
B22: Asociar Gastos de Estructura (% de incidencia) --> Pedir a Fran | C22: Santiago Alonso | D22: 0 | E22: =+F20+1 -> 45974 | F22: =+WORKDAY(E22,4) -> 45980 | H22: =IF(OR(ISBLANK(task_start),ISBLANK(task_end)),"",task_end-task_start+1) -> 7
B23: Armado de solicitudes extra x Módulos (Ej: Med. Laboral) | C23: Santiago Alonso | D23: 0 | E23: =+F19+1 -> 45981 | F23: =+WORKDAY(E23,3) -> 45986 | H23: =IF(OR(ISBLANK(task_start),ISBLANK(task_end)),"",task_end-task_start+1) -> 6
B24: Diseño de Dashboard | C24: Santiago Alonso | D24: 0 | E24: =+F23+1 -> 45987 | F24: =+WORKDAY(E24,4) -> 45993 | H24: =IF(OR(ISBLANK(task_start),ISBLANK(task_end)),"",task_end-task_start+1) -> 7
A25: Bloque de título fase de ejemplo | B25: 3- Planilla de Control | D25: =+AVERAGE(D26:D41) -> 0.394375 | F25: =+F41-E26+1 -> 74
B26: Planilla Activos Unificados (Nico Sifuentes) - Estandarizar | C26: Santiago Alonso | D26: 0 | E26: 45962 | F26: =+WORKDAY(E26,4) -> 45967 | H26: =IF(OR(ISBLANK(task_start),ISBLANK(task_end)),"",task_end-task_start+1) -> 6
A27: Las filas de la 10 a la 13 repiten el patrón de la fila 9. Repita las instrucciones de la celda A9 para todas las filas de tareas en esta hoja de cálculo. Sobrescriba los datos de ejemplo. Un ejemplo de otra fase empieza en la celda A14. Continue escribiendo tareas en las celdas de la A10 a la A13 o vaya a la celda A14 para obtener más información. | B27: Planilla DTM Estandarizada | C27: Santiago Alonso | D27: 0.9 | E27: =+F26 -> 45967 | F27: =+WORKDAY(E27,0) -> 45967 | H27: =IF(OR(ISBLANK(task_start),ISBLANK(task_end)),"",task_end-task_start+1) -> 1
B28: Planilla Aeroevaciaciones | C28: Santiago Alonso | D28: 0.9 | E28: =+F27+0 -> 45967 | F28: =+WORKDAY(E28,0) -> 45967 | H28: =IF(OR(ISBLANK(task_start),ISBLANK(task_end)),"",task_end-task_start+1) -> 1
B29: Resumen Clientes Petróleo | C29: Santiago Alonso | D29: 0.7 | E29: =+F26+1 -> 45968 | F29: =+WORKDAY(E29,3) -> 45973 | H29: =IF(OR(ISBLANK(task_start),ISBLANK(task_end)),"",task_end-task_start+1) -> 6
B30: Resumen Clientes Minería | C30: Santiago Alonso | D30: 0.2 | E30: =+F29+1 -> 45974 | F30: =+WORKDAY(E30,3) -> 45979 | H30: =IF(OR(ISBLANK(task_start),ISBLANK(task_end)),"",task_end-task_start+1) -> 6
B31: Resumen Clientes Op. Dedicadas | C31: Santiago Alonso | D31: 0.01 | E31: =+F30+1 -> 45980 | F31: =+WORKDAY(E31,1) -> 45981 | H31: =IF(OR(ISBLANK(task_start),ISBLANK(task_end)),"",task_end-task_start+1) -> 2
B32: Días en Calle (Sharepoint --> Excel) | C32: Santiago Alonso | D32: 0.5 | E32: =+F31+1 -> 45982 | F32: =+WORKDAY(E32,3) -> 45987 | H32: =IF(OR(ISBLANK(task_start),ISBLANK(task_end)),"",task_end-task_start+1) -> 6
B33: Aging (Sharepoint --> Excel) | C33: Santiago Alonso | D33: 0.5 | E33: =+F32+1 -> 45988 | F33: =+WORKDAY(E33,3) -> 45993 | H33: =IF(OR(ISBLANK(task_start),ISBLANK(task_end)),"",task_end-task_start+1) -> 6
B34: Importe Provisionado (Datalake --> Clik Sense "Venta Bruta") | C34: Santiago Alonso | D34: 0.5 | E34: =+F33+1 -> 45994 | F34: =+WORKDAY(E34,3) -> 45999 | H34: =IF(OR(ISBLANK(task_start),ISBLANK(task_end)),"",task_end-task_start+1) -> 6
B35: Importe Facturado (Datalake --> Clik Sense "Venta Bruta") | C35: Santiago Alonso | D35: 0.5 | E35: =+F34+1 -> 46000 | F35: =+WORKDAY(E35,3) -> 46003 | H35: =IF(OR(ISBLANK(task_start),ISBLANK(task_end)),"",task_end-task_start+1) -> 4
B36: Importe Pendiente Fc (Provisión) | C36: Santiago Alonso | D36: 0.8 | E36: =+F35+1 -> 46004 | F36: =+WORKDAY(E36,2) -> 46007 | H36: =IF(OR(ISBLANK(task_start),ISBLANK(task_end)),"",task_end-task_start+1) -> 4
B37: Locaciones Geográficas Pozos Petro (ver datos Secretaria de Energía) | C37: Santiago Alonso | D37: 0.1 | E37: =+F36+1 -> 46008 | F37: =+WORKDAY(E37,3) -> 46013
B38: Locaciones Geográficas Minería | C38: Santiago Alonso | D38: 0 | E38: =+F37+1 -> 46014 | F38: =+WORKDAY(E38,3) -> 46017
B39: Locaciones Geográficas Op. Dedicadas | C39: Santiago Alonso | D39: 0 | E39: =+F38+1 -> 46018 | F39: =+WORKDAY(E39,3) -> 46022
B40: Detalle Responsables (Comerciales + Analistas) | C40: Santiago Alonso | D40: 0.5 | E40: =+F39+1 -> 46023 | F40: =+WORKDAY(E40,1) -> 46024
B41: Armado de Dashboard + Diseño | C41: Santiago Alonso | D41: 0.2 | E41: =+F40+1 -> 46025 | F41: =+WORKDAY(E41,7) -> 46035 | H41: =IF(OR(ISBLANK(task_start),ISBLANK(task_end)),"",task_end-task_start+1) -> 11
A42: Bloque de título fase de ejemplo | B42: 4- Contratos Salesforce | D42: =+AVERAGE(D43:D45) -> 0.033333333 | F42: =+F45-E43+1 -> 38
B43: Eliminar contratos obsoletos | C43: Luis Barrozo/ Santiago Alonso | D43: 0.1 | E43: 45958 | F43: =+WORKDAY(E43,5) -> 45965 | H43: =IF(OR(ISBLANK(task_start),ISBLANK(task_end)),"",task_end-task_start+1) -> 8
B44: Estandarizar materíales de contratos | C44: Luis Barrozo/ Santiago Alonso | D44: 0 | E44: =+F43+1 -> 45966 | F44: =+WORKDAY(E44,10) -> 45980 | H44: =IF(OR(ISBLANK(task_start),ISBLANK(task_end)),"",task_end-task_start+1) -> 15
B45: Crear Boom´s para materiales que hacen alusión a US | C45: Luis Barrozo/ Santiago Alonso | D45: 0 | E45: =+F44+1 -> 45981 | F45: =+WORKDAY(E45,10) -> 45995 | H45: =IF(OR(ISBLANK(task_start),ISBLANK(task_end)),"",task_end-task_start+1) -> 15
B69: Resumen Clientes Op. Dedicadas
B70: Armado de Dashboard

Sheet Proyecto Datos
A1: Cree una programación para un proyecto en esta hoja de cálculo. Escriba el título de este proyecto en la celda B1. Para obtener información sobre cómo usar esta hoja de cálculo, incluidas las instrucciones para lectores de pantalla y el nombre del autor de este libro, vea la hoja de cálculo Información. Desplácese hacia abajo por la columna A para escuchar más instrucciones. | B1: Proyecto Datos Op. Complejas
A2: Escriba el nombre de la compañía en la celda B2. | B2: IHSA S.A.
A3: Escriba el nombre del responsable del proyecto en la celda B3. Escriba la fecha de comienzo del proyecto en la celda E3. Inicio del proyecto: la etiqueta se encuentra en la celda C3. | B3: Santiago Alonso | C3: Inicio del proyecto: | E3: 45958
A4: La semana que se muestra en la celda E4 representa la semana inicial para mostrar en la programación del proyecto en la celda I4. La fecha de inicio del proyecto se considera la semana 1. Para cambiar semana que se muestra, simplemente escriba un número de semana nuevo en la celda E4. La fecha de inicio de cada semana, comenzando por la semana mostrada en la celda E4, comienza en la celda I4 y se calcula automáticamente. Hay 8 semanas representadas en esta vista desde la celda I4 hasta la celda BF4. No debería modificar estas celdas. La etiqueta de la semana para mostrar se encuentra en la celda C4. | C4: Semana para mostrar: | E4: 1 | I4: =I5 -> 45957 | P4: =P5 -> 45964 | W4: =W5 -> 45971 | AD4: =AD5 -> 45978 | AK4: =AK5 -> 45985 | AR4: =AR5 -> 45992 | AY4: =AY5 -> 45999 | BF4: =BF5 -> 46006
A5: Las celdas I5 a BL5 contienen el número de días de la semana representado en el bloque de celdas encima de cada celda de fecha y se calculan automáticamente. No debería modificar estas celdas. La fecha actual está rodeada con una línea roja (hex. AD3815) desde la fecha actual en la fila 5 hasta toda la columna de fechas y el fin de la programación del proyecto. | I5: =Inicio_del_proyecto-WEEKDAY(Inicio_del_proyecto,1)+2+7*(Semana_para_mostrar-1) -> 45957 | J5: =I5+1 -> 45958 | K5: =J5+1 -> 45959 | L5: =K5+1 -> 45960 | M5: =L5+1 -> 45961 | N5: =M5+1 -> 45962 | O5: =N5+1 -> 45963 | P5: =O5+1 -> 45964 | Q5: =P5+1 -> 45965 | ... BL5: =BK5+1 -> 46012
A6: Esta fila contiene los encabezados de la programación del proyecto posterior debajo de estos. Navegue desde la celda B6 a BL 6 para escuchar el contenido. La primera letra de cada día de la semana de la fecha encima de ese encabezado empieza en la celda I6 y continúa hasta la celda BL6. Todo el gráficos de escala de tiempo del proyecto está generados automáticamente en función de las fechas de inicio y finalización especificadas, con formatos condicionales. No modifique el contenido de las celdas en las columnas después de la columna I comenzando por la celda I7. | B6: TAREA | C6: ASIGNADO A | D6: PROGRESO | E6: INICIO | F6: FIN | H6: DÍAS | I6: =LEFT(TEXT(I5,"ddd"),1) -> l | J6: =LEFT(TEXT(J5,"ddd"),1) -> m | K6: =LEFT(TEXT(K5,"ddd"),1) -> m | L6: =LEFT(TEXT(L5,"ddd"),1) -> j | M6: =LEFT(TEXT(M5,"ddd"),1) -> v | N6: =LEFT(TEXT(N5,"ddd"),1) -> s | O6: =LEFT(TEXT(O5,"ddd"),1) -> d | P6: =LEFT(TEXT(P5,"ddd"),1) -> l | ... BL6: =LEFT(TEXT(BL5,"ddd"),1) -> d
A7: No elimine esta fila. Esta fila está oculta para conservar una fórmula que se usa para resaltar el día actual dentro de la programación del proyecto. | H7: =IF(OR(ISBLANK(task_start),ISBLANK(task_end)),"",task_end-task_start+1)
A8: La celda B8 contiene el título de ejemplo de la Fase 1. Escriba un nuevo título en la celda B8. Escriba un nombre para asignar la fase, si se aplica para el proyecto, en la celda C8. Escriba el progreso de la fase completa, si se aplica para el proyecto, en la celda D8. Escriba las fechas de inicio y finalización de la fase completa, si se aplica para el proyecto, en las celdas E8 y F8. El gráfico de Gantt rellena automáticamente las fechas adecuadas y aplica un sombreado según el progreso especificado. Para eliminar la fase y trabajar solo con las tareas, elimine esta fila. | B8: 1- Automatización de Tareas | D8: =+AVERAGE(D9:D15) -> 0.16428571 | F8: =+F15-E11+1 -> 48
A9: La celda B9 contiene la tarea de ejemplo "Tarea 1". Escriba un nuevo nombre de tarea en la celda B9. Escriba una persona a la que asignar la tarea en la celda C9. Escriba el progreso de la tarea en la celda D9. Aparece una barra de progreso en la celda y se sombrea según el número de la celda. Por ejemplo, un progreso del 50 por ciento aplicaría sombreado a la mitad de la celda. Escriba la fecha de inicio de la tarea en la celda E9. Escriba la fecha de finalización de la tarea en la celda F9. Aparece una barra de estado con sombreado para las fechas especificadas en bloques comenzando desde la celda I9 hasta la BL9. | B9: Carpeta almacenamiento en Sharepoint p/ Datalake | C9: Julio Tinelli | D9: 0.2 | E9: =Inicio_del_proyecto -> 45958 | F9: =+WORKDAY(E9,10) -> 45972 | H9: =IF(OR(ISBLANK(task_start),ISBLANK(task_end)),"",task_end-task_start+1) -> 15
A10: La celda B9 contiene la tarea de ejemplo "Tarea 1". Escriba un nuevo nombre de tarea en la celda B9. Escriba una persona a la que asignar la tarea en la celda C9. Escriba el progreso de la tarea en la celda D9. Aparece una barra de progreso en la celda y se sombrea según el número de la celda. Por ejemplo, un progreso del 50 por ciento aplicaría sombreado a la mitad de la celda. Escriba la fecha de inicio de la tarea en la celda E9. Escriba la fecha de finalización de la tarea en la celda F9. Aparece una barra de estado con sombreado para las fechas especificadas en bloques comenzando desde la celda I9 hasta la BL9. | B10: Polinómicas + Tarifario + Ev. Parámetros Precios | C10: Santiago Alonso | D10: 0.7 | E10: 45962 | F10: =+WORKDAY(E10,2) -> 45965 | H10: =IF(OR(ISBLANK(task_start),ISBLANK(task_end)),"",task_end-task_start+1) -> 4
B11: Obtener información detallada de DTM x Service Desk | C11: Santiago Alonso | D11: 0.25 | E11: 46023 | F11: =+WORKDAY(E11,7) -> 46034
B12: Días en Calle Calculado | C12: Santiago Alonso | D12: 0 | E12: =+F11+1 -> 46035 | F12: =+WORKDAY(E12,4) -> 46041 | H12: =IF(OR(ISBLANK(task_start),ISBLANK(task_end)),"",task_end-task_start+1) -> 7
B13: Aging Calculado | C13: Santiago Alonso | D13: 0 | E13: =+F12+1 -> 46042 | F13: =+WORKDAY(E13,4) -> 46048 | H13: =IF(OR(ISBLANK(task_start),ISBLANK(task_end)),"",task_end-task_start+1) -> 7
B14: Automatización de Provisión | C14: Santiago Alonso | D14: 0 | E14: =+F13+1 -> 46049 | F14: =+WORKDAY(E14,7) -> 46058
B15: Automatización de Certificaciones Mensuales | C15: Santiago Alonso | D15: 0 | E15: =+F14+1 -> 46059 | F15: =+WORKDAY(E15,7) -> 46070
A16: La celda a la derecha contiene el título de ejemplo de la Fase 2. Puede crear una nueva fase en cualquier momento en la columna B. Esta programación de proyecto no necesita fases. Para quitar la fase, basta con eliminar la fila. Para crear un bloque de fase nuevo en esta fila, escriba un nuevo título en la celda a la derecha. Para continuar agregando tareas a la fase anterior, escriba una nueva fila encima de esta y rellene los datos de la tarea como se explica en la celda A9. Actualice los detalles de la fase en la celda a la derecha como se explica en la celda A8. Continúe navegando por las celdas de la columna A para obtener más información. Si no ha agregado nuevas filas en esta hoja de cálculo, verá que se han creado automáticamente 2 bloques de fase de ejemplo adicionales en las celdas B20 y B26. En caso contrario, desplácese por las celdas de la columna A para buscar los bloques adicionales. Repita las instrucciones de las celdas A8 y A9 cuando lo necesite. | B16: 2- Cotizador Automático (Neuquén) | D16: =+AVERAGE(D17:D23) -> 0.028571429 | F16: =+F23-E17+1 -> 36
B17: Crear estructura de Cotizador en base a modelo armado | C17: Santiago Alonso | D17: 0 | E17: 45958 | F17: =+WORKDAY(E17,60) -> 46042 | H17: =IF(OR(ISBLANK(task_start),ISBLANK(task_end)),"",task_end-task_start+1) -> 85
B18: Automatización Archivo Sueldos FATSA | C18: Santiago Alonso | D18: 0 | E18: 45978 | F18: =+WORKDAY(E18,2) -> 45980 | H18: =IF(OR(ISBLANK(task_start),ISBLANK(task_end)),"",task_end-task_start+1) -> 3
B19: Automatización Archivo Sueldos Petro | C19: Santiago Alonso | D19: 0 | E19: 45978 | F19: =+WORKDAY(E19,2) -> 45980 | H19: =IF(OR(ISBLANK(task_start),ISBLANK(task_end)),"",task_end-task_start+1) -> 3
B20: Estandarización cotizaciones COMPRAS | C20: Santiago Alonso | D20: 0.2 | E20: 45959 | F20: =+WORKDAY(E20,10) -> 45973 | H20: =IF(OR(ISBLANK(task_start),ISBLANK(task_end)),"",task_end-task_start+1) -> 15
B21: Asociar Gastos de Estructura (% de incidencia) | C21: Santiago Alonso | D21: 0 | E21: =+F20+1 -> 45974 | F21: =+WORKDAY(E21,4) -> 45980 | H21: =IF(OR(ISBLANK(task_start),ISBLANK(task_end)),"",task_end-task_start+1) -> 7
B22: Armado de solicitudes extra x Módulos (Ej: Med. Laboral) | C22: Santiago Alonso | D22: 0 | E22: =+F19+1 -> 45981 | F22: =+WORKDAY(E22,3) -> 45986 | H22: =IF(OR(ISBLANK(task_start),ISBLANK(task_end)),"",task_end-task_start+1) -> 6
B23: Diseño de Dashboard | C23: Santiago Alonso | D23: 0 | E23: =+F22+1 -> 45987 | F23: =+WORKDAY(E23,4) -> 45993 | H23: =IF(OR(ISBLANK(task_start),ISBLANK(task_end)),"",task_end-task_start+1) -> 7
A24: Bloque de título fase de ejemplo | B24: 3- Planilla de Control | D24: =+AVERAGE(D25:D40) -> 0.394375 | F24: =+F40-E25+1 -> 74
B25: Planilla Activos Unificados (Nico Sifuentes) - Estandarizar | C25: Santiago Alonso | D25: 0 | E25: 45962 | F25: =+WORKDAY(E25,4) -> 45967 | H25: =IF(OR(ISBLANK(task_start),ISBLANK(task_end)),"",task_end-task_start+1) -> 6
A26: Las filas de la 10 a la 13 repiten el patrón de la fila 9. Repita las instrucciones de la celda A9 para todas las filas de tareas en esta hoja de cálculo. Sobrescriba los datos de ejemplo. Un ejemplo de otra fase empieza en la celda A14. Continue escribiendo tareas en las celdas de la A10 a la A13 o vaya a la celda A14 para obtener más información. | B26: Planilla DTM Estandarizada | C26: Santiago Alonso | D26: 0.9 | E26: =+F25 -> 45967 | F26: =+WORKDAY(E26,0) -> 45967 | H26: =IF(OR(ISBLANK(task_start),ISBLANK(task_end)),"",task_end-task_start+1) -> 1
B27: Planilla Aeroevaciaciones | C27: Santiago Alonso | D27: 0.9 | E27: =+F26+0 -> 45967 | F27: =+WORKDAY(E27,0) -> 45967 | H27: =IF(OR(ISBLANK(task_start),ISBLANK(task_end)),"",task_end-task_start+1) -> 1
B28: Resumen Clientes Petróleo | C28: Santiago Alonso | D28: 0.7 | E28: =+F25+1 -> 45968 | F28: =+WORKDAY(E28,3) -> 45973 | H28: =IF(OR(ISBLANK(task_start),ISBLANK(task_end)),"",task_end-task_start+1) -> 6
B29: Resumen Clientes Minería | C29: Santiago Alonso | D29: 0.2 | E29: =+F28+1 -> 45974 | F29: =+WORKDAY(E29,3) -> 45979 | H29: =IF(OR(ISBLANK(task_start),ISBLANK(task_end)),"",task_end-task_start+1) -> 6
B30: Resumen Clientes Op. Dedicadas | C30: Santiago Alonso | D30: 0.01 | E30: =+F29+1 -> 45980 | F30: =+WORKDAY(E30,1) -> 45981 | H30: =IF(OR(ISBLANK(task_start),ISBLANK(task_end)),"",task_end-task_start+1) -> 2
B31: Días en Calle (Sharepoint --> Excel) | C31: Santiago Alonso | D31: 0.5 | E31: =+F30+1 -> 45982 | F31: =+WORKDAY(E31,3) -> 45987 | H31: =IF(OR(ISBLANK(task_start),ISBLANK(task_end)),"",task_end-task_start+1) -> 6
B32: Aging (Sharepoint --> Excel) | C32: Santiago Alonso | D32: 0.5 | E32: =+F31+1 -> 45988 | F32: =+WORKDAY(E32,3) -> 45993 | H32: =IF(OR(ISBLANK(task_start),ISBLANK(task_end)),"",task_end-task_start+1) -> 6
B33: Importe Provisionado (Datalake --> Clik Sense "Venta Bruta") | C33: Santiago Alonso | D33: 0.5 | E33: =+F32+1 -> 45994 | F33: =+WORKDAY(E33,3) -> 45999 | H33: =IF(OR(ISBLANK(task_start),ISBLANK(task_end)),"",task_end-task_start+1) -> 6
B34: Importe Facturado (Datalake --> Clik Sense "Venta Bruta") | C34: Santiago Alonso | D34: 0.5 | E34: =+F33+1 -> 46000 | F34: =+WORKDAY(E34,3) -> 46003 | H34: =IF(OR(ISBLANK(task_start),ISBLANK(task_end)),"",task_end-task_start+1) -> 4
B35: Importe Pendiente Fc (Provisión) | C35: Santiago Alonso | D35: 0.8 | E35: =+F34+1 -> 46004 | F35: =+WORKDAY(E35,2) -> 46007 | H35: =IF(OR(ISBLANK(task_start),ISBLANK(task_end)),"",task_end-task_start+1) -> 4
B36: Locaciones Geográficas Pozos Petro (ver datos Secretaria de Energía) | C36: Santiago Alonso | D36: 0.1 | E36: =+F35+1 -> 46008 | F36: =+WORKDAY(E36,3) -> 46013
B37: Locaciones Geográficas Minería | C37: Santiago Alonso | D37: 0 | E37: =+F36+1 -> 46014 | F37: =+WORKDAY(E37,3) -> 46017
B38: Locaciones Geográficas Op. Dedicadas | C38: Santiago Alonso | D38: 0 | E38: =+F37+1 -> 46018 | F38: =+WORKDAY(E38,3) -> 46022
B39: Detalle Responsables (Comerciales + Analistas) | C39: Santiago Alonso | D39: 0.5 | E39: =+F38+1 -> 46023 | F39: =+WORKDAY(E39,1) -> 46024
B40: Armado de Dashboard + Diseño | C40: Santiago Alonso | D40: 0.2 | E40: =+F39+1 -> 46025 | F40: =+WORKDAY(E40,7) -> 46035 | H40: =IF(OR(ISBLANK(task_start),ISBLANK(task_end)),"",task_end-task_start+1) -> 11
A41: Bloque de título fase de ejemplo | B41: 4- Contratos Salesforce | D41: =+AVERAGE(D42:D44) -> 0.033333333 | F41: =+F44-E42+1 -> 38
B42: Eliminar contratos obsoletos | C42: Luis Barrozo/ Santiago Alonso | D42: 0.1 | E42: 45958 | F42: =+WORKDAY(E42,5) -> 45965 | H42: =IF(OR(ISBLANK(task_start),ISBLANK(task_end)),"",task_end-task_start+1) -> 8
B43: Estandarizar materíales de contratos | C43: Luis Barrozo/ Santiago Alonso | D43: 0 | E43: =+F42+1 -> 45966 | F43: =+WORKDAY(E43,10) -> 45980 | H43: =IF(OR(ISBLANK(task_start),ISBLANK(task_end)),"",task_end-task_start+1) -> 15
B44: Crear Boom´s para materiales que hacen alusión a US | C44: Luis Barrozo/ Santiago Alonso | D44: 0 | E44: =+F43+1 -> 45981 | F44: =+WORKDAY(E44,10) -> 45995 | H44: =IF(OR(ISBLANK(task_start),ISBLANK(task_end)),"",task_end-task_start+1) -> 15
B68: Resumen Clientes Op. Dedicadas
B69: Armado de Dashboard

Sheet Acerca de
A2: GRÁFICO GANTT SIMPLE de Vertex42.com
A3: https://www.vertex42.com/ExcelTemplates/simple-gantt-chart.html
A4: Información sobre esta plantilla
A5: Esta plantilla proporciona una forma sencilla de crear un diagrama de Gantt para ayudarle a visualizar su proyecto y realizar un seguimiento de este. Simplemente escriba sus tareas y fechas de inicio y finalización, no necesita fórmulas. Las barras del gráfico de Gantt representan la duración de la tarea y se muestran con formato condicional. Para insertar nuevas tareas, inserte filas nuevas.
A6: Guía para lectores de pantalla
A7: Hay 2 hojas de cálculo en este libro. ParteDeHoras Información Las instrucciones de las hojas de cálculo se encuentran en la columna A de cada hoja, a partir de la celda A1. Están escritas con texto oculto. Cada paso le guiará a través de la información de esa fila. Los pasos posteriores continúan en la celda A2, A3, y así sucesivamente, a menos que se indique de forma explícita. Por ejemplo, el texto de una instrucción podría ser “Vaya a la celda A6” para continuar con el siguiente paso. Este texto oculto no se imprimirá. Para quitar las instrucciones de la hoja de cálculo, es suficiente con eliminar la columna A.
A8: Ayuda adicional
A9: Haga clic en el vínculo siguiente para visitar vertex42.com y obtener más información sobre cómo usar esta plantilla, como la forma de calcular los días laborales, crear dependencias de tareas, cambiar los colores de las barras, agregar una barra de desplazamiento para que sea más fácil cambiar la semana que se muestra, ampliar el intervalo de fechas que se muestran en el gráfico, etcétera.
A10: Cómo usar el gráfico de Gantt simple
A11: Más plantillas de administración de proyectos
A12: Visite Vertex42.com para descargar otras plantillas de administración de proyectos, como distintas programaciones de proyectos, diagramas de Gantt, listas de tareas, etcétera.
A13: Plantillas de administración de proyectos
... A16: Las empresas encontrarán plantillas de facturas, partes de horas, informes financieros, planificación de proyectos y plantillas para hacer un seguimiento del inventario. Los profesores y los estudiantes encontrarán recursos como programaciones de clases, libros de calificaciones y hojas de asistencia. Organice su vida familiar con planificadores de comidas, listas y registros de ejercicio. Cada plantilla ha sido cuidadosamente diseñada, perfeccionada y mejorada a lo largo del tiempo gracias a los comentarios de miles de usuarios.

Sheet Tablero
B1: TABLERO EJECUTIVO — PROYECTO DATOS OP. COMPLEJAS
B2: ="IHSA S.A. · Responsable: "&'Proyecto Datos (OKR´s)'!$G$3&" · Inicio: "&TEXT('Proyecto Datos (OKR´s)'!$K$3,"dd/mm/yyyy")&" · Actualizado al "&TEXT(TODAY(),"dd/mm/yyyy") -> IHSA S.A. · Responsable: Santiago Alonso · Inicio: 28/10/2025 · Actualizado al 19/06/2026
B4: Avance Global | D4: Tareas | E4: Completadas | F4: En curso | G4: Próximas (≤7d) | H4: Vencidas
B5: =IFERROR(AVERAGE(_Datos!$I$7:$I$200),0) -> 0.48928571 | D5: =COUNT(_Datos!$H$7:$H$200) -> 42 | E5: =COUNTIF(_Datos!$J$7:$J$200,"Completado") -> 2 | F5: =COUNTIF(_Datos!$J$7:$J$200,"En curso") -> 13 | G5: =COUNTIF(_Datos!$J$7:$J$200,"Próximo a vencer") -> 14 | H5: =COUNTIF(_Datos!$J$7:$J$200,"Vencido") -> 13
B8: AVANCE POR MÓDULO (OKR)
B9: Módulo / Entregable | G9: Tareas | H9: % Avance | I9: Avance
B10: ='Proyecto Datos (OKR´s)'!$G$7 -> 1- GOC: Módulo de Datos para Procesos de Certificación (Inteligencia Comercial) | G10: =COUNTIF(_Datos!$D$7:$D$200,$B10) -> 1 | H10: =IFERROR(AVERAGEIF(_Datos!$D$7:$D$200,$B10,_Datos!$I$7:$I$200),"") -> 0.2 | I10: =IFERROR(AVERAGEIF(_Datos!$D$7:$D$200,$B10,_Datos!$I$7:$I$200),"") -> 0.2
B11: ='Proyecto Datos (OKR´s)'!$G$9 -> 2- Cotizador de Operaciones Complejas | G11: =COUNTIF(_Datos!$D$7:$D$200,$B11) -> 12 | H11: =IFERROR(AVERAGEIF(_Datos!$D$7:$D$200,$B11,_Datos!$I$7:$I$200),"") -> 0.48333333 | I11: =IFERROR(AVERAGEIF(_Datos!$D$7:$D$200,$B11,_Datos!$I$7:$I$200),"") -> 0.48333333
B12: ='Proyecto Datos (OKR´s)'!$G$22 -> 3- Tablero BI OPEX - Real vs BO | G12: =COUNTIF(_Datos!$D$7:$D$200,$B12) -> 4 | H12: =IFERROR(AVERAGEIF(_Datos!$D$7:$D$200,$B12,_Datos!$I$7:$I$200),"") -> 0.875 | I12: =IFERROR(AVERAGEIF(_Datos!$D$7:$D$200,$B12,_Datos!$I$7:$I$200),"") -> 0.875
B13: ='Proyecto Datos (OKR´s)'!$G$27 -> 4- Tablero BI DEUDA | G13: =COUNTIF(_Datos!$D$7:$D$200,$B13) -> 8 | H13: =IFERROR(AVERAGEIF(_Datos!$D$7:$D$200,$B13,_Datos!$I$7:$I$200),"") -> 0.725 | I13: =IFERROR(AVERAGEIF(_Datos!$D$7:$D$200,$B13,_Datos!$I$7:$I$200),"") -> 0.725
B14: ='Proyecto Datos (OKR´s)'!$G$36 -> 5- Tablero Control General - Op. Complejas | G14: =COUNTIF(_Datos!$D$7:$D$200,$B14) -> 11 | H14: =IFERROR(AVERAGEIF(_Datos!$D$7:$D$200,$B14,_Datos!$I$7:$I$200),"") -> 0.43181818 | I14: =IFERROR(AVERAGEIF(_Datos!$D$7:$D$200,$B14,_Datos!$I$7:$I$200),"") -> 0.43181818
B15: ='Proyecto Datos (OKR´s)'!$G$48 -> 6- Automatización de procesos: certificación, provisión,polinómicas | G15: =COUNTIF(_Datos!$D$7:$D$200,$B15) -> 3 | H15: =IFERROR(AVERAGEIF(_Datos!$D$7:$D$200,$B15,_Datos!$I$7:$I$200),"") -> 0.13333333 | I15: =IFERROR(AVERAGEIF(_Datos!$D$7:$D$200,$B15,_Datos!$I$7:$I$200),"") -> 0.13333333
B16: ='Proyecto Datos (OKR´s)'!$G$52 -> 7- Incorporación de Operaciones Complejas en sistemas de la compañía: Salesforce, SAP, etc. | G16: =COUNTIF(_Datos!$D$7:$D$200,$B16) -> 3 | H16: =IFERROR(AVERAGEIF(_Datos!$D$7:$D$200,$B16,_Datos!$I$7:$I$200),"") -> 0.033333333 | I16: =IFERROR(AVERAGEIF(_Datos!$D$7:$D$200,$B16,_Datos!$I$7:$I$200),"") -> 0.033333333
B19: AVANCE POR SPRINT
B20: Sprint | C20: Tareas | D20: Pendientes | E20: Vencidas | F20: Próx. a vencer | G20: Próxima entrega | H20: % Avance
B21: =IF($K21="","",IF($K21=9999,"(Sin sprint)",$K21)) -> 1 | C21: =IF($K21="","",COUNTIF(_Datos!$AD$7:$AD$200,$K21)) -> 2 | D21: =IF($K21="","",COUNTIFS(_Datos!$AD$7:$AD$200,$K21,_Datos!$J$7:$J$200,"<>Completado")) -> 0 | E21: =IF($K21="","",COUNTIFS(_Datos!$AD$7:$AD$200,$K21,_Datos!$J$7:$J$200,"Vencido")) -> 0 | F21: =IF($K21="","",COUNTIFS(_Datos!$AD$7:$AD$200,$K21,_Datos!$J$7:$J$200,"Próximo a vencer")) -> 0 | G21: =IF($K21="","",IF($D21=0,"—",_xlfn.MINIFS(_Datos!$H$7:$H$200,_Datos!$AD$7:$AD$200,$K21,_Datos!$J$7:$J$200,"<>Completado"))) -> — | H21: =IF($K21="","",IFERROR(AVERAGEIF(_Datos!$AD$7:$AD$200,$K21,_Datos!$I$7:$I$200),"")) -> 1 | K21: =IFERROR(SMALL(_Datos!$Q$7:$Q$37,ROW()-21+1),"") -> 1
B22: =IF($K22="","",IF($K22=9999,"(Sin sprint)",$K22)) -> 2 | C22: =IF($K22="","",COUNTIF(_Datos!$AD$7:$AD$200,$K22)) -> 21 | D22: =IF($K22="","",COUNTIFS(_Datos!$AD$7:$AD$200,$K22,_Datos!$J$7:$J$200,"<>Completado")) -> 21 | E22: =IF($K22="","",COUNTIFS(_Datos!$AD$7:$AD$200,$K22,_Datos!$J$7:$J$200,"Vencido")) -> 13 | F22: =IF($K22="","",COUNTIFS(_Datos!$AD$7:$AD$200,$K22,_Datos!$J$7:$J$200,"Próximo a vencer")) -> 7 | G22: =IF($K22="","",IF($D22=0,"—",_xlfn.MINIFS(_Datos!$H$7:$H$200,_Datos!$AD$7:$AD$200,$K22,_Datos!$J$7:$J$200,"<>Completado"))) -> 46185 | H22: =IF($K22="","",IFERROR(AVERAGEIF(_Datos!$AD$7:$AD$200,$K22,_Datos!$I$7:$I$200),"")) -> 0.70238095 | K22: =IFERROR(SMALL(_Datos!$Q$7:$Q$37,ROW()-21+1),"") -> 2
B23: =IF($K23="","",IF($K23=9999,"(Sin sprint)",$K23)) -> (Sin sprint) | C23: =IF($K23="","",COUNTIF(_Datos!$AD$7:$AD$200,$K23)) -> 19 | D23: =IF($K23="","",COUNTIFS(_Datos!$AD$7:$AD$200,$K23,_Datos!$J$7:$J$200,"<>Completado")) -> 19 | E23: =IF($K23="","",COUNTIFS(_Datos!$AD$7:$AD$200,$K23,_Datos!$J$7:$J$200,"Vencido")) -> 0 | F23: =IF($K23="","",COUNTIFS(_Datos!$AD$7:$AD$200,$K23,_Datos!$J$7:$J$200,"Próximo a vencer")) -> 7 | G23: =IF($K23="","",IF($D23=0,"—",_xlfn.MINIFS(_Datos!$H$7:$H$200,_Datos!$AD$7:$AD$200,$K23,_Datos!$J$7:$J$200,"<>Completado"))) -> 46192 | H23: =IF($K23="","",IFERROR(AVERAGEIF(_Datos!$AD$7:$AD$200,$K23,_Datos!$I$7:$I$200),"")) -> 0.2 | K23: =IFERROR(SMALL(_Datos!$Q$7:$Q$37,ROW()-21+1),"") -> 9999
B24: =IF($K24="","",IF($K24=9999,"(Sin sprint)",$K24)) | C24: =IF($K24="","",COUNTIF(_Datos!$AD$7:$AD$200,$K24)) | D24: =IF($K24="","",COUNTIFS(_Datos!$AD$7:$AD$200,$K24,_Datos!$J$7:$J$200,"<>Completado")) | E24: =IF($K24="","",COUNTIFS(_Datos!$AD$7:$AD$200,$K24,_Datos!$J$7:$J$200,"Vencido")) | F24: =IF($K24="","",COUNTIFS(_Datos!$AD$7:$AD$200,$K24,_Datos!$J$7:$J$200,"Próximo a vencer")) | G24: =IF($K24="","",IF($D24=0,"—",_xlfn.MINIFS(_Datos!$H$7:$H$200,_Datos!$AD$7:$AD$200,$K24,_Datos!$J$7:$J$200,"<>Completado"))) | H24: =IF($K24="","",IFERROR(AVERAGEIF(_Datos!$AD$7:$AD$200,$K24,_Datos!$I$7:$I$200),"")) | K24: =IFERROR(SMALL(_Datos!$Q$7:$Q$37,ROW()-21+1),"")
B25: =IF($K25="","",IF($K25=9999,"(Sin sprint)",$K25)) | C25: =IF($K25="","",COUNTIF(_Datos!$AD$7:$AD$200,$K25)) | D25: =IF($K25="","",COUNTIFS(_Datos!$AD$7:$AD$200,$K25,_Datos!$J$7:$J$200,"<>Completado")) | E25: =IF($K25="","",COUNTIFS(_Datos!$AD$7:$AD$200,$K25,_Datos!$J$7:$J$200,"Vencido")) | F25: =IF($K25="","",COUNTIFS(_Datos!$AD$7:$AD$200,$K25,_Datos!$J$7:$J$200,"Próximo a vencer")) | G25: =IF($K25="","",IF($D25=0,"—",_xlfn.MINIFS(_Datos!$H$7:$H$200,_Datos!$AD$7:$AD$200,$K25,_Datos!$J$7:$J$200,"<>Completado"))) | H25: =IF($K25="","",IFERROR(AVERAGEIF(_Datos!$AD$7:$AD$200,$K25,_Datos!$I$7:$I$200),"")) | K25: =IFERROR(SMALL(_Datos!$Q$7:$Q$37,ROW()-21+1),"")
B26: =IF($K26="","",IF($K26=9999,"(Sin sprint)",$K26)) | C26: =IF($K26="","",COUNTIF(_Datos!$AD$7:$AD$200,$K26)) | D26: =IF($K26="","",COUNTIFS(_Datos!$AD$7:$AD$200,$K26,_Datos!$J$7:$J$200,"<>Completado")) | E26: =IF($K26="","",COUNTIFS(_Datos!$AD$7:$AD$200,$K26,_Datos!$J$7:$J$200,"Vencido")) | F26: =IF($K26="","",COUNTIFS(_Datos!$AD$7:$AD$200,$K26,_Datos!$J$7:$J$200,"Próximo a vencer")) | G26: =IF($K26="","",IF($D26=0,"—",_xlfn.MINIFS(_Datos!$H$7:$H$200,_Datos!$AD$7:$AD$200,$K26,_Datos!$J$7:$J$200,"<>Completado"))) | H26: =IF($K26="","",IFERROR(AVERAGEIF(_Datos!$AD$7:$AD$200,$K26,_Datos!$I$7:$I$200),"")) | K26: =IFERROR(SMALL(_Datos!$Q$7:$Q$37,ROW()-21+1),"")
B27: =IF($K27="","",IF($K27=9999,"(Sin sprint)",$K27)) | C27: =IF($K27="","",COUNTIF(_Datos!$AD$7:$AD$200,$K27)) | D27: =IF($K27="","",COUNTIFS(_Datos!$AD$7:$AD$200,$K27,_Datos!$J$7:$J$200,"<>Completado")) | E27: =IF($K27="","",COUNTIFS(_Datos!$AD$7:$AD$200,$K27,_Datos!$J$7:$J$200,"Vencido")) | F27: =IF($K27="","",COUNTIFS(_Datos!$AD$7:$AD$200,$K27,_Datos!$J$7:$J$200,"Próximo a vencer")) | G27: =IF($K27="","",IF($D27=0,"—",_xlfn.MINIFS(_Datos!$H$7:$H$200,_Datos!$AD$7:$AD$200,$K27,_Datos!$J$7:$J$200,"<>Completado"))) | H27: =IF($K27="","",IFERROR(AVERAGEIF(_Datos!$AD$7:$AD$200,$K27,_Datos!$I$7:$I$200),"")) | K27: =IFERROR(SMALL(_Datos!$Q$7:$Q$37,ROW()-21+1),"")
B28: =IF($K28="","",IF($K28=9999,"(Sin sprint)",$K28)) | C28: =IF($K28="","",COUNTIF(_Datos!$AD$7:$AD$200,$K28)) | D28: =IF($K28="","",COUNTIFS(_Datos!$AD$7:$AD$200,$K28,_Datos!$J$7:$J$200,"<>Completado")) | E28: =IF($K28="","",COUNTIFS(_Datos!$AD$7:$AD$200,$K28,_Datos!$J$7:$J$200,"Vencido")) | F28: =IF($K28="","",COUNTIFS(_Datos!$AD$7:$AD$200,$K28,_Datos!$J$7:$J$200,"Próximo a vencer")) | G28: =IF($K28="","",IF($D28=0,"—",_xlfn.MINIFS(_Datos!$H$7:$H$200,_Datos!$AD$7:$AD$200,$K28,_Datos!$J$7:$J$200,"<>Completado"))) | H28: =IF($K28="","",IFERROR(AVERAGEIF(_Datos!$AD$7:$AD$200,$K28,_Datos!$I$7:$I$200),"")) | K28: =IFERROR(SMALL(_Datos!$Q$7:$Q$37,ROW()-21+1),"")
B29: =IF($K29="","",IF($K29=9999,"(Sin sprint)",$K29)) | C29: =IF($K29="","",COUNTIF(_Datos!$AD$7:$AD$200,$K29)) | D29: =IF($K29="","",COUNTIFS(_Datos!$AD$7:$AD$200,$K29,_Datos!$J$7:$J$200,"<>Completado")) | E29: =IF($K29="","",COUNTIFS(_Datos!$AD$7:$AD$200,$K29,_Datos!$J$7:$J$200,"Vencido")) | F29: =IF($K29="","",COUNTIFS(_Datos!$AD$7:$AD$200,$K29,_Datos!$J$7:$J$200,"Próximo a vencer")) | G29: =IF($K29="","",IF($D29=0,"—",_xlfn.MINIFS(_Datos!$H$7:$H$200,_Datos!$AD$7:$AD$200,$K29,_Datos!$J$7:$J$200,"<>Completado"))) | H29: =IF($K29="","",IFERROR(AVERAGEIF(_Datos!$AD$7:$AD$200,$K29,_Datos!$I$7:$I$200),"")) | K29: =IFERROR(SMALL(_Datos!$Q$7:$Q$37,ROW()-21+1),"")
B30: =IF($K30="","",IF($K30=9999,"(Sin sprint)",$K30)) | C30: =IF($K30="","",COUNTIF(_Datos!$AD$7:$AD$200,$K30)) | D30: =IF($K30="","",COUNTIFS(_Datos!$AD$7:$AD$200,$K30,_Datos!$J$7:$J$200,"<>Completado")) | E30: =IF($K30="","",COUNTIFS(_Datos!$AD$7:$AD$200,$K30,_Datos!$J$7:$J$200,"Vencido")) | F30: =IF($K30="","",COUNTIFS(_Datos!$AD$7:$AD$200,$K30,_Datos!$J$7:$J$200,"Próximo a vencer")) | G30: =IF($K30="","",IF($D30=0,"—",_xlfn.MINIFS(_Datos!$H$7:$H$200,_Datos!$AD$7:$AD$200,$K30,_Datos!$J$7:$J$200,"<>Completado"))) | H30: =IF($K30="","",IFERROR(AVERAGEIF(_Datos!$AD$7:$AD$200,$K30,_Datos!$I$7:$I$200),"")) | K30: =IFERROR(SMALL(_Datos!$Q$7:$Q$37,ROW()-21+1),"")
B31: =IF($K31="","",IF($K31=9999,"(Sin sprint)",$K31)) | C31: =IF($K31="","",COUNTIF(_Datos!$AD$7:$AD$200,$K31)) | D31: =IF($K31="","",COUNTIFS(_Datos!$AD$7:$AD$200,$K31,_Datos!$J$7:$J$200,"<>Completado")) | E31: =IF($K31="","",COUNTIFS(_Datos!$AD$7:$AD$200,$K31,_Datos!$J$7:$J$200,"Vencido")) | F31: =IF($K31="","",COUNTIFS(_Datos!$AD$7:$AD$200,$K31,_Datos!$J$7:$J$200,"Próximo a vencer")) | G31: =IF($K31="","",IF($D31=0,"—",_xlfn.MINIFS(_Datos!$H$7:$H$200,_Datos!$AD$7:$AD$200,$K31,_Datos!$J$7:$J$200,"<>Completado"))) | H31: =IF($K31="","",IFERROR(AVERAGEIF(_Datos!$AD$7:$AD$200,$K31,_Datos!$I$7:$I$200),"")) | K31: =IFERROR(SMALL(_Datos!$Q$7:$Q$37,ROW()-21+1),"")
B32: =IF($K32="","",IF($K32=9999,"(Sin sprint)",$K32)) | C32: =IF($K32="","",COUNTIF(_Datos!$AD$7:$AD$200,$K32)) | D32: =IF($K32="","",COUNTIFS(_Datos!$AD$7:$AD$200,$K32,_Datos!$J$7:$J$200,"<>Completado")) | E32: =IF($K32="","",COUNTIFS(_Datos!$AD$7:$AD$200,$K32,_Datos!$J$7:$J$200,"Vencido")) | F32: =IF($K32="","",COUNTIFS(_Datos!$AD$7:$AD$200,$K32,_Datos!$J$7:$J$200,"Próximo a vencer")) | G32: =IF($K32="","",IF($D32=0,"—",_xlfn.MINIFS(_Datos!$H$7:$H$200,_Datos!$AD$7:$AD$200,$K32,_Datos!$J$7:$J$200,"<>Completado"))) | H32: =IF($K32="","",IFERROR(AVERAGEIF(_Datos!$AD$7:$AD$200,$K32,_Datos!$I$7:$I$200),"")) | K32: =IFERROR(SMALL(_Datos!$Q$7:$Q$37,ROW()-21+1),"")
B34: ALERTAS / CUELLOS DE BOTELLA
B35: Críticas | C35: Bloqueadas | D35: Atrasadas | E35: Sobrecarga
B36: =COUNTIF(_Datos!$AB$7:$AB$200,"Crítica") -> 6 | C36: =COUNTIF(_Datos!$Z$7:$Z$200,TRUE) -> 0 | D36: =COUNTIF(_Datos!$W$7:$W$200,">0") -> 13 | E36: =COUNTIF(_Datos!$AC$7:$AC$200,"*SOBRECARGA*") -> 37
B37: Bloqueada = debía iniciar y sigue en 0%. Atrasada = pasó la fecha objetivo sin completar. Sobrecarga = responsable con >8 tareas pendientes. La lista priorizada completa está en 'Entregas Próximas'.
B39: Las métricas se recalculan solas desde la hoja Gantt. Los sprints (vigentes) aparecen automáticamente al usarse y conservan el histórico. El % por módulo se recalcula de forma independiente (no usa las celdas de promedio de las filas de fase).

Sheet Entregas Próximas
B1: ENTREGAS PRÓXIMAS — PRIORIZADAS
B2: ="Proyecto Datos Op. Complejas · IHSA S.A. · Hoy "&TEXT(TODAY(),"dd/mm/yyyy")&" | Entregas: "&COUNT(_Datos!$H$7:$H$200)&" | Críticas: "&COUNTIF(_Datos!$AB$7:$AB$200,"Crítica")&" | Vencidas: "&COUNTIF(_Datos!$J$7:$J$200,"Vencido")&" | Próximas: "&COUNTIF(_Datos!$J$7:$J$200,"Próximo a vencer")&" | Bloqueadas: "&COUNTIF(_Datos!$Z$7:$Z$200,TRUE)&" | Avance: "&TEXT(IFERROR(AVERAGE(_Datos!$I$7:$I$200),0),"0%") -> Proyecto Datos Op. Complejas · IHSA S.A. · Hoy 19/06/2026 | Entregas: 42 | Críticas: 6 | Vencidas: 13 | Próximas: 14 | Bloqueadas: 0 | Avance: 49%
B3: Estados: | C3: Vencido | E3: Próximo a vencer | F3: En curso | H3: Completado | K3: Umbral 'Próximo' (días): | M3: 7
B5: DETALLE DE ENTREGAS (ordenado por PRIORIDAD: urgencia + atraso + riesgo + carga)
B6: Prioridad | C6: Sprint | D6: Tarea | E6: Responsable | F6: Fecha obj. | G6: Estado | H6: Días rest. | I6: Dur.est. | J6: Días real | K6: Variación | L6: Atraso(d) | M6: Alerta / Cuello de botella
B7: =IF($P7="","",INDEX(_Datos!$AB$7:$AB$200,$P7)) -> Crítica | C7: =IF($P7="","",INDEX(_Datos!$AE$7:$AE$200,$P7)) -> 2 | D7: =IF($P7="","",INDEX(_Datos!$F$7:$F$200,$P7)) -> Planilla Activos Unificados - Estandarizar + Procedimiento | E7: =IF($P7="","",INDEX(_Datos!$G$7:$G$200,$P7)) -> Santiago Alonso | F7: =IF($P7="","",INDEX(_Datos!$H$7:$H$200,$P7)) -> 46185 | G7: =IF($P7="","",INDEX(_Datos!$J$7:$J$200,$P7)) -> Vencido | H7: =IF($P7="","",INDEX(_Datos!$K$7:$K$200,$P7)) -> -7 | I7: =IF($P7="","",INDEX(_Datos!$S$7:$S$200,$P7)) -> 194 | J7: =IF($P7="","",INDEX(_Datos!$T$7:$T$200,$P7)) -> 200 | K7: =IF($P7="","",INDEX(_Datos!$V$7:$V$200,$P7)) -> -0.8 | L7: =IF($P7="","",INDEX(_Datos!$W$7:$W$200,$P7)) -> 7 | M7: =IF($P7="","",INDEX(_Datos!$AC$7:$AC$200,$P7)) -> ATRASO SOBRECARGA | P7: =IFERROR(MATCH(LARGE(_Datos!$AJ$7:$AJ$200,ROW()-7+1),_Datos!$AJ$7:$AJ$200,0),"") -> 31
B8: =IF($P8="","",INDEX(_Datos!$AB$7:$AB$200,$P8)) -> Crítica | C8: =IF($P8="","",INDEX(_Datos!$AE$7:$AE$200,$P8)) -> (Sin sprint) | D8: =IF($P8="","",INDEX(_Datos!$F$7:$F$200,$P8)) -> Locaciones Geográficas Pozos Petro (ver datos Secretaria de Energía) | E8: =IF($P8="","",INDEX(_Datos!$G$7:$G$200,$P8)) -> Santiago Alonso | F8: =IF($P8="","",INDEX(_Datos!$H$7:$H$200,$P8)) -> 46192 | G8: =IF($P8="","",INDEX(_Datos!$J$7:$J$200,$P8)) -> Próximo a vencer | H8: =IF($P8="","",INDEX(_Datos!$K$7:$K$200,$P8)) -> 0 | I8: =IF($P8="","",INDEX(_Datos!$S$7:$S$200,$P8)) -> 5 | J8: =IF($P8="","",INDEX(_Datos!$T$7:$T$200,$P8)) -> 4 | K8: =IF($P8="","",INDEX(_Datos!$V$7:$V$200,$P8)) -> -0.9 | L8: =IF($P8="","",INDEX(_Datos!$W$7:$W$200,$P8)) -> 0 | M8: =IF($P8="","",INDEX(_Datos!$AC$7:$AC$200,$P8)) -> ATRASO SOBRECARGA | P8: =IFERROR(MATCH(LARGE(_Datos!$AJ$7:$AJ$200,ROW()-7+1),_Datos!$AJ$7:$AJ$200,0),"") -> 37
B9: =IF($P9="","",INDEX(_Datos!$AB$7:$AB$200,$P9)) -> Crítica | C9: =IF($P9="","",INDEX(_Datos!$AE$7:$AE$200,$P9)) -> 2 | D9: =IF($P9="","",INDEX(_Datos!$F$7:$F$200,$P9)) -> Resumen Clientes Op. Dedicadas | E9: =IF($P9="","",INDEX(_Datos!$G$7:$G$200,$P9)) -> Santiago Alonso | F9: =IF($P9="","",INDEX(_Datos!$H$7:$H$200,$P9)) -> 46185 | G9: =IF($P9="","",INDEX(_Datos!$J$7:$J$200,$P9)) -> Vencido | H9: =IF($P9="","",INDEX(_Datos!$K$7:$K$200,$P9)) -> -7 | I9: =IF($P9="","",INDEX(_Datos!$S$7:$S$200,$P9)) -> -2 | J9: =IF($P9="","",INDEX(_Datos!$T$7:$T$200,$P9)) -> 4 | K9: =IF($P9="","",INDEX(_Datos!$V$7:$V$200,$P9)) -> -0.6 | L9: =IF($P9="","",INDEX(_Datos!$W$7:$W$200,$P9)) -> 7 | M9: =IF($P9="","",INDEX(_Datos!$AC$7:$AC$200,$P9)) -> ATRASO SOBRECARGA | P9: =IFERROR(MATCH(LARGE(_Datos!$AJ$7:$AJ$200,ROW()-7+1),_Datos!$AJ$7:$AJ$200,0),"") -> 36
B10: =IF($P10="","",INDEX(_Datos!$AB$7:$AB$200,$P10)) -> Crítica | C10: =IF($P10="","",INDEX(_Datos!$AE$7:$AE$200,$P10)) -> (Sin sprint) | D10: =IF($P10="","",INDEX(_Datos!$F$7:$F$200,$P10)) -> Estandarización cotizaciones COMPRAS (costos x provincia) - aguardo información | E10: =IF($P10="","",INDEX(_Datos!$G$7:$G$200,$P10)) -> Santiago Alonso | F10: =IF($P10="","",INDEX(_Datos!$H$7:$H$200,$P10)) -> 46199 | G10: =IF($P10="","",INDEX(_Datos!$J$7:$J$200,$P10)) -> Próximo a vencer | H10: =IF($P10="","",INDEX(_Datos!$K$7:$K$200,$P10)) -> 7 | I10: =IF($P10="","",INDEX(_Datos!$S$7:$S$200,$P10)) -> 241 | J10: =IF($P10="","",INDEX(_Datos!$T$7:$T$200,$P10)) -> 233 | K10: =IF($P10="","",INDEX(_Datos!$V$7:$V$200,$P10)) -> -0.77083333 | L10: =IF($P10="","",INDEX(_Datos!$W$7:$W$200,$P10)) -> 0 | M10: =IF($P10="","",INDEX(_Datos!$AC$7:$AC$200,$P10)) -> ATRASO SOBRECARGA | P10: =IFERROR(MATCH(LARGE(_Datos!$AJ$7:$AJ$200,ROW()-7+1),_Datos!$AJ$7:$AJ$200,0),"") -> 8
B11: =IF($P11="","",INDEX(_Datos!$AB$7:$AB$200,$P11)) -> Crítica | C11: =IF($P11="","",INDEX(_Datos!$AE$7:$AE$200,$P11)) -> 2 | D11: =IF($P11="","",INDEX(_Datos!$F$7:$F$200,$P11)) -> Resumen Clientes Minería | E11: =IF($P11="","",INDEX(_Datos!$G$7:$G$200,$P11)) -> Santiago Alonso | F11: =IF($P11="","",INDEX(_Datos!$H$7:$H$200,$P11)) -> 46185 | G11: =IF($P11="","",INDEX(_Datos!$J$7:$J$200,$P11)) -> Vencido | H11: =IF($P11="","",INDEX(_Datos!$K$7:$K$200,$P11)) -> -7 | I11: =IF($P11="","",INDEX(_Datos!$S$7:$S$200,$P11)) -> -2 | J11: =IF($P11="","",INDEX(_Datos!$T$7:$T$200,$P11)) -> 4 | K11: =IF($P11="","",INDEX(_Datos!$V$7:$V$200,$P11)) -> -0.5 | L11: =IF($P11="","",INDEX(_Datos!$W$7:$W$200,$P11)) -> 7 | M11: =IF($P11="","",INDEX(_Datos!$AC$7:$AC$200,$P11)) -> ATRASO SOBRECARGA | P11: =IFERROR(MATCH(LARGE(_Datos!$AJ$7:$AJ$200,ROW()-7+1),_Datos!$AJ$7:$AJ$200,0),"") -> 35
B12: =IF($P12="","",INDEX(_Datos!$AB$7:$AB$200,$P12)) -> Crítica | C12: =IF($P12="","",INDEX(_Datos!$AE$7:$AE$200,$P12)) -> 2 | D12: =IF($P12="","",INDEX(_Datos!$F$7:$F$200,$P12)) -> Armado de Dashboard + Diseño | E12: =IF($P12="","",INDEX(_Datos!$G$7:$G$200,$P12)) -> Santiago Alonso | F12: =IF($P12="","",INDEX(_Datos!$H$7:$H$200,$P12)) -> 46185 | G12: =IF($P12="","",INDEX(_Datos!$J$7:$J$200,$P12)) -> Vencido | H12: =IF($P12="","",INDEX(_Datos!$K$7:$K$200,$P12)) -> -7 | I12: =IF($P12="","",INDEX(_Datos!$S$7:$S$200,$P12)) -> 0 | J12: =IF($P12="","",INDEX(_Datos!$T$7:$T$200,$P12)) -> 6 | K12: =IF($P12="","",INDEX(_Datos!$V$7:$V$200,$P12)) -> -0.5 | L12: =IF($P12="","",INDEX(_Datos!$W$7:$W$200,$P12)) -> 7 | M12: =IF($P12="","",INDEX(_Datos!$AC$7:$AC$200,$P12)) -> ATRASO SOBRECARGA | P12: =IFERROR(MATCH(LARGE(_Datos!$AJ$7:$AJ$200,ROW()-7+1),_Datos!$AJ$7:$AJ$200,0),"") -> 41
B13: =IF($P13="","",INDEX(_Datos!$AB$7:$AB$200,$P13)) -> Alta | C13: =IF($P13="","",INDEX(_Datos!$AE$7:$AE$200,$P13)) -> (Sin sprint) | D13: =IF($P13="","",INDEX(_Datos!$F$7:$F$200,$P13)) -> Analizar viabilidad de input Redash: Importe Provisionado (Datalake --> Clik Sense) | E13: =IF($P13="","",INDEX(_Datos!$G$7:$G$200,$P13)) -> Santiago Alonso | F13: =IF($P13="","",INDEX(_Datos!$H$7:$H$200,$P13)) -> 46192 | G13: =IF($P13="","",INDEX(_Datos!$J$7:$J$200,$P13)) -> Próximo a vencer | H13: =IF($P13="","",INDEX(_Datos!$K$7:$K$200,$P13)) -> 0 | I13: =IF($P13="","",INDEX(_Datos!$S$7:$S$200,$P13)) -> 5 | J13: =IF($P13="","",INDEX(_Datos!$T$7:$T$200,$P13)) -> 4 | K13: =IF($P13="","",INDEX(_Datos!$V$7:$V$200,$P13)) -> -0.4 | L13: =IF($P13="","",INDEX(_Datos!$W$7:$W$200,$P13)) -> 0 | M13: =IF($P13="","",INDEX(_Datos!$AC$7:$AC$200,$P13)) -> ATRASO SOBRECARGA | P13: =IFERROR(MATCH(LARGE(_Datos!$AJ$7:$AJ$200,ROW()-7+1),_Datos!$AJ$7:$AJ$200,0),"") -> 26
B14: =IF($P14="","",INDEX(_Datos!$AB$7:$AB$200,$P14)) -> Alta | C14: =IF($P14="","",INDEX(_Datos!$AE$7:$AE$200,$P14)) -> 2 | D14: =IF($P14="","",INDEX(_Datos!$F$7:$F$200,$P14)) -> Revisión de viabilidad de incorporación datos Redash (input ZReal con clasificaciones automaticas por CECO - Directas e Indirectas) | E14: =IF($P14="","",INDEX(_Datos!$G$7:$G$200,$P14)) -> Santiago Alonso | F14: =IF($P14="","",INDEX(_Datos!$H$7:$H$200,$P14)) -> 46185 | G14: =IF($P14="","",INDEX(_Datos!$J$7:$J$200,$P14)) -> Vencido | H14: =IF($P14="","",INDEX(_Datos!$K$7:$K$200,$P14)) -> -7 | I14: =IF($P14="","",INDEX(_Datos!$S$7:$S$200,$P14)) -> 9 | J14: =IF($P14="","",INDEX(_Datos!$T$7:$T$200,$P14)) -> 15 | K14: =IF($P14="","",INDEX(_Datos!$V$7:$V$200,$P14)) -> -0.1 | L14: =IF($P14="","",INDEX(_Datos!$W$7:$W$200,$P14)) -> 7 | M14: =IF($P14="","",INDEX(_Datos!$AC$7:$AC$200,$P14)) -> ATRASO SOBRECARGA | P14: =IFERROR(MATCH(LARGE(_Datos!$AJ$7:$AJ$200,ROW()-7+1),_Datos!$AJ$7:$AJ$200,0),"") -> 19
B15: =IF($P15="","",INDEX(_Datos!$AB$7:$AB$200,$P15)) -> Alta | C15: =IF($P15="","",INDEX(_Datos!$AE$7:$AE$200,$P15)) -> 2 | D15: =IF($P15="","",INDEX(_Datos!$F$7:$F$200,$P15)) -> Procedimiento | E15: =IF($P15="","",INDEX(_Datos!$G$7:$G$200,$P15)) -> Santiago Alonso | F15: =IF($P15="","",INDEX(_Datos!$H$7:$H$200,$P15)) -> 46185 | G15: =IF($P15="","",INDEX(_Datos!$J$7:$J$200,$P15)) -> Vencido | H15: =IF($P15="","",INDEX(_Datos!$K$7:$K$200,$P15)) -> -7 | I15: =IF($P15="","",INDEX(_Datos!$S$7:$S$200,$P15)) -> 5 | J15: =IF($P15="","",INDEX(_Datos!$T$7:$T$200,$P15)) -> 11 | K15: =IF($P15="","",INDEX(_Datos!$V$7:$V$200,$P15)) -> -0.1 | L15: =IF($P15="","",INDEX(_Datos!$W$7:$W$200,$P15)) -> 7 | M15: =IF($P15="","",INDEX(_Datos!$AC$7:$AC$200,$P15)) -> ATRASO SOBRECARGA | P15: =IFERROR(MATCH(LARGE(_Datos!$AJ$7:$AJ$200,ROW()-7+1),_Datos!$AJ$7:$AJ$200,0),"") -> 22
B16: =IF($P16="","",INDEX(_Datos!$AB$7:$AB$200,$P16)) -> Alta | C16: =IF($P16="","",INDEX(_Datos!$AE$7:$AE$200,$P16)) -> 2 | D16: =IF($P16="","",INDEX(_Datos!$F$7:$F$200,$P16)) -> Aging - desde SharePoint | E16: =IF($P16="","",INDEX(_Datos!$G$7:$G$200,$P16)) -> Santiago Alonso | F16: =IF($P16="","",INDEX(_Datos!$H$7:$H$200,$P16)) -> 46185 | G16: =IF($P16="","",INDEX(_Datos!$J$7:$J$200,$P16)) -> Vencido | H16: =IF($P16="","",INDEX(_Datos!$K$7:$K$200,$P16)) -> -7 | I16: =IF($P16="","",INDEX(_Datos!$S$7:$S$200,$P16)) -> 194 | J16: =IF($P16="","",INDEX(_Datos!$T$7:$T$200,$P16)) -> 200 | K16: =IF($P16="","",INDEX(_Datos!$V$7:$V$200,$P16)) -> -0.1 | L16: =IF($P16="","",INDEX(_Datos!$W$7:$W$200,$P16)) -> 7 | M16: =IF($P16="","",INDEX(_Datos!$AC$7:$AC$200,$P16)) -> ATRASO SOBRECARGA | P16: =IFERROR(MATCH(LARGE(_Datos!$AJ$7:$AJ$200,ROW()-7+1),_Datos!$AJ$7:$AJ$200,0),"") -> 23
B17: =IF($P17="","",INDEX(_Datos!$AB$7:$AB$200,$P17)) -> Alta | C17: =IF($P17="","",INDEX(_Datos!$AE$7:$AE$200,$P17)) -> 2 | D17: =IF($P17="","",INDEX(_Datos!$F$7:$F$200,$P17)) -> Dias en Calle - desde SharePoint | E17: =IF($P17="","",INDEX(_Datos!$G$7:$G$200,$P17)) -> Santiago Alonso | F17: =IF($P17="","",INDEX(_Datos!$H$7:$H$200,$P17)) -> 46185 | G17: =IF($P17="","",INDEX(_Datos!$J$7:$J$200,$P17)) -> Vencido | H17: =IF($P17="","",INDEX(_Datos!$K$7:$K$200,$P17)) -> -7 | I17: =IF($P17="","",INDEX(_Datos!$S$7:$S$200,$P17)) -> 194 | J17: =IF($P17="","",INDEX(_Datos!$T$7:$T$200,$P17)) -> 200 | K17: =IF($P17="","",INDEX(_Datos!$V$7:$V$200,$P17)) -> -0.1 | L17: =IF($P17="","",INDEX(_Datos!$W$7:$W$200,$P17)) -> 7 | M17: =IF($P17="","",INDEX(_Datos!$AC$7:$AC$200,$P17)) -> ATRASO SOBRECARGA | P17: =IFERROR(MATCH(LARGE(_Datos!$AJ$7:$AJ$200,ROW()-7+1),_Datos!$AJ$7:$AJ$200,0),"") -> 24
B18: =IF($P18="","",INDEX(_Datos!$AB$7:$AB$200,$P18)) -> Alta | C18: =IF($P18="","",INDEX(_Datos!$AE$7:$AE$200,$P18)) -> 2 | D18: =IF($P18="","",INDEX(_Datos!$F$7:$F$200,$P18)) -> Input de datos desde Provisión mensual | E18: =IF($P18="","",INDEX(_Datos!$G$7:$G$200,$P18)) -> Santiago Alonso | F18: =IF($P18="","",INDEX(_Datos!$H$7:$H$200,$P18)) -> 46185 | G18: =IF($P18="","",INDEX(_Datos!$J$7:$J$200,$P18)) -> Vencido | H18: =IF($P18="","",INDEX(_Datos!$K$7:$K$200,$P18)) -> -7 | I18: =IF($P18="","",INDEX(_Datos!$S$7:$S$200,$P18)) -> 163 | J18: =IF($P18="","",INDEX(_Datos!$T$7:$T$200,$P18)) -> 169 | K18: =IF($P18="","",INDEX(_Datos!$V$7:$V$200,$P18)) -> -0.1 | L18: =IF($P18="","",INDEX(_Datos!$W$7:$W$200,$P18)) -> 7 | M18: =IF($P18="","",INDEX(_Datos!$AC$7:$AC$200,$P18)) -> ATRASO SOBRECARGA | P18: =IFERROR(MATCH(LARGE(_Datos!$AJ$7:$AJ$200,ROW()-7+1),_Datos!$AJ$7:$AJ$200,0),"") -> 25
... B156: =IF($P156="","",INDEX(_Datos!$AB$7:$AB$200,$P156)) | C156: =IF($P156="","",INDEX(_Datos!$AE$7:$AE$200,$P156)) | D156: =IF($P156="","",INDEX(_Datos!$F$7:$F$200,$P156)) | E156: =IF($P156="","",INDEX(_Datos!$G$7:$G$200,$P156)) | F156: =IF($P156="","",INDEX(_Datos!$H$7:$H$200,$P156)) | G156: =IF($P156="","",INDEX(_Datos!$J$7:$J$200,$P156)) | H156: =IF($P156="","",INDEX(_Datos!$K$7:$K$200,$P156)) | I156: =IF($P156="","",INDEX(_Datos!$S$7:$S$200,$P156)) | J156: =IF($P156="","",INDEX(_Datos!$T$7:$T$200,$P156)) | K156: =IF($P156="","",INDEX(_Datos!$V$7:$V$200,$P156)) | L156: =IF($P156="","",INDEX(_Datos!$W$7:$W$200,$P156)) | M156: =IF($P156="","",INDEX(_Datos!$AC$7:$AC$200,$P156)) | P156: =IFERROR(MATCH(LARGE(_Datos!$AJ$7:$AJ$200,ROW()-7+1),_Datos!$AJ$7:$AJ$200,0),"")

Sheet Sprints
B1: SPRINTS — gestión por reunión (1 sprint = 1 reunión de cierre)
B2: Un sprint es un PERÍODO que cierra en una reunión. Al cerrar, las tareas NO completadas pasan automáticamente al sprint siguiente, mostrando el desvío. Indique el motivo (editable) en la columna I. Edite las fechas de las reuniones en el calendario de la derecha.
B4: SEGUIMIENTO DE TAREAS POR SPRINT | K4: CALENDARIO DE SPRINTS (editable) | O4: Motivos del desvío (editable)
K5: Sprint | L5: Reunión / Hito | M5: Fecha de cierre | O5: Dependencia bloqueada
B6: ID | C6: Tarea | D6: Responsable | E6: Sprint planif. | F6: Estado | G6: Sprint vigente | H6: Desvío (d) | I6: Motivo del desvío (editable) | K6: 1 | L6: Reunión 1 | M6: =DATE(2026,6,13) -> 46186 | O6: Sobrecarga del responsable
B7: =IF(_Datos!$C7,_Datos!$O7,"") | C7: =IF(_Datos!$C7,_Datos!$F7,"") | D7: =IF(_Datos!$C7,_Datos!$G7,"") | E7: =IF(_Datos!$C7,IF(_Datos!$N7=9999,"(Sin sprint)",_Datos!$N7),"") | F7: =IF(_Datos!$C7,_Datos!$J7,"") | G7: =IF(_Datos!$C7,_Datos!$AE7,"") | H7: =IF(_Datos!$C7,IF(_Datos!$AF7,_Datos!$AP7,"-"),"") | K7: 2 | L7: Reunión 2 | M7: =DATE(2026,6,27) -> 46200 | O7: Falta de información / insumos
B8: =IF(_Datos!$C8,_Datos!$O8,"") -> T008 | C8: =IF(_Datos!$C8,_Datos!$F8,"") -> Disponibilidad de información centralizada en GOC (aguarda desarrollo) | D8: =IF(_Datos!$C8,_Datos!$G8,"") -> Lucila Pronzato | E8: =IF(_Datos!$C8,IF(_Datos!$N8=9999,"(Sin sprint)",_Datos!$N8),"") -> 1 | F8: =IF(_Datos!$C8,_Datos!$J8,"") -> En curso | G8: =IF(_Datos!$C8,_Datos!$AE8,"") -> 2 | H8: =IF(_Datos!$C8,IF(_Datos!$AF8,_Datos!$AP8,"-"),"") -> 6 | K8: 3 | L8: Reunión 3 | M8: =DATE(2026,7,11) -> 46214 | O8: Reestimación / mayor alcance
B9: =IF(_Datos!$C9,_Datos!$O9,"") | C9: =IF(_Datos!$C9,_Datos!$F9,"") | D9: =IF(_Datos!$C9,_Datos!$G9,"") | E9: =IF(_Datos!$C9,IF(_Datos!$N9=9999,"(Sin sprint)",_Datos!$N9),"") | F9: =IF(_Datos!$C9,_Datos!$J9,"") | G9: =IF(_Datos!$C9,_Datos!$AE9,"") | H9: =IF(_Datos!$C9,IF(_Datos!$AF9,_Datos!$AP9,"-"),"") | K9: 4 | L9: Reunión 4 | M9: =DATE(2026,7,25) -> 46228 | O9: Recurso no disponible
B10: =IF(_Datos!$C10,_Datos!$O10,"") -> T010 | C10: =IF(_Datos!$C10,_Datos!$F10,"") -> Crear estructura de Cotizador en base a modelo armado (migra a CLAUDE) | D10: =IF(_Datos!$C10,_Datos!$G10,"") -> Santiago Alonso | E10: =IF(_Datos!$C10,IF(_Datos!$N10=9999,"(Sin sprint)",_Datos!$N10),"") -> 1 | F10: =IF(_Datos!$C10,_Datos!$J10,"") -> Completado | G10: =IF(_Datos!$C10,_Datos!$AE10,"") -> 1 | H10: =IF(_Datos!$C10,IF(_Datos!$AF10,_Datos!$AP10,"-"),"") -> - | K10: 5 | L10: Reunión 5 | M10: =DATE(2026,8,8) -> 46242 | O10: Prioridad reasignada
B11: =IF(_Datos!$C11,_Datos!$O11,"") -> T011 | C11: =IF(_Datos!$C11,_Datos!$F11,"") -> Automatización Archivo Sueldos FATSA + Procedimientos | D11: =IF(_Datos!$C11,_Datos!$G11,"") -> Santiago Alonso | E11: =IF(_Datos!$C11,IF(_Datos!$N11=9999,"(Sin sprint)",_Datos!$N11),"") -> 1 | F11: =IF(_Datos!$C11,_Datos!$J11,"") -> Próximo a vencer | G11: =IF(_Datos!$C11,_Datos!$AE11,"") -> 2 | H11: =IF(_Datos!$C11,IF(_Datos!$AF11,_Datos!$AP11,"-"),"") -> 6 | K11: 6 | L11: Reunión 6 | M11: =DATE(2026,8,22) -> 46256 | O11: Bloqueo técnico
B12: =IF(_Datos!$C12,_Datos!$O12,"") -> T012 | C12: =IF(_Datos!$C12,_Datos!$F12,"") -> Automatización Archivo Sueldos Petro + Procedimientos | D12: =IF(_Datos!$C12,_Datos!$G12,"") -> Santiago Alonso | E12: =IF(_Datos!$C12,IF(_Datos!$N12=9999,"(Sin sprint)",_Datos!$N12),"") -> 1 | F12: =IF(_Datos!$C12,_Datos!$J12,"") -> Próximo a vencer | G12: =IF(_Datos!$C12,_Datos!$AE12,"") -> 2 | H12: =IF(_Datos!$C12,IF(_Datos!$AF12,_Datos!$AP12,"-"),"") -> 6 | K12: 7 | L12: Reunión 7 | M12: =DATE(2026,9,5) -> 46270 | O12: Otro
B13: =IF(_Datos!$C13,_Datos!$O13,"") -> T013 | C13: =IF(_Datos!$C13,_Datos!$F13,"") -> Relevamiento Últimos Sueldos de referencia Monotributistas | D13: =IF(_Datos!$C13,_Datos!$G13,"") -> Santiago Alonso | E13: =IF(_Datos!$C13,IF(_Datos!$N13=9999,"(Sin sprint)",_Datos!$N13),"") -> 1 | F13: =IF(_Datos!$C13,_Datos!$J13,"") -> Próximo a vencer | G13: =IF(_Datos!$C13,_Datos!$AE13,"") -> 2 | H13: =IF(_Datos!$C13,IF(_Datos!$AF13,_Datos!$AP13,"-"),"") -> 6 | K13: 8 | L13: Reunión 8 | M13: =DATE(2026,9,19) -> 46284
B14: =IF(_Datos!$C14,_Datos!$O14,"") -> T014 | C14: =IF(_Datos!$C14,_Datos!$F14,"") -> Estandarización cotizaciones COMPRAS (costos x provincia) - aguardo información | D14: =IF(_Datos!$C14,_Datos!$G14,"") -> Santiago Alonso | E14: =IF(_Datos!$C14,IF(_Datos!$N14=9999,"(Sin sprint)",_Datos!$N14),"") -> (Sin sprint) | F14: =IF(_Datos!$C14,_Datos!$J14,"") -> Próximo a vencer | G14: =IF(_Datos!$C14,_Datos!$AE14,"") -> (Sin sprint) | H14: =IF(_Datos!$C14,IF(_Datos!$AF14,_Datos!$AP14,"-"),"") -> -
B15: =IF(_Datos!$C15,_Datos!$O15,"") -> T015 | C15: =IF(_Datos!$C15,_Datos!$F15,"") -> Asociar Archivo Móviles y Tráilers (Nico Sifuentes) + procedimiento | D15: =IF(_Datos!$C15,_Datos!$G15,"") -> Santiago Alonso | E15: =IF(_Datos!$C15,IF(_Datos!$N15=9999,"(Sin sprint)",_Datos!$N15),"") -> 1 | F15: =IF(_Datos!$C15,_Datos!$J15,"") -> Próximo a vencer | G15: =IF(_Datos!$C15,_Datos!$AE15,"") -> 2 | H15: =IF(_Datos!$C15,IF(_Datos!$AF15,_Datos!$AP15,"-"),"") -> 6 | K15: Sprint actual: | M15: =MIN(COUNT($K$6:$K$13),COUNTIF($M$6:$M$13,"<"&TODAY())+1) -> 2
B16: =IF(_Datos!$C16,_Datos!$O16,"") -> T016 | C16: =IF(_Datos!$C16,_Datos!$F16,"") -> Asociar Archivo Masters de Medicación (Seba Oliver) + Capacitaciones + procedimiento | D16: =IF(_Datos!$C16,_Datos!$G16,"") -> Santiago Alonso | E16: =IF(_Datos!$C16,IF(_Datos!$N16=9999,"(Sin sprint)",_Datos!$N16),"") -> 1 | F16: =IF(_Datos!$C16,_Datos!$J16,"") -> Próximo a vencer | G16: =IF(_Datos!$C16,_Datos!$AE16,"") -> 2 | H16: =IF(_Datos!$C16,IF(_Datos!$AF16,_Datos!$AP16,"-"),"") -> 6 | K16: Hoy: | M16: =TODAY() -> 46192
B17: =IF(_Datos!$C17,_Datos!$O17,"") -> T017 | C17: =IF(_Datos!$C17,_Datos!$F17,"") -> Asociar Gastos de Estructura (% de incidencia) | D17: =IF(_Datos!$C17,_Datos!$G17,"") -> Santiago Alonso | E17: =IF(_Datos!$C17,IF(_Datos!$N17=9999,"(Sin sprint)",_Datos!$N17),"") -> (Sin sprint) | F17: =IF(_Datos!$C17,_Datos!$J17,"") -> En curso | G17: =IF(_Datos!$C17,_Datos!$AE17,"") -> (Sin sprint) | H17: =IF(_Datos!$C17,IF(_Datos!$AF17,_Datos!$AP17,"-"),"") -> -
B18: =IF(_Datos!$C18,_Datos!$O18,"") -> T018 | C18: =IF(_Datos!$C18,_Datos!$F18,"") -> Armado de solicitudes extra x Módulos (Ej: Med. Laboral) | D18: =IF(_Datos!$C18,_Datos!$G18,"") -> Santiago Alonso | E18: =IF(_Datos!$C18,IF(_Datos!$N18=9999,"(Sin sprint)",_Datos!$N18),"") -> (Sin sprint) | F18: =IF(_Datos!$C18,_Datos!$J18,"") -> En curso | G18: =IF(_Datos!$C18,_Datos!$AE18,"") -> (Sin sprint) | H18: =IF(_Datos!$C18,IF(_Datos!$AF18,_Datos!$AP18,"-"),"") -> -
B19: =IF(_Datos!$C19,_Datos!$O19,"") -> T019 | C19: =IF(_Datos!$C19,_Datos!$F19,"") -> Relevamiento área de IA - Repositorio (GitHub o AWS S3) + Seguridad | D19: =IF(_Datos!$C19,_Datos!$G19,"") -> Santiago Alonso | E19: =IF(_Datos!$C19,IF(_Datos!$N19=9999,"(Sin sprint)",_Datos!$N19),"") -> 1 | F19: =IF(_Datos!$C19,_Datos!$J19,"") -> Completado | G19: =IF(_Datos!$C19,_Datos!$AE19,"") -> 1 | H19: =IF(_Datos!$C19,IF(_Datos!$AF19,_Datos!$AP19,"-"),"") -> -
B20: =IF(_Datos!$C20,_Datos!$O20,"") -> T020 | C20: =IF(_Datos!$C20,_Datos!$F20,"") -> Crear Backend ETL - ver con Claude Code | D20: =IF(_Datos!$C20,_Datos!$G20,"") -> Santiago Alonso | E20: =IF(_Datos!$C20,IF(_Datos!$N20=9999,"(Sin sprint)",_Datos!$N20),"") -> (Sin sprint) | F20: =IF(_Datos!$C20,_Datos!$J20,"") -> En curso | G20: =IF(_Datos!$C20,_Datos!$AE20,"") -> (Sin sprint) | H20: =IF(_Datos!$C20,IF(_Datos!$AF20,_Datos!$AP20,"-"),"") -> -
B21: =IF(_Datos!$C21,_Datos!$O21,"") -> T021 | C21: =IF(_Datos!$C21,_Datos!$F21,"") -> Deployar (URL Web) | D21: =IF(_Datos!$C21,_Datos!$G21,"") -> Santiago Alonso | E21: =IF(_Datos!$C21,IF(_Datos!$N21=9999,"(Sin sprint)",_Datos!$N21),"") -> (Sin sprint) | F21: =IF(_Datos!$C21,_Datos!$J21,"") -> En curso | G21: =IF(_Datos!$C21,_Datos!$AE21,"") -> (Sin sprint) | H21: =IF(_Datos!$C21,IF(_Datos!$AF21,_Datos!$AP21,"-"),"") -> -
B22: =IF(_Datos!$C22,_Datos!$O22,"") | C22: =IF(_Datos!$C22,_Datos!$F22,"") | D22: =IF(_Datos!$C22,_Datos!$G22,"") | E22: =IF(_Datos!$C22,IF(_Datos!$N22=9999,"(Sin sprint)",_Datos!$N22),"") | F22: =IF(_Datos!$C22,_Datos!$J22,"") | G22: =IF(_Datos!$C22,_Datos!$AE22,"") | H22: =IF(_Datos!$C22,IF(_Datos!$AF22,_Datos!$AP22,"-"),"")
B23: =IF(_Datos!$C23,_Datos!$O23,"") -> T023 | C23: =IF(_Datos!$C23,_Datos!$F23,"") -> Armado de Procedimiento | D23: =IF(_Datos!$C23,_Datos!$G23,"") -> Santiago Alonso | E23: =IF(_Datos!$C23,IF(_Datos!$N23=9999,"(Sin sprint)",_Datos!$N23),"") -> 1 | F23: =IF(_Datos!$C23,_Datos!$J23,"") -> Próximo a vencer | G23: =IF(_Datos!$C23,_Datos!$AE23,"") -> 2 | H23: =IF(_Datos!$C23,IF(_Datos!$AF23,_Datos!$AP23,"-"),"") -> 6
B24: =IF(_Datos!$C24,_Datos!$O24,"") -> T024 | C24: =IF(_Datos!$C24,_Datos!$F24,"") -> Revisión de Gráfico en cascada: por desvío y desagregación por categorías. | D24: =IF(_Datos!$C24,_Datos!$G24,"") -> Santiago Alonso | E24: =IF(_Datos!$C24,IF(_Datos!$N24=9999,"(Sin sprint)",_Datos!$N24),"") -> 1 | F24: =IF(_Datos!$C24,_Datos!$J24,"") -> Próximo a vencer | G24: =IF(_Datos!$C24,_Datos!$AE24,"") -> 2 | H24: =IF(_Datos!$C24,IF(_Datos!$AF24,_Datos!$AP24,"-"),"") -> 6
B25: =IF(_Datos!$C25,_Datos!$O25,"") -> T025 | C25: =IF(_Datos!$C25,_Datos!$F25,"") -> Revisión de viabilidad de incorporación datos Redash (input ZReal con clasificaciones automaticas por CECO - Directas e Indirectas) | D25: =IF(_Datos!$C25,_Datos!$G25,"") -> Santiago Alonso | E25: =IF(_Datos!$C25,IF(_Datos!$N25=9999,"(Sin sprint)",_Datos!$N25),"") -> 1 | F25: =IF(_Datos!$C25,_Datos!$J25,"") -> Vencido | G25: =IF(_Datos!$C25,_Datos!$AE25,"") -> 2 | H25: =IF(_Datos!$C25,IF(_Datos!$AF25,_Datos!$AP25,"-"),"") -> 6
B26: =IF(_Datos!$C26,_Datos!$O26,"") -> T026 | C26: =IF(_Datos!$C26,_Datos!$F26,"") -> Revisión y Publicación de Tablero | D26: =IF(_Datos!$C26,_Datos!$G26,"") -> Santiago Alonso | E26: =IF(_Datos!$C26,IF(_Datos!$N26=9999,"(Sin sprint)",_Datos!$N26),"") -> (Sin sprint) | F26: =IF(_Datos!$C26,_Datos!$J26,"") -> Próximo a vencer | G26: =IF(_Datos!$C26,_Datos!$AE26,"") -> (Sin sprint) | H26: =IF(_Datos!$C26,IF(_Datos!$AF26,_Datos!$AP26,"-"),"") -> -
B27: =IF(_Datos!$C27,_Datos!$O27,"") | C27: =IF(_Datos!$C27,_Datos!$F27,"") | D27: =IF(_Datos!$C27,_Datos!$G27,"") | E27: =IF(_Datos!$C27,IF(_Datos!$N27=9999,"(Sin sprint)",_Datos!$N27),"") | F27: =IF(_Datos!$C27,_Datos!$J27,"") | G27: =IF(_Datos!$C27,_Datos!$AE27,"") | H27: =IF(_Datos!$C27,IF(_Datos!$AF27,_Datos!$AP27,"-"),"")
B28: =IF(_Datos!$C28,_Datos!$O28,"") -> T028 | C28: =IF(_Datos!$C28,_Datos!$F28,"") -> Procedimiento | D28: =IF(_Datos!$C28,_Datos!$G28,"") -> Santiago Alonso | E28: =IF(_Datos!$C28,IF(_Datos!$N28=9999,"(Sin sprint)",_Datos!$N28),"") -> 1 | F28: =IF(_Datos!$C28,_Datos!$J28,"") -> Vencido | G28: =IF(_Datos!$C28,_Datos!$AE28,"") -> 2 | H28: =IF(_Datos!$C28,IF(_Datos!$AF28,_Datos!$AP28,"-"),"") -> 6
... B200: =IF(_Datos!$C200,_Datos!$O200,"") | C200: =IF(_Datos!$C200,_Datos!$F200,"") | D200: =IF(_Datos!$C200,_Datos!$G200,"") | E200: =IF(_Datos!$C200,IF(_Datos!$N200=9999,"(Sin sprint)",_Datos!$N200),"") | F200: =IF(_Datos!$C200,_Datos!$J200,"") | G200: =IF(_Datos!$C200,_Datos!$AE200,"") | H200: =IF(_Datos!$C200,IF(_Datos!$AF200,_Datos!$AP200,"-"),"")

Sheet _Datos
A1: HOJA AUXILIAR — Motor de cálculo (no editar). Alimenta Tablero, Entregas Próximas e Historial de Sprints.
A6: Fila | B6: EsFase | C6: EsTarea | D6: Módulo | E6: SprintRaw | F6: Tarea | G6: Responsable | H6: FechaObj | I6: Progreso | J6: Estado | K6: DíasRest | L6: ClaveOrden | M6: SprintKey | N6: SprintNum | O6: ID | P6: CandSpr | Q6: SprExiste | R6: FinPlan | S6: DurEst | T6: DíasTransc | U6: AvEsper | V6: VarAvance | W6: Atraso | X6: DesvíoPlan | Y6: CargaResp | Z6: Bloqueo | AA6: Score | AB6: Prioridad | AC6: Alertas | AD6: SprVigente | AE6: SprVigKey | AF6: Movido | AG6: FechaMov | AH6: Motivo | AI6: ClaveAud | AJ6: ClavePri | AK6: urg | AL6: atr | AM6: rsk | AN6: AlertRaw | AO6: CierrePlan | AP6: DesvíoSprint
A7: =ROW() -> 7 | B7: =ISTEXT('Proyecto Datos (OKR´s)'!$K7) -> TRUE | C7: =AND(LEN('Proyecto Datos (OKR´s)'!$G7)>0,NOT($B7),OR(ISNUMBER('Proyecto Datos (OKR´s)'!$F7),ISNUMBER('Proyecto Datos (OKR´s)'!$L7))) -> FALSE | D7: =IF($C7,IFERROR(LOOKUP(2,1/((ISTEXT('Proyecto Datos (OKR´s)'!$K$7:$K7))*(LEN('Proyecto Datos (OKR´s)'!$G$7:$G7)>0)),'Proyecto Datos (OKR´s)'!$G$7:$G7),""),"") | E7: =IF($C7,'Proyecto Datos (OKR´s)'!$E7,"") | F7: =IF($C7,'Proyecto Datos (OKR´s)'!$G7,"") | G7: =IF($C7,IF('Proyecto Datos (OKR´s)'!$I7="","(Sin asignar)",'Proyecto Datos (OKR´s)'!$I7),"") | H7: =IF($C7,IF(ISNUMBER('Proyecto Datos (OKR´s)'!$F7),'Proyecto Datos (OKR´s)'!$F7,'Proyecto Datos (OKR´s)'!$L7),"") | I7: =IF($C7,'Proyecto Datos (OKR´s)'!$J7,"") | J7: =IF($C7,IF($I7>=1,"Completado",IF($H7<TODAY(),"Vencido",IF(($H7-TODAY())<='Entregas Próximas'!$M$3,"Próximo a vencer","En curso"))),"") | K7: =IF($C7,$H7-TODAY(),"") | L7: =IF($C7,$AD7*1000000+$H7+ROW()/100000,"") | M7: =IF($C7,IF($AD7=9999,"(Sin sprint)",$AD7),"") | N7: =IF($C7,IF('Proyecto Datos (OKR´s)'!$E7="",9999,'Proyecto Datos (OKR´s)'!$E7),"") | O7: =IF($C7,"T"&TEXT(ROW(),"000"),"") | P7: =ROW()-6 -> 1 | Q7: =IF(COUNTIF($AD$7:$AD$200,$P7)>0,$P7,"") -> 1 | R7: =IF($C7,IF(ISNUMBER('Proyecto Datos (OKR´s)'!$L7),'Proyecto Datos (OKR´s)'!$L7,$H7),"") | S7: =IF($C7,$R7-'Proyecto Datos (OKR´s)'!$K7+1,"") | T7: =IF($C7,MAX(0,TODAY()-'Proyecto Datos (OKR´s)'!$K7),"") | U7: =IF($C7,MEDIAN(0,(TODAY()-'Proyecto Datos (OKR´s)'!$K7)/MAX(1,$R7-'Proyecto Datos (OKR´s)'!$K7),1),"") | V7: =IF($C7,$I7-$U7,"") | W7: =IF($C7,IF($J7="Completado",0,MAX(0,TODAY()-$H7)),"") | X7: =IF($C7,IF(ISNUMBER($H7),$R7-$H7,0),"") | Y7: =IF($C7,COUNTIFS($G$7:$G$200,$G7,$J$7:$J$200,"<>Completado",$J$7:$J$200,"<>"),"") | Z7: =IF($C7,AND($I7=0,'Proyecto Datos (OKR´s)'!$K7<=TODAY(),$J7<>"Completado"),"") | AA7: =IF($C7,ROUND(100*(0.35*$AK7+0.3*$AL7+0.2*$AM7+0.15*MEDIAN(0,($Y7-4)/8,1)),0),"") | AB7: =IF($C7,IF($J7="Completado","—",IF($AA7>=70,"Crítica",IF($AA7>=45,"Alta",IF($AA7>=25,"Media","Baja")))),"") | AC7: =IF($C7,IF(LEN(TRIM($AN7))=0,"—",TRIM($AN7)),"") | AD7: =IF($C7,IF($N7=9999,9999,IF($J7="Completado",$N7,MAX($N7,Sprints!$M$15))),"") | AE7: =IF($C7,IF($AD7=9999,"(Sin sprint)",$AD7),"") | AF7: =IF($C7,AND($N7<>9999,$AD7<>$N7),FALSE) -> FALSE | AG7: =IF($AF7,$AO7,"") | AH7: =IF($AF7,IF(Sprints!$I7<>"",Sprints!$I7,"Comprometida y no completada al cierre del Sprint "&$N7),"") | AI7: =IF($AF7,$N7*100000+ROW(),"") | AJ7: =IF($C7,$AA7*1000000-MEDIAN(-9999,$K7,9999)*100+(300-ROW()),"") | AK7: =IF($C7,IF($J7="Completado",0,IF($K7<0,1,IF($K7<=3,0.9,IF($K7<=7,0.7,IF($K7<=14,0.45,0.2))))),"") | AL7: =IF($C7,IF($J7="Completado",0,MEDIAN(0,MAX(-$V7,$W7/30),1)),"") | AM7: =IF($C7,IF($J7="Completado",0,IF($Z7,1,IF(AND($I7<0.5,$K7<=7),0.7,0.3))),"") | AN7: =IF($C7,IF(OR($V7<-0.2,$W7>0),"ATRASO ","")&IF($Z7,"BLOQUEO ","")&IF($Y7>8,"SOBRECARGA ","")&IF($X7>0,"DESVÍO-PLAN ",""),"") | AO7: =IF($C7,IFERROR(INDEX(Sprints!$M$6:$M$13,MATCH($N7,Sprints!$K$6:$K$13,0)),""),"") | AP7: =IF($C7,IF(AND($N7<>9999,$AD7<>$N7,ISNUMBER($AO7)),TODAY()-$AO7,0),"")
A8: =ROW() -> 8 | B8: =ISTEXT('Proyecto Datos (OKR´s)'!$K8) -> FALSE | C8: =AND(LEN('Proyecto Datos (OKR´s)'!$G8)>0,NOT($B8),OR(ISNUMBER('Proyecto Datos (OKR´s)'!$F8),ISNUMBER('Proyecto Datos (OKR´s)'!$L8))) -> TRUE | D8: =IF($C8,IFERROR(LOOKUP(2,1/((ISTEXT('Proyecto Datos (OKR´s)'!$K$7:$K8))*(LEN('Proyecto Datos (OKR´s)'!$G$7:$G8)>0)),'Proyecto Datos (OKR´s)'!$G$7:$G8),""),"") -> 1- GOC: Módulo de Datos para Procesos de Certificación (Inteligencia Comercial) | E8: =IF($C8,'Proyecto Datos (OKR´s)'!$E8,"") -> 1 | F8: =IF($C8,'Proyecto Datos (OKR´s)'!$G8,"") -> Disponibilidad de información centralizada en GOC (aguarda desarrollo) | G8: =IF($C8,IF('Proyecto Datos (OKR´s)'!$I8="","(Sin asignar)",'Proyecto Datos (OKR´s)'!$I8),"") -> Lucila Pronzato | H8: =IF($C8,IF(ISNUMBER('Proyecto Datos (OKR´s)'!$F8),'Proyecto Datos (OKR´s)'!$F8,'Proyecto Datos (OKR´s)'!$L8),"") -> 46203 | I8: =IF($C8,'Proyecto Datos (OKR´s)'!$J8,"") -> 0.2 | J8: =IF($C8,IF($I8>=1,"Completado",IF($H8<TODAY(),"Vencido",IF(($H8-TODAY())<='Entregas Próximas'!$M$3,"Próximo a vencer","En curso"))),"") -> En curso | K8: =IF($C8,$H8-TODAY(),"") -> 11 | L8: =IF($C8,$AD8*1000000+$H8+ROW()/100000,"") -> 2046203 | M8: =IF($C8,IF($AD8=9999,"(Sin sprint)",$AD8),"") -> 2 | N8: =IF($C8,IF('Proyecto Datos (OKR´s)'!$E8="",9999,'Proyecto Datos (OKR´s)'!$E8),"") -> 1 | O8: =IF($C8,"T"&TEXT(ROW(),"000"),"") -> T008 | P8: =ROW()-6 -> 2 | Q8: =IF(COUNTIF($AD$7:$AD$200,$P8)>0,$P8,"") -> 2 | R8: =IF($C8,IF(ISNUMBER('Proyecto Datos (OKR´s)'!$L8),'Proyecto Datos (OKR´s)'!$L8,$H8),"") -> 46203 | S8: =IF($C8,$R8-'Proyecto Datos (OKR´s)'!$K8+1,"") -> 246 | T8: =IF($C8,MAX(0,TODAY()-'Proyecto Datos (OKR´s)'!$K8),"") -> 234 | U8: =IF($C8,MEDIAN(0,(TODAY()-'Proyecto Datos (OKR´s)'!$K8)/MAX(1,$R8-'Proyecto Datos (OKR´s)'!$K8),1),"") -> 0.95510204 | V8: =IF($C8,$I8-$U8,"") -> -0.75510204 | W8: =IF($C8,IF($J8="Completado",0,MAX(0,TODAY()-$H8)),"") -> 0 | X8: =IF($C8,IF(ISNUMBER($H8),$R8-$H8,0),"") -> 0 | Y8: =IF($C8,COUNTIFS($G$7:$G$200,$G8,$J$7:$J$200,"<>Completado",$J$7:$J$200,"<>"),"") -> 1 | Z8: =IF($C8,AND($I8=0,'Proyecto Datos (OKR´s)'!$K8<=TODAY(),$J8<>"Completado"),"") -> FALSE | AA8: =IF($C8,ROUND(100*(0.35*$AK8+0.3*$AL8+0.2*$AM8+0.15*MEDIAN(0,($Y8-4)/8,1)),0),"") -> 44 | AB8: =IF($C8,IF($J8="Completado","—",IF($AA8>=70,"Crítica",IF($AA8>=45,"Alta",IF($AA8>=25,"Media","Baja")))),"") -> Media | AC8: =IF($C8,IF(LEN(TRIM($AN8))=0,"—",TRIM($AN8)),"") -> ATRASO | AD8: =IF($C8,IF($N8=9999,9999,IF($J8="Completado",$N8,MAX($N8,Sprints!$M$15))),"") -> 2 | AE8: =IF($C8,IF($AD8=9999,"(Sin sprint)",$AD8),"") -> 2 | AF8: =IF($C8,AND($N8<>9999,$AD8<>$N8),FALSE) -> TRUE | AG8: =IF($AF8,$AO8,"") -> 46186 | AH8: =IF($AF8,IF(Sprints!$I8<>"",Sprints!$I8,"Comprometida y no completada al cierre del Sprint "&$N8),"") -> Comprometida y no completada al cierre del Sprint 1 | AI8: =IF($AF8,$N8*100000+ROW(),"") -> 100008 | AJ8: =IF($C8,$AA8*1000000-MEDIAN(-9999,$K8,9999)*100+(300-ROW()),"") -> 43999192 | AK8: =IF($C8,IF($J8="Completado",0,IF($K8<0,1,IF($K8<=3,0.9,IF($K8<=7,0.7,IF($K8<=14,0.45,0.2))))),"") -> 0.45 | AL8: =IF($C8,IF($J8="Completado",0,MEDIAN(0,MAX(-$V8,$W8/30),1)),"") -> 0.75510204 | AM8: =IF($C8,IF($J8="Completado",0,IF($Z8,1,IF(AND($I8<0.5,$K8<=7),0.7,0.3))),"") -> 0.3 | AN8: =IF($C8,IF(OR($V8<-0.2,$W8>0),"ATRASO ","")&IF($Z8,"BLOQUEO ","")&IF($Y8>8,"SOBRECARGA ","")&IF($X8>0,"DESVÍO-PLAN ",""),"") -> ATRASO | AO8: =IF($C8,IFERROR(INDEX(Sprints!$M$6:$M$13,MATCH($N8,Sprints!$K$6:$K$13,0)),""),"") -> 46186 | AP8: =IF($C8,IF(AND($N8<>9999,$AD8<>$N8,ISNUMBER($AO8)),TODAY()-$AO8,0),"") -> 6
A9: =ROW() -> 9 | B9: =ISTEXT('Proyecto Datos (OKR´s)'!$K9) -> TRUE | C9: =AND(LEN('Proyecto Datos (OKR´s)'!$G9)>0,NOT($B9),OR(ISNUMBER('Proyecto Datos (OKR´s)'!$F9),ISNUMBER('Proyecto Datos (OKR´s)'!$L9))) -> FALSE | D9: =IF($C9,IFERROR(LOOKUP(2,1/((ISTEXT('Proyecto Datos (OKR´s)'!$K$7:$K9))*(LEN('Proyecto Datos (OKR´s)'!$G$7:$G9)>0)),'Proyecto Datos (OKR´s)'!$G$7:$G9),""),"") | E9: =IF($C9,'Proyecto Datos (OKR´s)'!$E9,"") | F9: =IF($C9,'Proyecto Datos (OKR´s)'!$G9,"") | G9: =IF($C9,IF('Proyecto Datos (OKR´s)'!$I9="","(Sin asignar)",'Proyecto Datos (OKR´s)'!$I9),"") | H9: =IF($C9,IF(ISNUMBER('Proyecto Datos (OKR´s)'!$F9),'Proyecto Datos (OKR´s)'!$F9,'Proyecto Datos (OKR´s)'!$L9),"") | I9: =IF($C9,'Proyecto Datos (OKR´s)'!$J9,"") | J9: =IF($C9,IF($I9>=1,"Completado",IF($H9<TODAY(),"Vencido",IF(($H9-TODAY())<='Entregas Próximas'!$M$3,"Próximo a vencer","En curso"))),"") | K9: =IF($C9,$H9-TODAY(),"") | L9: =IF($C9,$AD9*1000000+$H9+ROW()/100000,"") | M9: =IF($C9,IF($AD9=9999,"(Sin sprint)",$AD9),"") | N9: =IF($C9,IF('Proyecto Datos (OKR´s)'!$E9="",9999,'Proyecto Datos (OKR´s)'!$E9),"") | O9: =IF($C9,"T"&TEXT(ROW(),"000"),"") | P9: =ROW()-6 -> 3 | Q9: =IF(COUNTIF($AD$7:$AD$200,$P9)>0,$P9,"") | R9: =IF($C9,IF(ISNUMBER('Proyecto Datos (OKR´s)'!$L9),'Proyecto Datos (OKR´s)'!$L9,$H9),"") | S9: =IF($C9,$R9-'Proyecto Datos (OKR´s)'!$K9+1,"") | T9: =IF($C9,MAX(0,TODAY()-'Proyecto Datos (OKR´s)'!$K9),"") | U9: =IF($C9,MEDIAN(0,(TODAY()-'Proyecto Datos (OKR´s)'!$K9)/MAX(1,$R9-'Proyecto Datos (OKR´s)'!$K9),1),"") | V9: =IF($C9,$I9-$U9,"") | W9: =IF($C9,IF($J9="Completado",0,MAX(0,TODAY()-$H9)),"") | X9: =IF($C9,IF(ISNUMBER($H9),$R9-$H9,0),"") | Y9: =IF($C9,COUNTIFS($G$7:$G$200,$G9,$J$7:$J$200,"<>Completado",$J$7:$J$200,"<>"),"") | Z9: =IF($C9,AND($I9=0,'Proyecto Datos (OKR´s)'!$K9<=TODAY(),$J9<>"Completado"),"") | AA9: =IF($C9,ROUND(100*(0.35*$AK9+0.3*$AL9+0.2*$AM9+0.15*MEDIAN(0,($Y9-4)/8,1)),0),"") | AB9: =IF($C9,IF($J9="Completado","—",IF($AA9>=70,"Crítica",IF($AA9>=45,"Alta",IF($AA9>=25,"Media","Baja")))),"") | AC9: =IF($C9,IF(LEN(TRIM($AN9))=0,"—",TRIM($AN9)),"") | AD9: =IF($C9,IF($N9=9999,9999,IF($J9="Completado",$N9,MAX($N9,Sprints!$M$15))),"") | AE9: =IF($C9,IF($AD9=9999,"(Sin sprint)",$AD9),"") | AF9: =IF($C9,AND($N9<>9999,$AD9<>$N9),FALSE) -> FALSE | AG9: =IF($AF9,$AO9,"") | AH9: =IF($AF9,IF(Sprints!$I9<>"",Sprints!$I9,"Comprometida y no completada al cierre del Sprint "&$N9),"") | AI9: =IF($AF9,$N9*100000+ROW(),"") | AJ9: =IF($C9,$AA9*1000000-MEDIAN(-9999,$K9,9999)*100+(300-ROW()),"") | AK9: =IF($C9,IF($J9="Completado",0,IF($K9<0,1,IF($K9<=3,0.9,IF($K9<=7,0.7,IF($K9<=14,0.45,0.2))))),"") | AL9: =IF($C9,IF($J9="Completado",0,MEDIAN(0,MAX(-$V9,$W9/30),1)),"") | AM9: =IF($C9,IF($J9="Completado",0,IF($Z9,1,IF(AND($I9<0.5,$K9<=7),0.7,0.3))),"") | AN9: =IF($C9,IF(OR($V9<-0.2,$W9>0),"ATRASO ","")&IF($Z9,"BLOQUEO ","")&IF($Y9>8,"SOBRECARGA ","")&IF($X9>0,"DESVÍO-PLAN ",""),"") | AO9: =IF($C9,IFERROR(INDEX(Sprints!$M$6:$M$13,MATCH($N9,Sprints!$K$6:$K$13,0)),""),"") | AP9: =IF($C9,IF(AND($N9<>9999,$AD9<>$N9,ISNUMBER($AO9)),TODAY()-$AO9,0),"")
A10: =ROW() -> 10 | B10: =ISTEXT('Proyecto Datos (OKR´s)'!$K10) -> FALSE | C10: =AND(LEN('Proyecto Datos (OKR´s)'!$G10)>0,NOT($B10),OR(ISNUMBER('Proyecto Datos (OKR´s)'!$F10),ISNUMBER('Proyecto Datos (OKR´s)'!$L10))) -> TRUE | D10: =IF($C10,IFERROR(LOOKUP(2,1/((ISTEXT('Proyecto Datos (OKR´s)'!$K$7:$K10))*(LEN('Proyecto Datos (OKR´s)'!$G$7:$G10)>0)),'Proyecto Datos (OKR´s)'!$G$7:$G10),""),"") -> 2- Cotizador de Operaciones Complejas | E10: =IF($C10,'Proyecto Datos (OKR´s)'!$E10,"") -> 1 | F10: =IF($C10,'Proyecto Datos (OKR´s)'!$G10,"") -> Crear estructura de Cotizador en base a modelo armado (migra a CLAUDE) | G10: =IF($C10,IF('Proyecto Datos (OKR´s)'!$I10="","(Sin asignar)",'Proyecto Datos (OKR´s)'!$I10),"") -> Santiago Alonso | H10: =IF($C10,IF(ISNUMBER('Proyecto Datos (OKR´s)'!$F10),'Proyecto Datos (OKR´s)'!$F10,'Proyecto Datos (OKR´s)'!$L10),"") -> 46192 | I10: =IF($C10,'Proyecto Datos (OKR´s)'!$J10,"") -> 1 | J10: =IF($C10,IF($I10>=1,"Completado",IF($H10<TODAY(),"Vencido",IF(($H10-TODAY())<='Entregas Próximas'!$M$3,"Próximo a vencer","En curso"))),"") -> Completado | K10: =IF($C10,$H10-TODAY(),"") -> 0 | L10: =IF($C10,$AD10*1000000+$H10+ROW()/100000,"") -> 1046192 | M10: =IF($C10,IF($AD10=9999,"(Sin sprint)",$AD10),"") -> 1 | N10: =IF($C10,IF('Proyecto Datos (OKR´s)'!$E10="",9999,'Proyecto Datos (OKR´s)'!$E10),"") -> 1 | O10: =IF($C10,"T"&TEXT(ROW(),"000"),"") -> T010 | P10: =ROW()-6 -> 4 | Q10: =IF(COUNTIF($AD$7:$AD$200,$P10)>0,$P10,"") | R10: =IF($C10,IF(ISNUMBER('Proyecto Datos (OKR´s)'!$L10),'Proyecto Datos (OKR´s)'!$L10,$H10),"") -> 46192 | S10: =IF($C10,$R10-'Proyecto Datos (OKR´s)'!$K10+1,"") -> 235 | T10: =IF($C10,MAX(0,TODAY()-'Proyecto Datos (OKR´s)'!$K10),"") -> 234 | U10: =IF($C10,MEDIAN(0,(TODAY()-'Proyecto Datos (OKR´s)'!$K10)/MAX(1,$R10-'Proyecto Datos (OKR´s)'!$K10),1),"") -> 1 | V10: =IF($C10,$I10-$U10,"") -> 0 | W10: =IF($C10,IF($J10="Completado",0,MAX(0,TODAY()-$H10)),"") -> 0 | X10: =IF($C10,IF(ISNUMBER($H10),$R10-$H10,0),"") -> 0 | Y10: =IF($C10,COUNTIFS($G$7:$G$200,$G10,$J$7:$J$200,"<>Completado",$J$7:$J$200,"<>"),"") -> 35 | Z10: =IF($C10,AND($I10=0,'Proyecto Datos (OKR´s)'!$K10<=TODAY(),$J10<>"Completado"),"") -> FALSE | AA10: =IF($C10,ROUND(100*(0.35*$AK10+0.3*$AL10+0.2*$AM10+0.15*MEDIAN(0,($Y10-4)/8,1)),0),"") -> 15 | AB10: =IF($C10,IF($J10="Completado","—",IF($AA10>=70,"Crítica",IF($AA10>=45,"Alta",IF($AA10>=25,"Media","Baja")))),"") -> — | AC10: =IF($C10,IF(LEN(TRIM($AN10))=0,"—",TRIM($AN10)),"") -> SOBRECARGA | AD10: =IF($C10,IF($N10=9999,9999,IF($J10="Completado",$N10,MAX($N10,Sprints!$M$15))),"") -> 1 | AE10: =IF($C10,IF($AD10=9999,"(Sin sprint)",$AD10),"") -> 1 | AF10: =IF($C10,AND($N10<>9999,$AD10<>$N10),FALSE) -> FALSE | AG10: =IF($AF10,$AO10,"") | AH10: =IF($AF10,IF(Sprints!$I10<>"",Sprints!$I10,"Comprometida y no completada al cierre del Sprint "&$N10),"") | AI10: =IF($AF10,$N10*100000+ROW(),"") | AJ10: =IF($C10,$AA10*1000000-MEDIAN(-9999,$K10,9999)*100+(300-ROW()),"") -> 15000290 | AK10: =IF($C10,IF($J10="Completado",0,IF($K10<0,1,IF($K10<=3,0.9,IF($K10<=7,0.7,IF($K10<=14,0.45,0.2))))),"") -> 0 | AL10: =IF($C10,IF($J10="Completado",0,MEDIAN(0,MAX(-$V10,$W10/30),1)),"") -> 0 | AM10: =IF($C10,IF($J10="Completado",0,IF($Z10,1,IF(AND($I10<0.5,$K10<=7),0.7,0.3))),"") -> 0 | AN10: =IF($C10,IF(OR($V10<-0.2,$W10>0),"ATRASO ","")&IF($Z10,"BLOQUEO ","")&IF($Y10>8,"SOBRECARGA ","")&IF($X10>0,"DESVÍO-PLAN ",""),"") -> SOBRECARGA | AO10: =IF($C10,IFERROR(INDEX(Sprints!$M$6:$M$13,MATCH($N10,Sprints!$K$6:$K$13,0)),""),"") -> 46186 | AP10: =IF($C10,IF(AND($N10<>9999,$AD10<>$N10,ISNUMBER($AO10)),TODAY()-$AO10,0),"") -> 0
A11: =ROW() -> 11 | B11: =ISTEXT('Proyecto Datos (OKR´s)'!$K11) -> FALSE | C11: =AND(LEN('Proyecto Datos (OKR´s)'!$G11)>0,NOT($B11),OR(ISNUMBER('Proyecto Datos (OKR´s)'!$F11),ISNUMBER('Proyecto Datos (OKR´s)'!$L11))) -> TRUE | D11: =IF($C11,IFERROR(LOOKUP(2,1/((ISTEXT('Proyecto Datos (OKR´s)'!$K$7:$K11))*(LEN('Proyecto Datos (OKR´s)'!$G$7:$G11)>0)),'Proyecto Datos (OKR´s)'!$G$7:$G11),""),"") -> 2- Cotizador de Operaciones Complejas | E11: =IF($C11,'Proyecto Datos (OKR´s)'!$E11,"") -> 1 | F11: =IF($C11,'Proyecto Datos (OKR´s)'!$G11,"") -> Automatización Archivo Sueldos FATSA + Procedimientos | G11: =IF($C11,IF('Proyecto Datos (OKR´s)'!$I11="","(Sin asignar)",'Proyecto Datos (OKR´s)'!$I11),"") -> Santiago Alonso | H11: =IF($C11,IF(ISNUMBER('Proyecto Datos (OKR´s)'!$F11),'Proyecto Datos (OKR´s)'!$F11,'Proyecto Datos (OKR´s)'!$L11),"") -> 46192 | I11: =IF($C11,'Proyecto Datos (OKR´s)'!$J11,"") -> 0.75 | J11: =IF($C11,IF($I11>=1,"Completado",IF($H11<TODAY(),"Vencido",IF(($H11-TODAY())<='Entregas Próximas'!$M$3,"Próximo a vencer","En curso"))),"") -> Próximo a vencer | K11: =IF($C11,$H11-TODAY(),"") -> 0 | L11: =IF($C11,$AD11*1000000+$H11+ROW()/100000,"") -> 2046192 | M11: =IF($C11,IF($AD11=9999,"(Sin sprint)",$AD11),"") -> 2 | N11: =IF($C11,IF('Proyecto Datos (OKR´s)'!$E11="",9999,'Proyecto Datos (OKR´s)'!$E11),"") -> 1 | O11: =IF($C11,"T"&TEXT(ROW(),"000"),"") -> T011 | P11: =ROW()-6 -> 5 | Q11: =IF(COUNTIF($AD$7:$AD$200,$P11)>0,$P11,"") | R11: =IF($C11,IF(ISNUMBER('Proyecto Datos (OKR´s)'!$L11),'Proyecto Datos (OKR´s)'!$L11,$H11),"") -> 46192 | S11: =IF($C11,$R11-'Proyecto Datos (OKR´s)'!$K11+1,"") -> 235 | T11: =IF($C11,MAX(0,TODAY()-'Proyecto Datos (OKR´s)'!$K11),"") -> 234 | U11: =IF($C11,MEDIAN(0,(TODAY()-'Proyecto Datos (OKR´s)'!$K11)/MAX(1,$R11-'Proyecto Datos (OKR´s)'!$K11),1),"") -> 1 | V11: =IF($C11,$I11-$U11,"") -> -0.25 | W11: =IF($C11,IF($J11="Completado",0,MAX(0,TODAY()-$H11)),"") -> 0 | X11: =IF($C11,IF(ISNUMBER($H11),$R11-$H11,0),"") -> 0 | Y11: =IF($C11,COUNTIFS($G$7:$G$200,$G11,$J$7:$J$200,"<>Completado",$J$7:$J$200,"<>"),"") -> 35 | Z11: =IF($C11,AND($I11=0,'Proyecto Datos (OKR´s)'!$K11<=TODAY(),$J11<>"Completado"),"") -> FALSE | AA11: =IF($C11,ROUND(100*(0.35*$AK11+0.3*$AL11+0.2*$AM11+0.15*MEDIAN(0,($Y11-4)/8,1)),0),"") -> 60 | AB11: =IF($C11,IF($J11="Completado","—",IF($AA11>=70,"Crítica",IF($AA11>=45,"Alta",IF($AA11>=25,"Media","Baja")))),"") -> Alta | AC11: =IF($C11,IF(LEN(TRIM($AN11))=0,"—",TRIM($AN11)),"") -> ATRASO SOBRECARGA | AD11: =IF($C11,IF($N11=9999,9999,IF($J11="Completado",$N11,MAX($N11,Sprints!$M$15))),"") -> 2 | AE11: =IF($C11,IF($AD11=9999,"(Sin sprint)",$AD11),"") -> 2 | AF11: =IF($C11,AND($N11<>9999,$AD11<>$N11),FALSE) -> TRUE | AG11: =IF($AF11,$AO11,"") -> 46186 | AH11: =IF($AF11,IF(Sprints!$I11<>"",Sprints!$I11,"Comprometida y no completada al cierre del Sprint "&$N11),"") -> Comprometida y no completada al cierre del Sprint 1 | AI11: =IF($AF11,$N11*100000+ROW(),"") -> 100011 | AJ11: =IF($C11,$AA11*1000000-MEDIAN(-9999,$K11,9999)*100+(300-ROW()),"") -> 60000289 | AK11: =IF($C11,IF($J11="Completado",0,IF($K11<0,1,IF($K11<=3,0.9,IF($K11<=7,0.7,IF($K11<=14,0.45,0.2))))),"") -> 0.9 | AL11: =IF($C11,IF($J11="Completado",0,MEDIAN(0,MAX(-$V11,$W11/30),1)),"") -> 0.25 | AM11: =IF($C11,IF($J11="Completado",0,IF($Z11,1,IF(AND($I11<0.5,$K11<=7),0.7,0.3))),"") -> 0.3 | AN11: =IF($C11,IF(OR($V11<-0.2,$W11>0),"ATRASO ","")&IF($Z11,"BLOQUEO ","")&IF($Y11>8,"SOBRECARGA ","")&IF($X11>0,"DESVÍO-PLAN ",""),"") -> ATRASO SOBRECARGA | AO11: =IF($C11,IFERROR(INDEX(Sprints!$M$6:$M$13,MATCH($N11,Sprints!$K$6:$K$13,0)),""),"") -> 46186 | AP11: =IF($C11,IF(AND($N11<>9999,$AD11<>$N11,ISNUMBER($AO11)),TODAY()-$AO11,0),"") -> 6
A12: =ROW() -> 12 | B12: =ISTEXT('Proyecto Datos (OKR´s)'!$K12) -> FALSE | C12: =AND(LEN('Proyecto Datos (OKR´s)'!$G12)>0,NOT($B12),OR(ISNUMBER('Proyecto Datos (OKR´s)'!$F12),ISNUMBER('Proyecto Datos (OKR´s)'!$L12))) -> TRUE | D12: =IF($C12,IFERROR(LOOKUP(2,1/((ISTEXT('Proyecto Datos (OKR´s)'!$K$7:$K12))*(LEN('Proyecto Datos (OKR´s)'!$G$7:$G12)>0)),'Proyecto Datos (OKR´s)'!$G$7:$G12),""),"") -> 2- Cotizador de Operaciones Complejas | E12: =IF($C12,'Proyecto Datos (OKR´s)'!$E12,"") -> 1 | F12: =IF($C12,'Proyecto Datos (OKR´s)'!$G12,"") -> Automatización Archivo Sueldos Petro + Procedimientos | G12: =IF($C12,IF('Proyecto Datos (OKR´s)'!$I12="","(Sin asignar)",'Proyecto Datos (OKR´s)'!$I12),"") -> Santiago Alonso | H12: =IF($C12,IF(ISNUMBER('Proyecto Datos (OKR´s)'!$F12),'Proyecto Datos (OKR´s)'!$F12,'Proyecto Datos (OKR´s)'!$L12),"") -> 46192 | I12: =IF($C12,'Proyecto Datos (OKR´s)'!$J12,"") -> 0.75 | J12: =IF($C12,IF($I12>=1,"Completado",IF($H12<TODAY(),"Vencido",IF(($H12-TODAY())<='Entregas Próximas'!$M$3,"Próximo a vencer","En curso"))),"") -> Próximo a vencer | K12: =IF($C12,$H12-TODAY(),"") -> 0 | L12: =IF($C12,$AD12*1000000+$H12+ROW()/100000,"") -> 2046192 | M12: =IF($C12,IF($AD12=9999,"(Sin sprint)",$AD12),"") -> 2 | N12: =IF($C12,IF('Proyecto Datos (OKR´s)'!$E12="",9999,'Proyecto Datos (OKR´s)'!$E12),"") -> 1 | O12: =IF($C12,"T"&TEXT(ROW(),"000"),"") -> T012 | P12: =ROW()-6 -> 6 | Q12: =IF(COUNTIF($AD$7:$AD$200,$P12)>0,$P12,"") | R12: =IF($C12,IF(ISNUMBER('Proyecto Datos (OKR´s)'!$L12),'Proyecto Datos (OKR´s)'!$L12,$H12),"") -> 46192 | S12: =IF($C12,$R12-'Proyecto Datos (OKR´s)'!$K12+1,"") -> 215 | T12: =IF($C12,MAX(0,TODAY()-'Proyecto Datos (OKR´s)'!$K12),"") -> 214 | U12: =IF($C12,MEDIAN(0,(TODAY()-'Proyecto Datos (OKR´s)'!$K12)/MAX(1,$R12-'Proyecto Datos (OKR´s)'!$K12),1),"") -> 1 | V12: =IF($C12,$I12-$U12,"") -> -0.25 | W12: =IF($C12,IF($J12="Completado",0,MAX(0,TODAY()-$H12)),"") -> 0 | X12: =IF($C12,IF(ISNUMBER($H12),$R12-$H12,0),"") -> 0 | Y12: =IF($C12,COUNTIFS($G$7:$G$200,$G12,$J$7:$J$200,"<>Completado",$J$7:$J$200,"<>"),"") -> 35 | Z12: =IF($C12,AND($I12=0,'Proyecto Datos (OKR´s)'!$K12<=TODAY(),$J12<>"Completado"),"") -> FALSE | AA12: =IF($C12,ROUND(100*(0.35*$AK12+0.3*$AL12+0.2*$AM12+0.15*MEDIAN(0,($Y12-4)/8,1)),0),"") -> 60 | AB12: =IF($C12,IF($J12="Completado","—",IF($AA12>=70,"Crítica",IF($AA12>=45,"Alta",IF($AA12>=25,"Media","Baja")))),"") -> Alta | AC12: =IF($C12,IF(LEN(TRIM($AN12))=0,"—",TRIM($AN12)),"") -> ATRASO SOBRECARGA | AD12: =IF($C12,IF($N12=9999,9999,IF($J12="Completado",$N12,MAX($N12,Sprints!$M$15))),"") -> 2 | AE12: =IF($C12,IF($AD12=9999,"(Sin sprint)",$AD12),"") -> 2 | AF12: =IF($C12,AND($N12<>9999,$AD12<>$N12),FALSE) -> TRUE | AG12: =IF($AF12,$AO12,"") -> 46186 | AH12: =IF($AF12,IF(Sprints!$I12<>"",Sprints!$I12,"Comprometida y no completada al cierre del Sprint "&$N12),"") -> Comprometida y no completada al cierre del Sprint 1 | AI12: =IF($AF12,$N12*100000+ROW(),"") -> 100012 | AJ12: =IF($C12,$AA12*1000000-MEDIAN(-9999,$K12,9999)*100+(300-ROW()),"") -> 60000288 | AK12: =IF($C12,IF($J12="Completado",0,IF($K12<0,1,IF($K12<=3,0.9,IF($K12<=7,0.7,IF($K12<=14,0.45,0.2))))),"") -> 0.9 | AL12: =IF($C12,IF($J12="Completado",0,MEDIAN(0,MAX(-$V12,$W12/30),1)),"") -> 0.25 | AM12: =IF($C12,IF($J12="Completado",0,IF($Z12,1,IF(AND($I12<0.5,$K12<=7),0.7,0.3))),"") -> 0.3 | AN12: =IF($C12,IF(OR($V12<-0.2,$W12>0),"ATRASO ","")&IF($Z12,"BLOQUEO ","")&IF($Y12>8,"SOBRECARGA ","")&IF($X12>0,"DESVÍO-PLAN ",""),"") -> ATRASO SOBRECARGA | AO12: =IF($C12,IFERROR(INDEX(Sprints!$M$6:$M$13,MATCH($N12,Sprints!$K$6:$K$13,0)),""),"") -> 46186 | AP12: =IF($C12,IF(AND($N12<>9999,$AD12<>$N12,ISNUMBER($AO12)),TODAY()-$AO12,0),"") -> 6
A13: =ROW() -> 13 | B13: =ISTEXT('Proyecto Datos (OKR´s)'!$K13) -> FALSE | C13: =AND(LEN('Proyecto Datos (OKR´s)'!$G13)>0,NOT($B13),OR(ISNUMBER('Proyecto Datos (OKR´s)'!$F13),ISNUMBER('Proyecto Datos (OKR´s)'!$L13))) -> TRUE | D13: =IF($C13,IFERROR(LOOKUP(2,1/((ISTEXT('Proyecto Datos (OKR´s)'!$K$7:$K13))*(LEN('Proyecto Datos (OKR´s)'!$G$7:$G13)>0)),'Proyecto Datos (OKR´s)'!$G$7:$G13),""),"") -> 2- Cotizador de Operaciones Complejas | E13: =IF($C13,'Proyecto Datos (OKR´s)'!$E13,"") -> 1 | F13: =IF($C13,'Proyecto Datos (OKR´s)'!$G13,"") -> Relevamiento Últimos Sueldos de referencia Monotributistas | G13: =IF($C13,IF('Proyecto Datos (OKR´s)'!$I13="","(Sin asignar)",'Proyecto Datos (OKR´s)'!$I13),"") -> Santiago Alonso | H13: =IF($C13,IF(ISNUMBER('Proyecto Datos (OKR´s)'!$F13),'Proyecto Datos (OKR´s)'!$F13,'Proyecto Datos (OKR´s)'!$L13),"") -> 46192 | I13: =IF($C13,'Proyecto Datos (OKR´s)'!$J13,"") -> 0.5 | J13: =IF($C13,IF($I13>=1,"Completado",IF($H13<TODAY(),"Vencido",IF(($H13-TODAY())<='Entregas Próximas'!$M$3,"Próximo a vencer","En curso"))),"") -> Próximo a vencer | K13: =IF($C13,$H13-TODAY(),"") -> 0 | L13: =IF($C13,$AD13*1000000+$H13+ROW()/100000,"") -> 2046192 | M13: =IF($C13,IF($AD13=9999,"(Sin sprint)",$AD13),"") -> 2 | N13: =IF($C13,IF('Proyecto Datos (OKR´s)'!$E13="",9999,'Proyecto Datos (OKR´s)'!$E13),"") -> 1 | O13: =IF($C13,"T"&TEXT(ROW(),"000"),"") -> T013 | P13: =ROW()-6 -> 7 | Q13: =IF(COUNTIF($AD$7:$AD$200,$P13)>0,$P13,"") | R13: =IF($C13,IF(ISNUMBER('Proyecto Datos (OKR´s)'!$L13),'Proyecto Datos (OKR´s)'!$L13,$H13),"") -> 46192 | S13: =IF($C13,$R13-'Proyecto Datos (OKR´s)'!$K13+1,"") -> -152 | T13: =IF($C13,MAX(0,TODAY()-'Proyecto Datos (OKR´s)'!$K13),"") -> 0 | U13: =IF($C13,MEDIAN(0,(TODAY()-'Proyecto Datos (OKR´s)'!$K13)/MAX(1,$R13-'Proyecto Datos (OKR´s)'!$K13),1),"") -> 0 | V13: =IF($C13,$I13-$U13,"") -> 0.5 | W13: =IF($C13,IF($J13="Completado",0,MAX(0,TODAY()-$H13)),"") -> 0 | X13: =IF($C13,IF(ISNUMBER($H13),$R13-$H13,0),"") -> 0 | Y13: =IF($C13,COUNTIFS($G$7:$G$200,$G13,$J$7:$J$200,"<>Completado",$J$7:$J$200,"<>"),"") -> 35 | Z13: =IF($C13,AND($I13=0,'Proyecto Datos (OKR´s)'!$K13<=TODAY(),$J13<>"Completado"),"") -> FALSE | AA13: =IF($C13,ROUND(100*(0.35*$AK13+0.3*$AL13+0.2*$AM13+0.15*MEDIAN(0,($Y13-4)/8,1)),0),"") -> 53 | AB13: =IF($C13,IF($J13="Completado","—",IF($AA13>=70,"Crítica",IF($AA13>=45,"Alta",IF($AA13>=25,"Media","Baja")))),"") -> Alta | AC13: =IF($C13,IF(LEN(TRIM($AN13))=0,"—",TRIM($AN13)),"") -> SOBRECARGA | AD13: =IF($C13,IF($N13=9999,9999,IF($J13="Completado",$N13,MAX($N13,Sprints!$M$15))),"") -> 2 | AE13: =IF($C13,IF($AD13=9999,"(Sin sprint)",$AD13),"") -> 2 | AF13: =IF($C13,AND($N13<>9999,$AD13<>$N13),FALSE) -> TRUE | AG13: =IF($AF13,$AO13,"") -> 46186 | AH13: =IF($AF13,IF(Sprints!$I13<>"",Sprints!$I13,"Comprometida y no completada al cierre del Sprint "&$N13),"") -> Comprometida y no completada al cierre del Sprint 1 | AI13: =IF($AF13,$N13*100000+ROW(),"") -> 100013 | AJ13: =IF($C13,$AA13*1000000-MEDIAN(-9999,$K13,9999)*100+(300-ROW()),"") -> 53000287 | AK13: =IF($C13,IF($J13="Completado",0,IF($K13<0,1,IF($K13<=3,0.9,IF($K13<=7,0.7,IF($K13<=14,0.45,0.2))))),"") -> 0.9 | AL13: =IF($C13,IF($J13="Completado",0,MEDIAN(0,MAX(-$V13,$W13/30),1)),"") -> 0 | AM13: =IF($C13,IF($J13="Completado",0,IF($Z13,1,IF(AND($I13<0.5,$K13<=7),0.7,0.3))),"") -> 0.3 | AN13: =IF($C13,IF(OR($V13<-0.2,$W13>0),"ATRASO ","")&IF($Z13,"BLOQUEO ","")&IF($Y13>8,"SOBRECARGA ","")&IF($X13>0,"DESVÍO-PLAN ",""),"") -> SOBRECARGA | AO13: =IF($C13,IFERROR(INDEX(Sprints!$M$6:$M$13,MATCH($N13,Sprints!$K$6:$K$13,0)),""),"") -> 46186 | AP13: =IF($C13,IF(AND($N13<>9999,$AD13<>$N13,ISNUMBER($AO13)),TODAY()-$AO13,0),"") -> 6
A14: =ROW() -> 14 | B14: =ISTEXT('Proyecto Datos (OKR´s)'!$K14) -> FALSE | C14: =AND(LEN('Proyecto Datos (OKR´s)'!$G14)>0,NOT($B14),OR(ISNUMBER('Proyecto Datos (OKR´s)'!$F14),ISNUMBER('Proyecto Datos (OKR´s)'!$L14))) -> TRUE | D14: =IF($C14,IFERROR(LOOKUP(2,1/((ISTEXT('Proyecto Datos (OKR´s)'!$K$7:$K14))*(LEN('Proyecto Datos (OKR´s)'!$G$7:$G14)>0)),'Proyecto Datos (OKR´s)'!$G$7:$G14),""),"") -> 2- Cotizador de Operaciones Complejas | E14: =IF($C14,'Proyecto Datos (OKR´s)'!$E14,"") -> 0 | F14: =IF($C14,'Proyecto Datos (OKR´s)'!$G14,"") -> Estandarización cotizaciones COMPRAS (costos x provincia) - aguardo información | G14: =IF($C14,IF('Proyecto Datos (OKR´s)'!$I14="","(Sin asignar)",'Proyecto Datos (OKR´s)'!$I14),"") -> Santiago Alonso | H14: =IF($C14,IF(ISNUMBER('Proyecto Datos (OKR´s)'!$F14),'Proyecto Datos (OKR´s)'!$F14,'Proyecto Datos (OKR´s)'!$L14),"") -> 46199 | I14: =IF($C14,'Proyecto Datos (OKR´s)'!$J14,"") -> 0.2 | J14: =IF($C14,IF($I14>=1,"Completado",IF($H14<TODAY(),"Vencido",IF(($H14-TODAY())<='Entregas Próximas'!$M$3,"Próximo a vencer","En curso"))),"") -> Próximo a vencer | K14: =IF($C14,$H14-TODAY(),"") -> 7 | L14: =IF($C14,$AD14*1000000+$H14+ROW()/100000,"") -> 9.9990462e+09 | M14: =IF($C14,IF($AD14=9999,"(Sin sprint)",$AD14),"") -> (Sin sprint) | N14: =IF($C14,IF('Proyecto Datos (OKR´s)'!$E14="",9999,'Proyecto Datos (OKR´s)'!$E14),"") -> 9999 | O14: =IF($C14,"T"&TEXT(ROW(),"000"),"") -> T014 | P14: =ROW()-6 -> 8 | Q14: =IF(COUNTIF($AD$7:$AD$200,$P14)>0,$P14,"") | R14: =IF($C14,IF(ISNUMBER('Proyecto Datos (OKR´s)'!$L14),'Proyecto Datos (OKR´s)'!$L14,$H14),"") -> 46199 | S14: =IF($C14,$R14-'Proyecto Datos (OKR´s)'!$K14+1,"") -> 241 | T14: =IF($C14,MAX(0,TODAY()-'Proyecto Datos (OKR´s)'!$K14),"") -> 233 | U14: =IF($C14,MEDIAN(0,(TODAY()-'Proyecto Datos (OKR´s)'!$K14)/MAX(1,$R14-'Proyecto Datos (OKR´s)'!$K14),1),"") -> 0.97083333 | V14: =IF($C14,$I14-$U14,"") -> -0.77083333 | W14: =IF($C14,IF($J14="Completado",0,MAX(0,TODAY()-$H14)),"") -> 0 | X14: =IF($C14,IF(ISNUMBER($H14),$R14-$H14,0),"") -> 0 | Y14: =IF($C14,COUNTIFS($G$7:$G$200,$G14,$J$7:$J$200,"<>Completado",$J$7:$J$200,"<>"),"") -> 35 | Z14: =IF($C14,AND($I14=0,'Proyecto Datos (OKR´s)'!$K14<=TODAY(),$J14<>"Completado"),"") -> FALSE | AA14: =IF($C14,ROUND(100*(0.35*$AK14+0.3*$AL14+0.2*$AM14+0.15*MEDIAN(0,($Y14-4)/8,1)),0),"") -> 77 | AB14: =IF($C14,IF($J14="Completado","—",IF($AA14>=70,"Crítica",IF($AA14>=45,"Alta",IF($AA14>=25,"Media","Baja")))),"") -> Crítica | AC14: =IF($C14,IF(LEN(TRIM($AN14))=0,"—",TRIM($AN14)),"") -> ATRASO SOBRECARGA | AD14: =IF($C14,IF($N14=9999,9999,IF($J14="Completado",$N14,MAX($N14,Sprints!$M$15))),"") -> 9999 | AE14: =IF($C14,IF($AD14=9999,"(Sin sprint)",$AD14),"") -> (Sin sprint) | AF14: =IF($C14,AND($N14<>9999,$AD14<>$N14),FALSE) -> FALSE | AG14: =IF($AF14,$AO14,"") | AH14: =IF($AF14,IF(Sprints!$I14<>"",Sprints!$I14,"Comprometida y no completada al cierre del Sprint "&$N14),"") | AI14: =IF($AF14,$N14*100000+ROW(),"") | AJ14: =IF($C14,$AA14*1000000-MEDIAN(-9999,$K14,9999)*100+(300-ROW()),"") -> 76999586 | AK14: =IF($C14,IF($J14="Completado",0,IF($K14<0,1,IF($K14<=3,0.9,IF($K14<=7,0.7,IF($K14<=14,0.45,0.2))))),"") -> 0.7 | AL14: =IF($C14,IF($J14="Completado",0,MEDIAN(0,MAX(-$V14,$W14/30),1)),"") -> 0.77083333 | AM14: =IF($C14,IF($J14="Completado",0,IF($Z14,1,IF(AND($I14<0.5,$K14<=7),0.7,0.3))),"") -> 0.7 | AN14: =IF($C14,IF(OR($V14<-0.2,$W14>0),"ATRASO ","")&IF($Z14,"BLOQUEO ","")&IF($Y14>8,"SOBRECARGA ","")&IF($X14>0,"DESVÍO-PLAN ",""),"") -> ATRASO SOBRECARGA | AO14: =IF($C14,IFERROR(INDEX(Sprints!$M$6:$M$13,MATCH($N14,Sprints!$K$6:$K$13,0)),""),"") | AP14: =IF($C14,IF(AND($N14<>9999,$AD14<>$N14,ISNUMBER($AO14)),TODAY()-$AO14,0),"") -> 0
A15: =ROW() -> 15 | B15: =ISTEXT('Proyecto Datos (OKR´s)'!$K15) -> FALSE | C15: =AND(LEN('Proyecto Datos (OKR´s)'!$G15)>0,NOT($B15),OR(ISNUMBER('Proyecto Datos (OKR´s)'!$F15),ISNUMBER('Proyecto Datos (OKR´s)'!$L15))) -> TRUE | D15: =IF($C15,IFERROR(LOOKUP(2,1/((ISTEXT('Proyecto Datos (OKR´s)'!$K$7:$K15))*(LEN('Proyecto Datos (OKR´s)'!$G$7:$G15)>0)),'Proyecto Datos (OKR´s)'!$G$7:$G15),""),"") -> 2- Cotizador de Operaciones Complejas | E15: =IF($C15,'Proyecto Datos (OKR´s)'!$E15,"") -> 1 | F15: =IF($C15,'Proyecto Datos (OKR´s)'!$G15,"") -> Asociar Archivo Móviles y Tráilers (Nico Sifuentes) + procedimiento | G15: =IF($C15,IF('Proyecto Datos (OKR´s)'!$I15="","(Sin asignar)",'Proyecto Datos (OKR´s)'!$I15),"") -> Santiago Alonso | H15: =IF($C15,IF(ISNUMBER('Proyecto Datos (OKR´s)'!$F15),'Proyecto Datos (OKR´s)'!$F15,'Proyecto Datos (OKR´s)'!$L15),"") -> 46192 | I15: =IF($C15,'Proyecto Datos (OKR´s)'!$J15,"") -> 0.95 | J15: =IF($C15,IF($I15>=1,"Completado",IF($H15<TODAY(),"Vencido",IF(($H15-TODAY())<='Entregas Próximas'!$M$3,"Próximo a vencer","En curso"))),"") -> Próximo a vencer | K15: =IF($C15,$H15-TODAY(),"") -> 0 | L15: =IF($C15,$AD15*1000000+$H15+ROW()/100000,"") -> 2046192 | M15: =IF($C15,IF($AD15=9999,"(Sin sprint)",$AD15),"") -> 2 | N15: =IF($C15,IF('Proyecto Datos (OKR´s)'!$E15="",9999,'Proyecto Datos (OKR´s)'!$E15),"") -> 1 | O15: =IF($C15,"T"&TEXT(ROW(),"000"),"") -> T015 | P15: =ROW()-6 -> 9 | Q15: =IF(COUNTIF($AD$7:$AD$200,$P15)>0,$P15,"") | R15: =IF($C15,IF(ISNUMBER('Proyecto Datos (OKR´s)'!$L15),'Proyecto Datos (OKR´s)'!$L15,$H15),"") -> 46192 | S15: =IF($C15,$R15-'Proyecto Datos (OKR´s)'!$K15+1,"") -> 201 | T15: =IF($C15,MAX(0,TODAY()-'Proyecto Datos (OKR´s)'!$K15),"") -> 200 | U15: =IF($C15,MEDIAN(0,(TODAY()-'Proyecto Datos (OKR´s)'!$K15)/MAX(1,$R15-'Proyecto Datos (OKR´s)'!$K15),1),"") -> 1 | V15: =IF($C15,$I15-$U15,"") -> -0.05 | W15: =IF($C15,IF($J15="Completado",0,MAX(0,TODAY()-$H15)),"") -> 0 | X15: =IF($C15,IF(ISNUMBER($H15),$R15-$H15,0),"") -> 0 | Y15: =IF($C15,COUNTIFS($G$7:$G$200,$G15,$J$7:$J$200,"<>Completado",$J$7:$J$200,"<>"),"") -> 35 | Z15: =IF($C15,AND($I15=0,'Proyecto Datos (OKR´s)'!$K15<=TODAY(),$J15<>"Completado"),"") -> FALSE | AA15: =IF($C15,ROUND(100*(0.35*$AK15+0.3*$AL15+0.2*$AM15+0.15*MEDIAN(0,($Y15-4)/8,1)),0),"") -> 54 | AB15: =IF($C15,IF($J15="Completado","—",IF($AA15>=70,"Crítica",IF($AA15>=45,"Alta",IF($AA15>=25,"Media","Baja")))),"") -> Alta | AC15: =IF($C15,IF(LEN(TRIM($AN15))=0,"—",TRIM($AN15)),"") -> SOBRECARGA | AD15: =IF($C15,IF($N15=9999,9999,IF($J15="Completado",$N15,MAX($N15,Sprints!$M$15))),"") -> 2 | AE15: =IF($C15,IF($AD15=9999,"(Sin sprint)",$AD15),"") -> 2 | AF15: =IF($C15,AND($N15<>9999,$AD15<>$N15),FALSE) -> TRUE | AG15: =IF($AF15,$AO15,"") -> 46186 | AH15: =IF($AF15,IF(Sprints!$I15<>"",Sprints!$I15,"Comprometida y no completada al cierre del Sprint "&$N15),"") -> Comprometida y no completada al cierre del Sprint 1 | AI15: =IF($AF15,$N15*100000+ROW(),"") -> 100015 | AJ15: =IF($C15,$AA15*1000000-MEDIAN(-9999,$K15,9999)*100+(300-ROW()),"") -> 54000285 | AK15: =IF($C15,IF($J15="Completado",0,IF($K15<0,1,IF($K15<=3,0.9,IF($K15<=7,0.7,IF($K15<=14,0.45,0.2))))),"") -> 0.9 | AL15: =IF($C15,IF($J15="Completado",0,MEDIAN(0,MAX(-$V15,$W15/30),1)),"") -> 0.05 | AM15: =IF($C15,IF($J15="Completado",0,IF($Z15,1,IF(AND($I15<0.5,$K15<=7),0.7,0.3))),"") -> 0.3 | AN15: =IF($C15,IF(OR($V15<-0.2,$W15>0),"ATRASO ","")&IF($Z15,"BLOQUEO ","")&IF($Y15>8,"SOBRECARGA ","")&IF($X15>0,"DESVÍO-PLAN ",""),"") -> SOBRECARGA | AO15: =IF($C15,IFERROR(INDEX(Sprints!$M$6:$M$13,MATCH($N15,Sprints!$K$6:$K$13,0)),""),"") -> 46186 | AP15: =IF($C15,IF(AND($N15<>9999,$AD15<>$N15,ISNUMBER($AO15)),TODAY()-$AO15,0),"") -> 6
A16: =ROW() -> 16 | B16: =ISTEXT('Proyecto Datos (OKR´s)'!$K16) -> FALSE | C16: =AND(LEN('Proyecto Datos (OKR´s)'!$G16)>0,NOT($B16),OR(ISNUMBER('Proyecto Datos (OKR´s)'!$F16),ISNUMBER('Proyecto Datos (OKR´s)'!$L16))) -> TRUE | D16: =IF($C16,IFERROR(LOOKUP(2,1/((ISTEXT('Proyecto Datos (OKR´s)'!$K$7:$K16))*(LEN('Proyecto Datos (OKR´s)'!$G$7:$G16)>0)),'Proyecto Datos (OKR´s)'!$G$7:$G16),""),"") -> 2- Cotizador de Operaciones Complejas | E16: =IF($C16,'Proyecto Datos (OKR´s)'!$E16,"") -> 1 | F16: =IF($C16,'Proyecto Datos (OKR´s)'!$G16,"") -> Asociar Archivo Masters de Medicación (Seba Oliver) + Capacitaciones + procedimiento | G16: =IF($C16,IF('Proyecto Datos (OKR´s)'!$I16="","(Sin asignar)",'Proyecto Datos (OKR´s)'!$I16),"") -> Santiago Alonso | H16: =IF($C16,IF(ISNUMBER('Proyecto Datos (OKR´s)'!$F16),'Proyecto Datos (OKR´s)'!$F16,'Proyecto Datos (OKR´s)'!$L16),"") -> 46192 | I16: =IF($C16,'Proyecto Datos (OKR´s)'!$J16,"") -> 0.65 | J16: =IF($C16,IF($I16>=1,"Completado",IF($H16<TODAY(),"Vencido",IF(($H16-TODAY())<='Entregas Próximas'!$M$3,"Próximo a vencer","En curso"))),"") -> Próximo a vencer | K16: =IF($C16,$H16-TODAY(),"") -> 0 | L16: =IF($C16,$AD16*1000000+$H16+ROW()/100000,"") -> 2046192 | M16: =IF($C16,IF($AD16=9999,"(Sin sprint)",$AD16),"") -> 2 | N16: =IF($C16,IF('Proyecto Datos (OKR´s)'!$E16="",9999,'Proyecto Datos (OKR´s)'!$E16),"") -> 1 | O16: =IF($C16,"T"&TEXT(ROW(),"000"),"") -> T016 | P16: =ROW()-6 -> 10 | Q16: =IF(COUNTIF($AD$7:$AD$200,$P16)>0,$P16,"") | R16: =IF($C16,IF(ISNUMBER('Proyecto Datos (OKR´s)'!$L16),'Proyecto Datos (OKR´s)'!$L16,$H16),"") -> 46192 | S16: =IF($C16,$R16-'Proyecto Datos (OKR´s)'!$K16+1,"") -> 201 | T16: =IF($C16,MAX(0,TODAY()-'Proyecto Datos (OKR´s)'!$K16),"") -> 200 | U16: =IF($C16,MEDIAN(0,(TODAY()-'Proyecto Datos (OKR´s)'!$K16)/MAX(1,$R16-'Proyecto Datos (OKR´s)'!$K16),1),"") -> 1 | V16: =IF($C16,$I16-$U16,"") -> -0.35 | W16: =IF($C16,IF($J16="Completado",0,MAX(0,TODAY()-$H16)),"") -> 0 | X16: =IF($C16,IF(ISNUMBER($H16),$R16-$H16,0),"") -> 0 | Y16: =IF($C16,COUNTIFS($G$7:$G$200,$G16,$J$7:$J$200,"<>Completado",$J$7:$J$200,"<>"),"") -> 35 | Z16: =IF($C16,AND($I16=0,'Proyecto Datos (OKR´s)'!$K16<=TODAY(),$J16<>"Completado"),"") -> FALSE | AA16: =IF($C16,ROUND(100*(0.35*$AK16+0.3*$AL16+0.2*$AM16+0.15*MEDIAN(0,($Y16-4)/8,1)),0),"") -> 63 | AB16: =IF($C16,IF($J16="Completado","—",IF($AA16>=70,"Crítica",IF($AA16>=45,"Alta",IF($AA16>=25,"Media","Baja")))),"") -> Alta | AC16: =IF($C16,IF(LEN(TRIM($AN16))=0,"—",TRIM($AN16)),"") -> ATRASO SOBRECARGA | AD16: =IF($C16,IF($N16=9999,9999,IF($J16="Completado",$N16,MAX($N16,Sprints!$M$15))),"") -> 2 | AE16: =IF($C16,IF($AD16=9999,"(Sin sprint)",$AD16),"") -> 2 | AF16: =IF($C16,AND($N16<>9999,$AD16<>$N16),FALSE) -> TRUE | AG16: =IF($AF16,$AO16,"") -> 46186 | AH16: =IF($AF16,IF(Sprints!$I16<>"",Sprints!$I16,"Comprometida y no completada al cierre del Sprint "&$N16),"") -> Comprometida y no completada al cierre del Sprint 1 | AI16: =IF($AF16,$N16*100000+ROW(),"") -> 100016 | AJ16: =IF($C16,$AA16*1000000-MEDIAN(-9999,$K16,9999)*100+(300-ROW()),"") -> 63000284 | AK16: =IF($C16,IF($J16="Completado",0,IF($K16<0,1,IF($K16<=3,0.9,IF($K16<=7,0.7,IF($K16<=14,0.45,0.2))))),"") -> 0.9 | AL16: =IF($C16,IF($J16="Completado",0,MEDIAN(0,MAX(-$V16,$W16/30),1)),"") -> 0.35 | AM16: =IF($C16,IF($J16="Completado",0,IF($Z16,1,IF(AND($I16<0.5,$K16<=7),0.7,0.3))),"") -> 0.3 | AN16: =IF($C16,IF(OR($V16<-0.2,$W16>0),"ATRASO ","")&IF($Z16,"BLOQUEO ","")&IF($Y16>8,"SOBRECARGA ","")&IF($X16>0,"DESVÍO-PLAN ",""),"") -> ATRASO SOBRECARGA | AO16: =IF($C16,IFERROR(INDEX(Sprints!$M$6:$M$13,MATCH($N16,Sprints!$K$6:$K$13,0)),""),"") -> 46186 | AP16: =IF($C16,IF(AND($N16<>9999,$AD16<>$N16,ISNUMBER($AO16)),TODAY()-$AO16,0),"") -> 6
A17: =ROW() -> 17 | B17: =ISTEXT('Proyecto Datos (OKR´s)'!$K17) -> FALSE | C17: =AND(LEN('Proyecto Datos (OKR´s)'!$G17)>0,NOT($B17),OR(ISNUMBER('Proyecto Datos (OKR´s)'!$F17),ISNUMBER('Proyecto Datos (OKR´s)'!$L17))) -> TRUE | D17: =IF($C17,IFERROR(LOOKUP(2,1/((ISTEXT('Proyecto Datos (OKR´s)'!$K$7:$K17))*(LEN('Proyecto Datos (OKR´s)'!$G$7:$G17)>0)),'Proyecto Datos (OKR´s)'!$G$7:$G17),""),"") -> 2- Cotizador de Operaciones Complejas | E17: =IF($C17,'Proyecto Datos (OKR´s)'!$E17,"") -> 0 | F17: =IF($C17,'Proyecto Datos (OKR´s)'!$G17,"") -> Asociar Gastos de Estructura (% de incidencia) | G17: =IF($C17,IF('Proyecto Datos (OKR´s)'!$I17="","(Sin asignar)",'Proyecto Datos (OKR´s)'!$I17),"") -> Santiago Alonso | H17: =IF($C17,IF(ISNUMBER('Proyecto Datos (OKR´s)'!$F17),'Proyecto Datos (OKR´s)'!$F17,'Proyecto Datos (OKR´s)'!$L17),"") -> 46206 | I17: =IF($C17,'Proyecto Datos (OKR´s)'!$J17,"") -> 0 | J17: =IF($C17,IF($I17>=1,"Completado",IF($H17<TODAY(),"Vencido",IF(($H17-TODAY())<='Entregas Próximas'!$M$3,"Próximo a vencer","En curso"))),"") -> En curso | K17: =IF($C17,$H17-TODAY(),"") -> 14 | L17: =IF($C17,$AD17*1000000+$H17+ROW()/100000,"") -> 9.9990462e+09 | M17: =IF($C17,IF($AD17=9999,"(Sin sprint)",$AD17),"") -> (Sin sprint) | N17: =IF($C17,IF('Proyecto Datos (OKR´s)'!$E17="",9999,'Proyecto Datos (OKR´s)'!$E17),"") -> 9999 | O17: =IF($C17,"T"&TEXT(ROW(),"000"),"") -> T017 | P17: =ROW()-6 -> 11 | Q17: =IF(COUNTIF($AD$7:$AD$200,$P17)>0,$P17,"") | R17: =IF($C17,IF(ISNUMBER('Proyecto Datos (OKR´s)'!$L17),'Proyecto Datos (OKR´s)'!$L17,$H17),"") -> 46206 | S17: =IF($C17,$R17-'Proyecto Datos (OKR´s)'!$K17+1,"") -> 7 | T17: =IF($C17,MAX(0,TODAY()-'Proyecto Datos (OKR´s)'!$K17),"") -> 0 | U17: =IF($C17,MEDIAN(0,(TODAY()-'Proyecto Datos (OKR´s)'!$K17)/MAX(1,$R17-'Proyecto Datos (OKR´s)'!$K17),1),"") -> 0 | V17: =IF($C17,$I17-$U17,"") -> 0 | W17: =IF($C17,IF($J17="Completado",0,MAX(0,TODAY()-$H17)),"") -> 0 | X17: =IF($C17,IF(ISNUMBER($H17),$R17-$H17,0),"") -> 0 | Y17: =IF($C17,COUNTIFS($G$7:$G$200,$G17,$J$7:$J$200,"<>Completado",$J$7:$J$200,"<>"),"") -> 35 | Z17: =IF($C17,AND($I17=0,'Proyecto Datos (OKR´s)'!$K17<=TODAY(),$J17<>"Completado"),"") -> FALSE | AA17: =IF($C17,ROUND(100*(0.35*$AK17+0.3*$AL17+0.2*$AM17+0.15*MEDIAN(0,($Y17-4)/8,1)),0),"") -> 37 | AB17: =IF($C17,IF($J17="Completado","—",IF($AA17>=70,"Crítica",IF($AA17>=45,"Alta",IF($AA17>=25,"Media","Baja")))),"") -> Media | AC17: =IF($C17,IF(LEN(TRIM($AN17))=0,"—",TRIM($AN17)),"") -> SOBRECARGA | AD17: =IF($C17,IF($N17=9999,9999,IF($J17="Completado",$N17,MAX($N17,Sprints!$M$15))),"") -> 9999 | AE17: =IF($C17,IF($AD17=9999,"(Sin sprint)",$AD17),"") -> (Sin sprint) | AF17: =IF($C17,AND($N17<>9999,$AD17<>$N17),FALSE) -> FALSE | AG17: =IF($AF17,$AO17,"") | AH17: =IF($AF17,IF(Sprints!$I17<>"",Sprints!$I17,"Comprometida y no completada al cierre del Sprint "&$N17),"") | AI17: =IF($AF17,$N17*100000+ROW(),"") | AJ17: =IF($C17,$AA17*1000000-MEDIAN(-9999,$K17,9999)*100+(300-ROW()),"") -> 36998883 | AK17: =IF($C17,IF($J17="Completado",0,IF($K17<0,1,IF($K17<=3,0.9,IF($K17<=7,0.7,IF($K17<=14,0.45,0.2))))),"") -> 0.45 | AL17: =IF($C17,IF($J17="Completado",0,MEDIAN(0,MAX(-$V17,$W17/30),1)),"") -> 0 | AM17: =IF($C17,IF($J17="Completado",0,IF($Z17,1,IF(AND($I17<0.5,$K17<=7),0.7,0.3))),"") -> 0.3 | AN17: =IF($C17,IF(OR($V17<-0.2,$W17>0),"ATRASO ","")&IF($Z17,"BLOQUEO ","")&IF($Y17>8,"SOBRECARGA ","")&IF($X17>0,"DESVÍO-PLAN ",""),"") -> SOBRECARGA | AO17: =IF($C17,IFERROR(INDEX(Sprints!$M$6:$M$13,MATCH($N17,Sprints!$K$6:$K$13,0)),""),"") | AP17: =IF($C17,IF(AND($N17<>9999,$AD17<>$N17,ISNUMBER($AO17)),TODAY()-$AO17,0),"") -> 0
A18: =ROW() -> 18 | B18: =ISTEXT('Proyecto Datos (OKR´s)'!$K18) -> FALSE | C18: =AND(LEN('Proyecto Datos (OKR´s)'!$G18)>0,NOT($B18),OR(ISNUMBER('Proyecto Datos (OKR´s)'!$F18),ISNUMBER('Proyecto Datos (OKR´s)'!$L18))) -> TRUE | D18: =IF($C18,IFERROR(LOOKUP(2,1/((ISTEXT('Proyecto Datos (OKR´s)'!$K$7:$K18))*(LEN('Proyecto Datos (OKR´s)'!$G$7:$G18)>0)),'Proyecto Datos (OKR´s)'!$G$7:$G18),""),"") -> 2- Cotizador de Operaciones Complejas | E18: =IF($C18,'Proyecto Datos (OKR´s)'!$E18,"") -> 0 | F18: =IF($C18,'Proyecto Datos (OKR´s)'!$G18,"") -> Armado de solicitudes extra x Módulos (Ej: Med. Laboral) | G18: =IF($C18,IF('Proyecto Datos (OKR´s)'!$I18="","(Sin asignar)",'Proyecto Datos (OKR´s)'!$I18),"") -> Santiago Alonso | H18: =IF($C18,IF(ISNUMBER('Proyecto Datos (OKR´s)'!$F18),'Proyecto Datos (OKR´s)'!$F18,'Proyecto Datos (OKR´s)'!$L18),"") -> 46213 | I18: =IF($C18,'Proyecto Datos (OKR´s)'!$J18,"") -> 0 | J18: =IF($C18,IF($I18>=1,"Completado",IF($H18<TODAY(),"Vencido",IF(($H18-TODAY())<='Entregas Próximas'!$M$3,"Próximo a vencer","En curso"))),"") -> En curso | K18: =IF($C18,$H18-TODAY(),"") -> 21 | L18: =IF($C18,$AD18*1000000+$H18+ROW()/100000,"") -> 9.9990462e+09 | M18: =IF($C18,IF($AD18=9999,"(Sin sprint)",$AD18),"") -> (Sin sprint) | N18: =IF($C18,IF('Proyecto Datos (OKR´s)'!$E18="",9999,'Proyecto Datos (OKR´s)'!$E18),"") -> 9999 | O18: =IF($C18,"T"&TEXT(ROW(),"000"),"") -> T018 | P18: =ROW()-6 -> 12 | Q18: =IF(COUNTIF($AD$7:$AD$200,$P18)>0,$P18,"") | R18: =IF($C18,IF(ISNUMBER('Proyecto Datos (OKR´s)'!$L18),'Proyecto Datos (OKR´s)'!$L18,$H18),"") -> 46213 | S18: =IF($C18,$R18-'Proyecto Datos (OKR´s)'!$K18+1,"") -> 21 | T18: =IF($C18,MAX(0,TODAY()-'Proyecto Datos (OKR´s)'!$K18),"") -> 0 | U18: =IF($C18,MEDIAN(0,(TODAY()-'Proyecto Datos (OKR´s)'!$K18)/MAX(1,$R18-'Proyecto Datos (OKR´s)'!$K18),1),"") -> 0 | V18: =IF($C18,$I18-$U18,"") -> 0 | W18: =IF($C18,IF($J18="Completado",0,MAX(0,TODAY()-$H18)),"") -> 0 | X18: =IF($C18,IF(ISNUMBER($H18),$R18-$H18,0),"") -> 0 | Y18: =IF($C18,COUNTIFS($G$7:$G$200,$G18,$J$7:$J$200,"<>Completado",$J$7:$J$200,"<>"),"") -> 35 | Z18: =IF($C18,AND($I18=0,'Proyecto Datos (OKR´s)'!$K18<=TODAY(),$J18<>"Completado"),"") -> FALSE | AA18: =IF($C18,ROUND(100*(0.35*$AK18+0.3*$AL18+0.2*$AM18+0.15*MEDIAN(0,($Y18-4)/8,1)),0),"") -> 28 | AB18: =IF($C18,IF($J18="Completado","—",IF($AA18>=70,"Crítica",IF($AA18>=45,"Alta",IF($AA18>=25,"Media","Baja")))),"") -> Media | AC18: =IF($C18,IF(LEN(TRIM($AN18))=0,"—",TRIM($AN18)),"") -> SOBRECARGA | AD18: =IF($C18,IF($N18=9999,9999,IF($J18="Completado",$N18,MAX($N18,Sprints!$M$15))),"") -> 9999 | AE18: =IF($C18,IF($AD18=9999,"(Sin sprint)",$AD18),"") -> (Sin sprint) | AF18: =IF($C18,AND($N18<>9999,$AD18<>$N18),FALSE) -> FALSE | AG18: =IF($AF18,$AO18,"") | AH18: =IF($AF18,IF(Sprints!$I18<>"",Sprints!$I18,"Comprometida y no completada al cierre del Sprint "&$N18),"") | AI18: =IF($AF18,$N18*100000+ROW(),"") | AJ18: =IF($C18,$AA18*1000000-MEDIAN(-9999,$K18,9999)*100+(300-ROW()),"") -> 27998182 | AK18: =IF($C18,IF($J18="Completado",0,IF($K18<0,1,IF($K18<=3,0.9,IF($K18<=7,0.7,IF($K18<=14,0.45,0.2))))),"") -> 0.2 | AL18: =IF($C18,IF($J18="Completado",0,MEDIAN(0,MAX(-$V18,$W18/30),1)),"") -> 0 | AM18: =IF($C18,IF($J18="Completado",0,IF($Z18,1,IF(AND($I18<0.5,$K18<=7),0.7,0.3))),"") -> 0.3 | AN18: =IF($C18,IF(OR($V18<-0.2,$W18>0),"ATRASO ","")&IF($Z18,"BLOQUEO ","")&IF($Y18>8,"SOBRECARGA ","")&IF($X18>0,"DESVÍO-PLAN ",""),"") -> SOBRECARGA | AO18: =IF($C18,IFERROR(INDEX(Sprints!$M$6:$M$13,MATCH($N18,Sprints!$K$6:$K$13,0)),""),"") | AP18: =IF($C18,IF(AND($N18<>9999,$AD18<>$N18,ISNUMBER($AO18)),TODAY()-$AO18,0),"") -> 0
... A36: =ROW() -> 36 | B36: =ISTEXT('Proyecto Datos (OKR´s)'!$K36) -> TRUE | C36: =AND(LEN('Proyecto Datos (OKR´s)'!$G36)>0,NOT($B36),OR(ISNUMBER('Proyecto Datos (OKR´s)'!$F36),ISNUMBER('Proyecto Datos (OKR´s)'!$L36))) -> FALSE | D36: =IF($C36,IFERROR(LOOKUP(2,1/((ISTEXT('Proyecto Datos (OKR´s)'!$K$7:$K36))*(LEN('Proyecto Datos (OKR´s)'!$G$7:$G36)>0)),'Proyecto Datos (OKR´s)'!$G$7:$G36),""),"") | E36: =IF($C36,'Proyecto Datos (OKR´s)'!$E36,"") | F36: =IF($C36,'Proyecto Datos (OKR´s)'!$G36,"") | G36: =IF($C36,IF('Proyecto Datos (OKR´s)'!$I36="","(Sin asignar)",'Proyecto Datos (OKR´s)'!$I36),"") | H36: =IF($C36,IF(ISNUMBER('Proyecto Datos (OKR´s)'!$F36),'Proyecto Datos (OKR´s)'!$F36,'Proyecto Datos (OKR´s)'!$L36),"") | I36: =IF($C36,'Proyecto Datos (OKR´s)'!$J36,"") | J36: =IF($C36,IF($I36>=1,"Completado",IF($H36<TODAY(),"Vencido",IF(($H36-TODAY())<='Entregas Próximas'!$M$3,"Próximo a vencer","En curso"))),"") | K36: =IF($C36,$H36-TODAY(),"") | L36: =IF($C36,$AD36*1000000+$H36+ROW()/100000,"") | M36: =IF($C36,IF($AD36=9999,"(Sin sprint)",$AD36),"") | N36: =IF($C36,IF('Proyecto Datos (OKR´s)'!$E36="",9999,'Proyecto Datos (OKR´s)'!$E36),"") | O36: =IF($C36,"T"&TEXT(ROW(),"000"),"") | P36: =ROW()-6 -> 30 | Q36: =IF(COUNTIF($AD$7:$AD$200,$P36)>0,$P36,"") | R36: =IF($C36,IF(ISNUMBER('Proyecto Datos (OKR´s)'!$L36),'Proyecto Datos (OKR´s)'!$L36,$H36),"") | S36: =IF($C36,$R36-'Proyecto Datos (OKR´s)'!$K36+1,"") | T36: =IF($C36,MAX(0,TODAY()-'Proyecto Datos (OKR´s)'!$K36),"") | U36: =IF($C36,MEDIAN(0,(TODAY()-'Proyecto Datos (OKR´s)'!$K36)/MAX(1,$R36-'Proyecto Datos (OKR´s)'!$K36),1),"") | V36: =IF($C36,$I36-$U36,"") | W36: =IF($C36,IF($J36="Completado",0,MAX(0,TODAY()-$H36)),"") | X36: =IF($C36,IF(ISNUMBER($H36),$R36-$H36,0),"") | Y36: =IF($C36,COUNTIFS($G$7:$G$200,$G36,$J$7:$J$200,"<>Completado",$J$7:$J$200,"<>"),"") | Z36: =IF($C36,AND($I36=0,'Proyecto Datos (OKR´s)'!$K36<=TODAY(),$J36<>"Completado"),"") | AA36: =IF($C36,ROUND(100*(0.35*$AK36+0.3*$AL36+0.2*$AM36+0.15*MEDIAN(0,($Y36-4)/8,1)),0),"") | AB36: =IF($C36,IF($J36="Completado","—",IF($AA36>=70,"Crítica",IF($AA36>=45,"Alta",IF($AA36>=25,"Media","Baja")))),"") | AC36: =IF($C36,IF(LEN(TRIM($AN36))=0,"—",TRIM($AN36)),"") | AD36: =IF($C36,IF($N36=9999,9999,IF($J36="Completado",$N36,MAX($N36,Sprints!$M$15))),"") | AE36: =IF($C36,IF($AD36=9999,"(Sin sprint)",$AD36),"") | AF36: =IF($C36,AND($N36<>9999,$AD36<>$N36),FALSE) -> FALSE | AG36: =IF($AF36,$AO36,"") | AH36: =IF($AF36,IF(Sprints!$I36<>"",Sprints!$I36,"Comprometida y no completada al cierre del Sprint "&$N36),"") | AI36: =IF($AF36,$N36*100000+ROW(),"") | AJ36: =IF($C36,$AA36*1000000-MEDIAN(-9999,$K36,9999)*100+(300-ROW()),"") | AK36: =IF($C36,IF($J36="Completado",0,IF($K36<0,1,IF($K36<=3,0.9,IF($K36<=7,0.7,IF($K36<=14,0.45,0.2))))),"") | AL36: =IF($C36,IF($J36="Completado",0,MEDIAN(0,MAX(-$V36,$W36/30),1)),"") | AM36: =IF($C36,IF($J36="Completado",0,IF($Z36,1,IF(AND($I36<0.5,$K36<=7),0.7,0.3))),"") | AN36: =IF($C36,IF(OR($V36<-0.2,$W36>0),"ATRASO ","")&IF($Z36,"BLOQUEO ","")&IF($Y36>8,"SOBRECARGA ","")&IF($X36>0,"DESVÍO-PLAN ",""),"") | AO36: =IF($C36,IFERROR(INDEX(Sprints!$M$6:$M$13,MATCH($N36,Sprints!$K$6:$K$13,0)),""),"") | AP36: =IF($C36,IF(AND($N36<>9999,$AD36<>$N36,ISNUMBER($AO36)),TODAY()-$AO36,0),"")
A37: =ROW() -> 37 | B37: =ISTEXT('Proyecto Datos (OKR´s)'!$K37) -> FALSE | C37: =AND(LEN('Proyecto Datos (OKR´s)'!$G37)>0,NOT($B37),OR(ISNUMBER('Proyecto Datos (OKR´s)'!$F37),ISNUMBER('Proyecto Datos (OKR´s)'!$L37))) -> TRUE | D37: =IF($C37,IFERROR(LOOKUP(2,1/((ISTEXT('Proyecto Datos (OKR´s)'!$K$7:$K37))*(LEN('Proyecto Datos (OKR´s)'!$G$7:$G37)>0)),'Proyecto Datos (OKR´s)'!$G$7:$G37),""),"") -> 5- Tablero Control General - Op. Complejas | E37: =IF($C37,'Proyecto Datos (OKR´s)'!$E37,"") -> 1 | F37: =IF($C37,'Proyecto Datos (OKR´s)'!$G37,"") -> Planilla Activos Unificados - Estandarizar + Procedimiento | G37: =IF($C37,IF('Proyecto Datos (OKR´s)'!$I37="","(Sin asignar)",'Proyecto Datos (OKR´s)'!$I37),"") -> Santiago Alonso | H37: =IF($C37,IF(ISNUMBER('Proyecto Datos (OKR´s)'!$F37),'Proyecto Datos (OKR´s)'!$F37,'Proyecto Datos (OKR´s)'!$L37),"") -> 46185 | I37: =IF($C37,'Proyecto Datos (OKR´s)'!$J37,"") -> 0.2 | J37: =IF($C37,IF($I37>=1,"Completado",IF($H37<TODAY(),"Vencido",IF(($H37-TODAY())<='Entregas Próximas'!$M$3,"Próximo a vencer","En curso"))),"") -> Vencido | K37: =IF($C37,$H37-TODAY(),"") -> -7 | L37: =IF($C37,$AD37*1000000+$H37+ROW()/100000,"") -> 2046185 | M37: =IF($C37,IF($AD37=9999,"(Sin sprint)",$AD37),"") -> 2 | N37: =IF($C37,IF('Proyecto Datos (OKR´s)'!$E37="",9999,'Proyecto Datos (OKR´s)'!$E37),"") -> 1 | O37: =IF($C37,"T"&TEXT(ROW(),"000"),"") -> T037 | P37: 9999 | Q37: =IF(COUNTIF($AD$7:$AD$200,9999)>0,9999,"") -> 9999 | R37: =IF($C37,IF(ISNUMBER('Proyecto Datos (OKR´s)'!$L37),'Proyecto Datos (OKR´s)'!$L37,$H37),"") -> 46185 | S37: =IF($C37,$R37-'Proyecto Datos (OKR´s)'!$K37+1,"") -> 194 | T37: =IF($C37,MAX(0,TODAY()-'Proyecto Datos (OKR´s)'!$K37),"") -> 200 | U37: =IF($C37,MEDIAN(0,(TODAY()-'Proyecto Datos (OKR´s)'!$K37)/MAX(1,$R37-'Proyecto Datos (OKR´s)'!$K37),1),"") -> 1 | V37: =IF($C37,$I37-$U37,"") -> -0.8 | W37: =IF($C37,IF($J37="Completado",0,MAX(0,TODAY()-$H37)),"") -> 7 | X37: =IF($C37,IF(ISNUMBER($H37),$R37-$H37,0),"") -> 0 | Y37: =IF($C37,COUNTIFS($G$7:$G$200,$G37,$J$7:$J$200,"<>Completado",$J$7:$J$200,"<>"),"") -> 35 | Z37: =IF($C37,AND($I37=0,'Proyecto Datos (OKR´s)'!$K37<=TODAY(),$J37<>"Completado"),"") -> FALSE | AA37: =IF($C37,ROUND(100*(0.35*$AK37+0.3*$AL37+0.2*$AM37+0.15*MEDIAN(0,($Y37-4)/8,1)),0),"") -> 88 | AB37: =IF($C37,IF($J37="Completado","—",IF($AA37>=70,"Crítica",IF($AA37>=45,"Alta",IF($AA37>=25,"Media","Baja")))),"") -> Crítica | AC37: =IF($C37,IF(LEN(TRIM($AN37))=0,"—",TRIM($AN37)),"") -> ATRASO SOBRECARGA | AD37: =IF($C37,IF($N37=9999,9999,IF($J37="Completado",$N37,MAX($N37,Sprints!$M$15))),"") -> 2 | AE37: =IF($C37,IF($AD37=9999,"(Sin sprint)",$AD37),"") -> 2 | AF37: =IF($C37,AND($N37<>9999,$AD37<>$N37),FALSE) -> TRUE | AG37: =IF($AF37,$AO37,"") -> 46186 | AH37: =IF($AF37,IF(Sprints!$I37<>"",Sprints!$I37,"Comprometida y no completada al cierre del Sprint "&$N37),"") -> Comprometida y no completada al cierre del Sprint 1 | AI37: =IF($AF37,$N37*100000+ROW(),"") -> 100037 | AJ37: =IF($C37,$AA37*1000000-MEDIAN(-9999,$K37,9999)*100+(300-ROW()),"") -> 88000963 | AK37: =IF($C37,IF($J37="Completado",0,IF($K37<0,1,IF($K37<=3,0.9,IF($K37<=7,0.7,IF($K37<=14,0.45,0.2))))),"") -> 1 | AL37: =IF($C37,IF($J37="Completado",0,MEDIAN(0,MAX(-$V37,$W37/30),1)),"") -> 0.8 | AM37: =IF($C37,IF($J37="Completado",0,IF($Z37,1,IF(AND($I37<0.5,$K37<=7),0.7,0.3))),"") -> 0.7 | AN37: =IF($C37,IF(OR($V37<-0.2,$W37>0),"ATRASO ","")&IF($Z37,"BLOQUEO ","")&IF($Y37>8,"SOBRECARGA ","")&IF($X37>0,"DESVÍO-PLAN ",""),"") -> ATRASO SOBRECARGA | AO37: =IF($C37,IFERROR(INDEX(Sprints!$M$6:$M$13,MATCH($N37,Sprints!$K$6:$K$13,0)),""),"") -> 46186 | AP37: =IF($C37,IF(AND($N37<>9999,$AD37<>$N37,ISNUMBER($AO37)),TODAY()-$AO37,0),"") -> 6
A38: =ROW() -> 38 | B38: =ISTEXT('Proyecto Datos (OKR´s)'!$K38) -> FALSE | C38: =AND(LEN('Proyecto Datos (OKR´s)'!$G38)>0,NOT($B38),OR(ISNUMBER('Proyecto Datos (OKR´s)'!$F38),ISNUMBER('Proyecto Datos (OKR´s)'!$L38))) -> TRUE | D38: =IF($C38,IFERROR(LOOKUP(2,1/((ISTEXT('Proyecto Datos (OKR´s)'!$K$7:$K38))*(LEN('Proyecto Datos (OKR´s)'!$G$7:$G38)>0)),'Proyecto Datos (OKR´s)'!$G$7:$G38),""),"") -> 5- Tablero Control General - Op. Complejas | E38: =IF($C38,'Proyecto Datos (OKR´s)'!$E38,"") -> 1 | F38: =IF($C38,'Proyecto Datos (OKR´s)'!$G38,"") -> Planilla DTM Estandarizada+ Procedimiento | G38: =IF($C38,IF('Proyecto Datos (OKR´s)'!$I38="","(Sin asignar)",'Proyecto Datos (OKR´s)'!$I38),"") -> Santiago Alonso | H38: =IF($C38,IF(ISNUMBER('Proyecto Datos (OKR´s)'!$F38),'Proyecto Datos (OKR´s)'!$F38,'Proyecto Datos (OKR´s)'!$L38),"") -> 46185 | I38: =IF($C38,'Proyecto Datos (OKR´s)'!$J38,"") -> 0.9 | J38: =IF($C38,IF($I38>=1,"Completado",IF($H38<TODAY(),"Vencido",IF(($H38-TODAY())<='Entregas Próximas'!$M$3,"Próximo a vencer","En curso"))),"") -> Vencido | K38: =IF($C38,$H38-TODAY(),"") -> -7 | L38: =IF($C38,$AD38*1000000+$H38+ROW()/100000,"") -> 2046185 | M38: =IF($C38,IF($AD38=9999,"(Sin sprint)",$AD38),"") -> 2 | N38: =IF($C38,IF('Proyecto Datos (OKR´s)'!$E38="",9999,'Proyecto Datos (OKR´s)'!$E38),"") -> 1 | O38: =IF($C38,"T"&TEXT(ROW(),"000"),"") -> T038 | R38: =IF($C38,IF(ISNUMBER('Proyecto Datos (OKR´s)'!$L38),'Proyecto Datos (OKR´s)'!$L38,$H38),"") -> 46185 | S38: =IF($C38,$R38-'Proyecto Datos (OKR´s)'!$K38+1,"") -> 163 | T38: =IF($C38,MAX(0,TODAY()-'Proyecto Datos (OKR´s)'!$K38),"") -> 169 | U38: =IF($C38,MEDIAN(0,(TODAY()-'Proyecto Datos (OKR´s)'!$K38)/MAX(1,$R38-'Proyecto Datos (OKR´s)'!$K38),1),"") -> 1 | V38: =IF($C38,$I38-$U38,"") -> -0.1 | W38: =IF($C38,IF($J38="Completado",0,MAX(0,TODAY()-$H38)),"") -> 7 | X38: =IF($C38,IF(ISNUMBER($H38),$R38-$H38,0),"") -> 0 | Y38: =IF($C38,COUNTIFS($G$7:$G$200,$G38,$J$7:$J$200,"<>Completado",$J$7:$J$200,"<>"),"") -> 35 | Z38: =IF($C38,AND($I38=0,'Proyecto Datos (OKR´s)'!$K38<=TODAY(),$J38<>"Completado"),"") -> FALSE | AA38: =IF($C38,ROUND(100*(0.35*$AK38+0.3*$AL38+0.2*$AM38+0.15*MEDIAN(0,($Y38-4)/8,1)),0),"") -> 63 | AB38: =IF($C38,IF($J38="Completado","—",IF($AA38>=70,"Crítica",IF($AA38>=45,"Alta",IF($AA38>=25,"Media","Baja")))),"") -> Alta | AC38: =IF($C38,IF(LEN(TRIM($AN38))=0,"—",TRIM($AN38)),"") -> ATRASO SOBRECARGA | AD38: =IF($C38,IF($N38=9999,9999,IF($J38="Completado",$N38,MAX($N38,Sprints!$M$15))),"") -> 2 | AE38: =IF($C38,IF($AD38=9999,"(Sin sprint)",$AD38),"") -> 2 | AF38: =IF($C38,AND($N38<>9999,$AD38<>$N38),FALSE) -> TRUE | AG38: =IF($AF38,$AO38,"") -> 46186 | AH38: =IF($AF38,IF(Sprints!$I38<>"",Sprints!$I38,"Comprometida y no completada al cierre del Sprint "&$N38),"") -> Comprometida y no completada al cierre del Sprint 1 | AI38: =IF($AF38,$N38*100000+ROW(),"") -> 100038 | AJ38: =IF($C38,$AA38*1000000-MEDIAN(-9999,$K38,9999)*100+(300-ROW()),"") -> 63000962 | AK38: =IF($C38,IF($J38="Completado",0,IF($K38<0,1,IF($K38<=3,0.9,IF($K38<=7,0.7,IF($K38<=14,0.45,0.2))))),"") -> 1 | AL38: =IF($C38,IF($J38="Completado",0,MEDIAN(0,MAX(-$V38,$W38/30),1)),"") -> 0.23333333 | AM38: =IF($C38,IF($J38="Completado",0,IF($Z38,1,IF(AND($I38<0.5,$K38<=7),0.7,0.3))),"") -> 0.3 | AN38: =IF($C38,IF(OR($V38<-0.2,$W38>0),"ATRASO ","")&IF($Z38,"BLOQUEO ","")&IF($Y38>8,"SOBRECARGA ","")&IF($X38>0,"DESVÍO-PLAN ",""),"") -> ATRASO SOBRECARGA | AO38: =IF($C38,IFERROR(INDEX(Sprints!$M$6:$M$13,MATCH($N38,Sprints!$K$6:$K$13,0)),""),"") -> 46186 | AP38: =IF($C38,IF(AND($N38<>9999,$AD38<>$N38,ISNUMBER($AO38)),TODAY()-$AO38,0),"") -> 6
A39: =ROW() -> 39 | B39: =ISTEXT('Proyecto Datos (OKR´s)'!$K39) -> FALSE | C39: =AND(LEN('Proyecto Datos (OKR´s)'!$G39)>0,NOT($B39),OR(ISNUMBER('Proyecto Datos (OKR´s)'!$F39),ISNUMBER('Proyecto Datos (OKR´s)'!$L39))) -> TRUE | D39: =IF($C39,IFERROR(LOOKUP(2,1/((ISTEXT('Proyecto Datos (OKR´s)'!$K$7:$K39))*(LEN('Proyecto Datos (OKR´s)'!$G$7:$G39)>0)),'Proyecto Datos (OKR´s)'!$G$7:$G39),""),"") -> 5- Tablero Control General - Op. Complejas | E39: =IF($C39,'Proyecto Datos (OKR´s)'!$E39,"") -> 1 | F39: =IF($C39,'Proyecto Datos (OKR´s)'!$G39,"") -> Planilla Aeroevaciaciones + Procedimiento | G39: =IF($C39,IF('Proyecto Datos (OKR´s)'!$I39="","(Sin asignar)",'Proyecto Datos (OKR´s)'!$I39),"") -> Santiago Alonso | H39: =IF($C39,IF(ISNUMBER('Proyecto Datos (OKR´s)'!$F39),'Proyecto Datos (OKR´s)'!$F39,'Proyecto Datos (OKR´s)'!$L39),"") -> 46185 | I39: =IF($C39,'Proyecto Datos (OKR´s)'!$J39,"") -> 0.95 | J39: =IF($C39,IF($I39>=1,"Completado",IF($H39<TODAY(),"Vencido",IF(($H39-TODAY())<='Entregas Próximas'!$M$3,"Próximo a vencer","En curso"))),"") -> Vencido | K39: =IF($C39,$H39-TODAY(),"") -> -7 | L39: =IF($C39,$AD39*1000000+$H39+ROW()/100000,"") -> 2046185 | M39: =IF($C39,IF($AD39=9999,"(Sin sprint)",$AD39),"") -> 2 | N39: =IF($C39,IF('Proyecto Datos (OKR´s)'!$E39="",9999,'Proyecto Datos (OKR´s)'!$E39),"") -> 1 | O39: =IF($C39,"T"&TEXT(ROW(),"000"),"") -> T039 | R39: =IF($C39,IF(ISNUMBER('Proyecto Datos (OKR´s)'!$L39),'Proyecto Datos (OKR´s)'!$L39,$H39),"") -> 46185 | S39: =IF($C39,$R39-'Proyecto Datos (OKR´s)'!$K39+1,"") -> 194 | T39: =IF($C39,MAX(0,TODAY()-'Proyecto Datos (OKR´s)'!$K39),"") -> 200 | U39: =IF($C39,MEDIAN(0,(TODAY()-'Proyecto Datos (OKR´s)'!$K39)/MAX(1,$R39-'Proyecto Datos (OKR´s)'!$K39),1),"") -> 1 | V39: =IF($C39,$I39-$U39,"") -> -0.05 | W39: =IF($C39,IF($J39="Completado",0,MAX(0,TODAY()-$H39)),"") -> 7 | X39: =IF($C39,IF(ISNUMBER($H39),$R39-$H39,0),"") -> 0 | Y39: =IF($C39,COUNTIFS($G$7:$G$200,$G39,$J$7:$J$200,"<>Completado",$J$7:$J$200,"<>"),"") -> 35 | Z39: =IF($C39,AND($I39=0,'Proyecto Datos (OKR´s)'!$K39<=TODAY(),$J39<>"Completado"),"") -> FALSE | AA39: =IF($C39,ROUND(100*(0.35*$AK39+0.3*$AL39+0.2*$AM39+0.15*MEDIAN(0,($Y39-4)/8,1)),0),"") -> 63 | AB39: =IF($C39,IF($J39="Completado","—",IF($AA39>=70,"Crítica",IF($AA39>=45,"Alta",IF($AA39>=25,"Media","Baja")))),"") -> Alta | AC39: =IF($C39,IF(LEN(TRIM($AN39))=0,"—",TRIM($AN39)),"") -> ATRASO SOBRECARGA | AD39: =IF($C39,IF($N39=9999,9999,IF($J39="Completado",$N39,MAX($N39,Sprints!$M$15))),"") -> 2 | AE39: =IF($C39,IF($AD39=9999,"(Sin sprint)",$AD39),"") -> 2 | AF39: =IF($C39,AND($N39<>9999,$AD39<>$N39),FALSE) -> TRUE | AG39: =IF($AF39,$AO39,"") -> 46186 | AH39: =IF($AF39,IF(Sprints!$I39<>"",Sprints!$I39,"Comprometida y no completada al cierre del Sprint "&$N39),"") -> Comprometida y no completada al cierre del Sprint 1 | AI39: =IF($AF39,$N39*100000+ROW(),"") -> 100039 | AJ39: =IF($C39,$AA39*1000000-MEDIAN(-9999,$K39,9999)*100+(300-ROW()),"") -> 63000961 | AK39: =IF($C39,IF($J39="Completado",0,IF($K39<0,1,IF($K39<=3,0.9,IF($K39<=7,0.7,IF($K39<=14,0.45,0.2))))),"") -> 1 | AL39: =IF($C39,IF($J39="Completado",0,MEDIAN(0,MAX(-$V39,$W39/30),1)),"") -> 0.23333333 | AM39: =IF($C39,IF($J39="Completado",0,IF($Z39,1,IF(AND($I39<0.5,$K39<=7),0.7,0.3))),"") -> 0.3 | AN39: =IF($C39,IF(OR($V39<-0.2,$W39>0),"ATRASO ","")&IF($Z39,"BLOQUEO ","")&IF($Y39>8,"SOBRECARGA ","")&IF($X39>0,"DESVÍO-PLAN ",""),"") -> ATRASO SOBRECARGA | AO39: =IF($C39,IFERROR(INDEX(Sprints!$M$6:$M$13,MATCH($N39,Sprints!$K$6:$K$13,0)),""),"") -> 46186 | AP39: =IF($C39,IF(AND($N39<>9999,$AD39<>$N39,ISNUMBER($AO39)),TODAY()-$AO39,0),"") -> 6
A40: =ROW() -> 40 | B40: =ISTEXT('Proyecto Datos (OKR´s)'!$K40) -> FALSE | C40: =AND(LEN('Proyecto Datos (OKR´s)'!$G40)>0,NOT($B40),OR(ISNUMBER('Proyecto Datos (OKR´s)'!$F40),ISNUMBER('Proyecto Datos (OKR´s)'!$L40))) -> TRUE | D40: =IF($C40,IFERROR(LOOKUP(2,1/((ISTEXT('Proyecto Datos (OKR´s)'!$K$7:$K40))*(LEN('Proyecto Datos (OKR´s)'!$G$7:$G40)>0)),'Proyecto Datos (OKR´s)'!$G$7:$G40),""),"") -> 5- Tablero Control General - Op. Complejas | E40: =IF($C40,'Proyecto Datos (OKR´s)'!$E40,"") -> 1 | F40: =IF($C40,'Proyecto Datos (OKR´s)'!$G40,"") -> Resumen Clientes Petróleo | G40: =IF($C40,IF('Proyecto Datos (OKR´s)'!$I40="","(Sin asignar)",'Proyecto Datos (OKR´s)'!$I40),"") -> Santiago Alonso | H40: =IF($C40,IF(ISNUMBER('Proyecto Datos (OKR´s)'!$F40),'Proyecto Datos (OKR´s)'!$F40,'Proyecto Datos (OKR´s)'!$L40),"") -> 46185 | I40: =IF($C40,'Proyecto Datos (OKR´s)'!$J40,"") -> 0.7 | J40: =IF($C40,IF($I40>=1,"Completado",IF($H40<TODAY(),"Vencido",IF(($H40-TODAY())<='Entregas Próximas'!$M$3,"Próximo a vencer","En curso"))),"") -> Vencido | K40: =IF($C40,$H40-TODAY(),"") -> -7 | L40: =IF($C40,$AD40*1000000+$H40+ROW()/100000,"") -> 2046185 | M40: =IF($C40,IF($AD40=9999,"(Sin sprint)",$AD40),"") -> 2 | N40: =IF($C40,IF('Proyecto Datos (OKR´s)'!$E40="",9999,'Proyecto Datos (OKR´s)'!$E40),"") -> 1 | O40: =IF($C40,"T"&TEXT(ROW(),"000"),"") -> T040 | R40: =IF($C40,IF(ISNUMBER('Proyecto Datos (OKR´s)'!$L40),'Proyecto Datos (OKR´s)'!$L40,$H40),"") -> 46185 | S40: =IF($C40,$R40-'Proyecto Datos (OKR´s)'!$K40+1,"") -> -171 | T40: =IF($C40,MAX(0,TODAY()-'Proyecto Datos (OKR´s)'!$K40),"") -> 0 | U40: =IF($C40,MEDIAN(0,(TODAY()-'Proyecto Datos (OKR´s)'!$K40)/MAX(1,$R40-'Proyecto Datos (OKR´s)'!$K40),1),"") -> 0 | V40: =IF($C40,$I40-$U40,"") -> 0.7 | W40: =IF($C40,IF($J40="Completado",0,MAX(0,TODAY()-$H40)),"") -> 7 | X40: =IF($C40,IF(ISNUMBER($H40),$R40-$H40,0),"") -> 0 | Y40: =IF($C40,COUNTIFS($G$7:$G$200,$G40,$J$7:$J$200,"<>Completado",$J$7:$J$200,"<>"),"") -> 35 | Z40: =IF($C40,AND($I40=0,'Proyecto Datos (OKR´s)'!$K40<=TODAY(),$J40<>"Completado"),"") -> FALSE | AA40: =IF($C40,ROUND(100*(0.35*$AK40+0.3*$AL40+0.2*$AM40+0.15*MEDIAN(0,($Y40-4)/8,1)),0),"") -> 63 | AB40: =IF($C40,IF($J40="Completado","—",IF($AA40>=70,"Crítica",IF($AA40>=45,"Alta",IF($AA40>=25,"Media","Baja")))),"") -> Alta | AC40: =IF($C40,IF(LEN(TRIM($AN40))=0,"—",TRIM($AN40)),"") -> ATRASO SOBRECARGA | AD40: =IF($C40,IF($N40=9999,9999,IF($J40="Completado",$N40,MAX($N40,Sprints!$M$15))),"") -> 2 | AE40: =IF($C40,IF($AD40=9999,"(Sin sprint)",$AD40),"") -> 2 | AF40: =IF($C40,AND($N40<>9999,$AD40<>$N40),FALSE) -> TRUE | AG40: =IF($AF40,$AO40,"") -> 46186 | AH40: =IF($AF40,IF(Sprints!$I40<>"",Sprints!$I40,"Comprometida y no completada al cierre del Sprint "&$N40),"") -> Comprometida y no completada al cierre del Sprint 1 | AI40: =IF($AF40,$N40*100000+ROW(),"") -> 100040 | AJ40: =IF($C40,$AA40*1000000-MEDIAN(-9999,$K40,9999)*100+(300-ROW()),"") -> 63000960 | AK40: =IF($C40,IF($J40="Completado",0,IF($K40<0,1,IF($K40<=3,0.9,IF($K40<=7,0.7,IF($K40<=14,0.45,0.2))))),"") -> 1 | AL40: =IF($C40,IF($J40="Completado",0,MEDIAN(0,MAX(-$V40,$W40/30),1)),"") -> 0.23333333 | AM40: =IF($C40,IF($J40="Completado",0,IF($Z40,1,IF(AND($I40<0.5,$K40<=7),0.7,0.3))),"") -> 0.3 | AN40: =IF($C40,IF(OR($V40<-0.2,$W40>0),"ATRASO ","")&IF($Z40,"BLOQUEO ","")&IF($Y40>8,"SOBRECARGA ","")&IF($X40>0,"DESVÍO-PLAN ",""),"") -> ATRASO SOBRECARGA | AO40: =IF($C40,IFERROR(INDEX(Sprints!$M$6:$M$13,MATCH($N40,Sprints!$K$6:$K$13,0)),""),"") -> 46186 | AP40: =IF($C40,IF(AND($N40<>9999,$AD40<>$N40,ISNUMBER($AO40)),TODAY()-$AO40,0),"") -> 6
A41: =ROW() -> 41 | B41: =ISTEXT('Proyecto Datos (OKR´s)'!$K41) -> FALSE | C41: =AND(LEN('Proyecto Datos (OKR´s)'!$G41)>0,NOT($B41),OR(ISNUMBER('Proyecto Datos (OKR´s)'!$F41),ISNUMBER('Proyecto Datos (OKR´s)'!$L41))) -> TRUE | D41: =IF($C41,IFERROR(LOOKUP(2,1/((ISTEXT('Proyecto Datos (OKR´s)'!$K$7:$K41))*(LEN('Proyecto Datos (OKR´s)'!$G$7:$G41)>0)),'Proyecto Datos (OKR´s)'!$G$7:$G41),""),"") -> 5- Tablero Control General - Op. Complejas | E41: =IF($C41,'Proyecto Datos (OKR´s)'!$E41,"") -> 1 | F41: =IF($C41,'Proyecto Datos (OKR´s)'!$G41,"") -> Resumen Clientes Minería | G41: =IF($C41,IF('Proyecto Datos (OKR´s)'!$I41="","(Sin asignar)",'Proyecto Datos (OKR´s)'!$I41),"") -> Santiago Alonso | H41: =IF($C41,IF(ISNUMBER('Proyecto Datos (OKR´s)'!$F41),'Proyecto Datos (OKR´s)'!$F41,'Proyecto Datos (OKR´s)'!$L41),"") -> 46185 | I41: =IF($C41,'Proyecto Datos (OKR´s)'!$J41,"") -> 0.5 | J41: =IF($C41,IF($I41>=1,"Completado",IF($H41<TODAY(),"Vencido",IF(($H41-TODAY())<='Entregas Próximas'!$M$3,"Próximo a vencer","En curso"))),"") -> Vencido | K41: =IF($C41,$H41-TODAY(),"") -> -7 | L41: =IF($C41,$AD41*1000000+$H41+ROW()/100000,"") -> 2046185 | M41: =IF($C41,IF($AD41=9999,"(Sin sprint)",$AD41),"") -> 2 | N41: =IF($C41,IF('Proyecto Datos (OKR´s)'!$E41="",9999,'Proyecto Datos (OKR´s)'!$E41),"") -> 1 | O41: =IF($C41,"T"&TEXT(ROW(),"000"),"") -> T041 | R41: =IF($C41,IF(ISNUMBER('Proyecto Datos (OKR´s)'!$L41),'Proyecto Datos (OKR´s)'!$L41,$H41),"") -> 46185 | S41: =IF($C41,$R41-'Proyecto Datos (OKR´s)'!$K41+1,"") -> -2 | T41: =IF($C41,MAX(0,TODAY()-'Proyecto Datos (OKR´s)'!$K41),"") -> 4 | U41: =IF($C41,MEDIAN(0,(TODAY()-'Proyecto Datos (OKR´s)'!$K41)/MAX(1,$R41-'Proyecto Datos (OKR´s)'!$K41),1),"") -> 1 | V41: =IF($C41,$I41-$U41,"") -> -0.5 | W41: =IF($C41,IF($J41="Completado",0,MAX(0,TODAY()-$H41)),"") -> 7 | X41: =IF($C41,IF(ISNUMBER($H41),$R41-$H41,0),"") -> 0 | Y41: =IF($C41,COUNTIFS($G$7:$G$200,$G41,$J$7:$J$200,"<>Completado",$J$7:$J$200,"<>"),"") -> 35 | Z41: =IF($C41,AND($I41=0,'Proyecto Datos (OKR´s)'!$K41<=TODAY(),$J41<>"Completado"),"") -> FALSE | AA41: =IF($C41,ROUND(100*(0.35*$AK41+0.3*$AL41+0.2*$AM41+0.15*MEDIAN(0,($Y41-4)/8,1)),0),"") -> 71 | AB41: =IF($C41,IF($J41="Completado","—",IF($AA41>=70,"Crítica",IF($AA41>=45,"Alta",IF($AA41>=25,"Media","Baja")))),"") -> Crítica | AC41: =IF($C41,IF(LEN(TRIM($AN41))=0,"—",TRIM($AN41)),"") -> ATRASO SOBRECARGA | AD41: =IF($C41,IF($N41=9999,9999,IF($J41="Completado",$N41,MAX($N41,Sprints!$M$15))),"") -> 2 | AE41: =IF($C41,IF($AD41=9999,"(Sin sprint)",$AD41),"") -> 2 | AF41: =IF($C41,AND($N41<>9999,$AD41<>$N41),FALSE) -> TRUE | AG41: =IF($AF41,$AO41,"") -> 46186 | AH41: =IF($AF41,IF(Sprints!$I41<>"",Sprints!$I41,"Comprometida y no completada al cierre del Sprint "&$N41),"") -> Comprometida y no completada al cierre del Sprint 1 | AI41: =IF($AF41,$N41*100000+ROW(),"") -> 100041 | AJ41: =IF($C41,$AA41*1000000-MEDIAN(-9999,$K41,9999)*100+(300-ROW()),"") -> 71000959 | AK41: =IF($C41,IF($J41="Completado",0,IF($K41<0,1,IF($K41<=3,0.9,IF($K41<=7,0.7,IF($K41<=14,0.45,0.2))))),"") -> 1 | AL41: =IF($C41,IF($J41="Completado",0,MEDIAN(0,MAX(-$V41,$W41/30),1)),"") -> 0.5 | AM41: =IF($C41,IF($J41="Completado",0,IF($Z41,1,IF(AND($I41<0.5,$K41<=7),0.7,0.3))),"") -> 0.3 | AN41: =IF($C41,IF(OR($V41<-0.2,$W41>0),"ATRASO ","")&IF($Z41,"BLOQUEO ","")&IF($Y41>8,"SOBRECARGA ","")&IF($X41>0,"DESVÍO-PLAN ",""),"") -> ATRASO SOBRECARGA | AO41: =IF($C41,IFERROR(INDEX(Sprints!$M$6:$M$13,MATCH($N41,Sprints!$K$6:$K$13,0)),""),"") -> 46186 | AP41: =IF($C41,IF(AND($N41<>9999,$AD41<>$N41,ISNUMBER($AO41)),TODAY()-$AO41,0),"") -> 6
A42: =ROW() -> 42 | B42: =ISTEXT('Proyecto Datos (OKR´s)'!$K42) -> FALSE | C42: =AND(LEN('Proyecto Datos (OKR´s)'!$G42)>0,NOT($B42),OR(ISNUMBER('Proyecto Datos (OKR´s)'!$F42),ISNUMBER('Proyecto Datos (OKR´s)'!$L42))) -> TRUE | D42: =IF($C42,IFERROR(LOOKUP(2,1/((ISTEXT('Proyecto Datos (OKR´s)'!$K$7:$K42))*(LEN('Proyecto Datos (OKR´s)'!$G$7:$G42)>0)),'Proyecto Datos (OKR´s)'!$G$7:$G42),""),"") -> 5- Tablero Control General - Op. Complejas | E42: =IF($C42,'Proyecto Datos (OKR´s)'!$E42,"") -> 1 | F42: =IF($C42,'Proyecto Datos (OKR´s)'!$G42,"") -> Resumen Clientes Op. Dedicadas | G42: =IF($C42,IF('Proyecto Datos (OKR´s)'!$I42="","(Sin asignar)",'Proyecto Datos (OKR´s)'!$I42),"") -> Santiago Alonso | H42: =IF($C42,IF(ISNUMBER('Proyecto Datos (OKR´s)'!$F42),'Proyecto Datos (OKR´s)'!$F42,'Proyecto Datos (OKR´s)'!$L42),"") -> 46185 | I42: =IF($C42,'Proyecto Datos (OKR´s)'!$J42,"") -> 0.4 | J42: =IF($C42,IF($I42>=1,"Completado",IF($H42<TODAY(),"Vencido",IF(($H42-TODAY())<='Entregas Próximas'!$M$3,"Próximo a vencer","En curso"))),"") -> Vencido | K42: =IF($C42,$H42-TODAY(),"") -> -7 | L42: =IF($C42,$AD42*1000000+$H42+ROW()/100000,"") -> 2046185 | M42: =IF($C42,IF($AD42=9999,"(Sin sprint)",$AD42),"") -> 2 | N42: =IF($C42,IF('Proyecto Datos (OKR´s)'!$E42="",9999,'Proyecto Datos (OKR´s)'!$E42),"") -> 1 | O42: =IF($C42,"T"&TEXT(ROW(),"000"),"") -> T042 | R42: =IF($C42,IF(ISNUMBER('Proyecto Datos (OKR´s)'!$L42),'Proyecto Datos (OKR´s)'!$L42,$H42),"") -> 46185 | S42: =IF($C42,$R42-'Proyecto Datos (OKR´s)'!$K42+1,"") -> -2 | T42: =IF($C42,MAX(0,TODAY()-'Proyecto Datos (OKR´s)'!$K42),"") -> 4 | U42: =IF($C42,MEDIAN(0,(TODAY()-'Proyecto Datos (OKR´s)'!$K42)/MAX(1,$R42-'Proyecto Datos (OKR´s)'!$K42),1),"") -> 1 | V42: =IF($C42,$I42-$U42,"") -> -0.6 | W42: =IF($C42,IF($J42="Completado",0,MAX(0,TODAY()-$H42)),"") -> 7 | X42: =IF($C42,IF(ISNUMBER($H42),$R42-$H42,0),"") -> 0 | Y42: =IF($C42,COUNTIFS($G$7:$G$200,$G42,$J$7:$J$200,"<>Completado",$J$7:$J$200,"<>"),"") -> 35 | Z42: =IF($C42,AND($I42=0,'Proyecto Datos (OKR´s)'!$K42<=TODAY(),$J42<>"Completado"),"") -> FALSE | AA42: =IF($C42,ROUND(100*(0.35*$AK42+0.3*$AL42+0.2*$AM42+0.15*MEDIAN(0,($Y42-4)/8,1)),0),"") -> 82 | AB42: =IF($C42,IF($J42="Completado","—",IF($AA42>=70,"Crítica",IF($AA42>=45,"Alta",IF($AA42>=25,"Media","Baja")))),"") -> Crítica | AC42: =IF($C42,IF(LEN(TRIM($AN42))=0,"—",TRIM($AN42)),"") -> ATRASO SOBRECARGA | AD42: =IF($C42,IF($N42=9999,9999,IF($J42="Completado",$N42,MAX($N42,Sprints!$M$15))),"") -> 2 | AE42: =IF($C42,IF($AD42=9999,"(Sin sprint)",$AD42),"") -> 2 | AF42: =IF($C42,AND($N42<>9999,$AD42<>$N42),FALSE) -> TRUE | AG42: =IF($AF42,$AO42,"") -> 46186 | AH42: =IF($AF42,IF(Sprints!$I42<>"",Sprints!$I42,"Comprometida y no completada al cierre del Sprint "&$N42),"") -> Comprometida y no completada al cierre del Sprint 1 | AI42: =IF($AF42,$N42*100000+ROW(),"") -> 100042 | AJ42: =IF($C42,$AA42*1000000-MEDIAN(-9999,$K42,9999)*100+(300-ROW()),"") -> 82000958 | AK42: =IF($C42,IF($J42="Completado",0,IF($K42<0,1,IF($K42<=3,0.9,IF($K42<=7,0.7,IF($K42<=14,0.45,0.2))))),"") -> 1 | AL42: =IF($C42,IF($J42="Completado",0,MEDIAN(0,MAX(-$V42,$W42/30),1)),"") -> 0.6 | AM42: =IF($C42,IF($J42="Completado",0,IF($Z42,1,IF(AND($I42<0.5,$K42<=7),0.7,0.3))),"") -> 0.7 | AN42: =IF($C42,IF(OR($V42<-0.2,$W42>0),"ATRASO ","")&IF($Z42,"BLOQUEO ","")&IF($Y42>8,"SOBRECARGA ","")&IF($X42>0,"DESVÍO-PLAN ",""),"") -> ATRASO SOBRECARGA | AO42: =IF($C42,IFERROR(INDEX(Sprints!$M$6:$M$13,MATCH($N42,Sprints!$K$6:$K$13,0)),""),"") -> 46186 | AP42: =IF($C42,IF(AND($N42<>9999,$AD42<>$N42,ISNUMBER($AO42)),TODAY()-$AO42,0),"") -> 6
A43: =ROW() -> 43 | B43: =ISTEXT('Proyecto Datos (OKR´s)'!$K43) -> FALSE | C43: =AND(LEN('Proyecto Datos (OKR´s)'!$G43)>0,NOT($B43),OR(ISNUMBER('Proyecto Datos (OKR´s)'!$F43),ISNUMBER('Proyecto Datos (OKR´s)'!$L43))) -> TRUE | D43: =IF($C43,IFERROR(LOOKUP(2,1/((ISTEXT('Proyecto Datos (OKR´s)'!$K$7:$K43))*(LEN('Proyecto Datos (OKR´s)'!$G$7:$G43)>0)),'Proyecto Datos (OKR´s)'!$G$7:$G43),""),"") -> 5- Tablero Control General - Op. Complejas | E43: =IF($C43,'Proyecto Datos (OKR´s)'!$E43,"") -> 0 | F43: =IF($C43,'Proyecto Datos (OKR´s)'!$G43,"") -> Locaciones Geográficas Pozos Petro (ver datos Secretaria de Energía) | G43: =IF($C43,IF('Proyecto Datos (OKR´s)'!$I43="","(Sin asignar)",'Proyecto Datos (OKR´s)'!$I43),"") -> Santiago Alonso | H43: =IF($C43,IF(ISNUMBER('Proyecto Datos (OKR´s)'!$F43),'Proyecto Datos (OKR´s)'!$F43,'Proyecto Datos (OKR´s)'!$L43),"") -> 46192 | I43: =IF($C43,'Proyecto Datos (OKR´s)'!$J43,"") -> 0.1 | J43: =IF($C43,IF($I43>=1,"Completado",IF($H43<TODAY(),"Vencido",IF(($H43-TODAY())<='Entregas Próximas'!$M$3,"Próximo a vencer","En curso"))),"") -> Próximo a vencer | K43: =IF($C43,$H43-TODAY(),"") -> 0 | L43: =IF($C43,$AD43*1000000+$H43+ROW()/100000,"") -> 9.9990462e+09 | M43: =IF($C43,IF($AD43=9999,"(Sin sprint)",$AD43),"") -> (Sin sprint) | N43: =IF($C43,IF('Proyecto Datos (OKR´s)'!$E43="",9999,'Proyecto Datos (OKR´s)'!$E43),"") -> 9999 | O43: =IF($C43,"T"&TEXT(ROW(),"000"),"") -> T043 | R43: =IF($C43,IF(ISNUMBER('Proyecto Datos (OKR´s)'!$L43),'Proyecto Datos (OKR´s)'!$L43,$H43),"") -> 46192 | S43: =IF($C43,$R43-'Proyecto Datos (OKR´s)'!$K43+1,"") -> 5 | T43: =IF($C43,MAX(0,TODAY()-'Proyecto Datos (OKR´s)'!$K43),"") -> 4 | U43: =IF($C43,MEDIAN(0,(TODAY()-'Proyecto Datos (OKR´s)'!$K43)/MAX(1,$R43-'Proyecto Datos (OKR´s)'!$K43),1),"") -> 1 | V43: =IF($C43,$I43-$U43,"") -> -0.9 | W43: =IF($C43,IF($J43="Completado",0,MAX(0,TODAY()-$H43)),"") -> 0 | X43: =IF($C43,IF(ISNUMBER($H43),$R43-$H43,0),"") -> 0 | Y43: =IF($C43,COUNTIFS($G$7:$G$200,$G43,$J$7:$J$200,"<>Completado",$J$7:$J$200,"<>"),"") -> 35 | Z43: =IF($C43,AND($I43=0,'Proyecto Datos (OKR´s)'!$K43<=TODAY(),$J43<>"Completado"),"") -> FALSE | AA43: =IF($C43,ROUND(100*(0.35*$AK43+0.3*$AL43+0.2*$AM43+0.15*MEDIAN(0,($Y43-4)/8,1)),0),"") -> 88 | AB43: =IF($C43,IF($J43="Completado","—",IF($AA43>=70,"Crítica",IF($AA43>=45,"Alta",IF($AA43>=25,"Media","Baja")))),"") -> Crítica | AC43: =IF($C43,IF(LEN(TRIM($AN43))=0,"—",TRIM($AN43)),"") -> ATRASO SOBRECARGA | AD43: =IF($C43,IF($N43=9999,9999,IF($J43="Completado",$N43,MAX($N43,Sprints!$M$15))),"") -> 9999 | AE43: =IF($C43,IF($AD43=9999,"(Sin sprint)",$AD43),"") -> (Sin sprint) | AF43: =IF($C43,AND($N43<>9999,$AD43<>$N43),FALSE) -> FALSE | AG43: =IF($AF43,$AO43,"") | AH43: =IF($AF43,IF(Sprints!$I43<>"",Sprints!$I43,"Comprometida y no completada al cierre del Sprint "&$N43),"") | AI43: =IF($AF43,$N43*100000+ROW(),"") | AJ43: =IF($C43,$AA43*1000000-MEDIAN(-9999,$K43,9999)*100+(300-ROW()),"") -> 88000257 | AK43: =IF($C43,IF($J43="Completado",0,IF($K43<0,1,IF($K43<=3,0.9,IF($K43<=7,0.7,IF($K43<=14,0.45,0.2))))),"") -> 0.9 | AL43: =IF($C43,IF($J43="Completado",0,MEDIAN(0,MAX(-$V43,$W43/30),1)),"") -> 0.9 | AM43: =IF($C43,IF($J43="Completado",0,IF($Z43,1,IF(AND($I43<0.5,$K43<=7),0.7,0.3))),"") -> 0.7 | AN43: =IF($C43,IF(OR($V43<-0.2,$W43>0),"ATRASO ","")&IF($Z43,"BLOQUEO ","")&IF($Y43>8,"SOBRECARGA ","")&IF($X43>0,"DESVÍO-PLAN ",""),"") -> ATRASO SOBRECARGA | AO43: =IF($C43,IFERROR(INDEX(Sprints!$M$6:$M$13,MATCH($N43,Sprints!$K$6:$K$13,0)),""),"") | AP43: =IF($C43,IF(AND($N43<>9999,$AD43<>$N43,ISNUMBER($AO43)),TODAY()-$AO43,0),"") -> 0
A44: =ROW() -> 44 | B44: =ISTEXT('Proyecto Datos (OKR´s)'!$K44) -> FALSE | C44: =AND(LEN('Proyecto Datos (OKR´s)'!$G44)>0,NOT($B44),OR(ISNUMBER('Proyecto Datos (OKR´s)'!$F44),ISNUMBER('Proyecto Datos (OKR´s)'!$L44))) -> TRUE | D44: =IF($C44,IFERROR(LOOKUP(2,1/((ISTEXT('Proyecto Datos (OKR´s)'!$K$7:$K44))*(LEN('Proyecto Datos (OKR´s)'!$G$7:$G44)>0)),'Proyecto Datos (OKR´s)'!$G$7:$G44),""),"") -> 5- Tablero Control General - Op. Complejas | E44: =IF($C44,'Proyecto Datos (OKR´s)'!$E44,"") -> 0 | F44: =IF($C44,'Proyecto Datos (OKR´s)'!$G44,"") -> Locaciones Geográficas Minería | G44: =IF($C44,IF('Proyecto Datos (OKR´s)'!$I44="","(Sin asignar)",'Proyecto Datos (OKR´s)'!$I44),"") -> Santiago Alonso | H44: =IF($C44,IF(ISNUMBER('Proyecto Datos (OKR´s)'!$F44),'Proyecto Datos (OKR´s)'!$F44,'Proyecto Datos (OKR´s)'!$L44),"") -> 46199 | I44: =IF($C44,'Proyecto Datos (OKR´s)'!$J44,"") -> 0 | J44: =IF($C44,IF($I44>=1,"Completado",IF($H44<TODAY(),"Vencido",IF(($H44-TODAY())<='Entregas Próximas'!$M$3,"Próximo a vencer","En curso"))),"") -> Próximo a vencer | K44: =IF($C44,$H44-TODAY(),"") -> 7 | L44: =IF($C44,$AD44*1000000+$H44+ROW()/100000,"") -> 9.9990462e+09 | M44: =IF($C44,IF($AD44=9999,"(Sin sprint)",$AD44),"") -> (Sin sprint) | N44: =IF($C44,IF('Proyecto Datos (OKR´s)'!$E44="",9999,'Proyecto Datos (OKR´s)'!$E44),"") -> 9999 | O44: =IF($C44,"T"&TEXT(ROW(),"000"),"") -> T044 | R44: =IF($C44,IF(ISNUMBER('Proyecto Datos (OKR´s)'!$L44),'Proyecto Datos (OKR´s)'!$L44,$H44),"") -> 46199 | S44: =IF($C44,$R44-'Proyecto Datos (OKR´s)'!$K44+1,"") -> 5 | T44: =IF($C44,MAX(0,TODAY()-'Proyecto Datos (OKR´s)'!$K44),"") -> 0 | U44: =IF($C44,MEDIAN(0,(TODAY()-'Proyecto Datos (OKR´s)'!$K44)/MAX(1,$R44-'Proyecto Datos (OKR´s)'!$K44),1),"") -> 0 | V44: =IF($C44,$I44-$U44,"") -> 0 | W44: =IF($C44,IF($J44="Completado",0,MAX(0,TODAY()-$H44)),"") -> 0 | X44: =IF($C44,IF(ISNUMBER($H44),$R44-$H44,0),"") -> 0 | Y44: =IF($C44,COUNTIFS($G$7:$G$200,$G44,$J$7:$J$200,"<>Completado",$J$7:$J$200,"<>"),"") -> 35 | Z44: =IF($C44,AND($I44=0,'Proyecto Datos (OKR´s)'!$K44<=TODAY(),$J44<>"Completado"),"") -> FALSE | AA44: =IF($C44,ROUND(100*(0.35*$AK44+0.3*$AL44+0.2*$AM44+0.15*MEDIAN(0,($Y44-4)/8,1)),0),"") -> 54 | AB44: =IF($C44,IF($J44="Completado","—",IF($AA44>=70,"Crítica",IF($AA44>=45,"Alta",IF($AA44>=25,"Media","Baja")))),"") -> Alta | AC44: =IF($C44,IF(LEN(TRIM($AN44))=0,"—",TRIM($AN44)),"") -> SOBRECARGA | AD44: =IF($C44,IF($N44=9999,9999,IF($J44="Completado",$N44,MAX($N44,Sprints!$M$15))),"") -> 9999 | AE44: =IF($C44,IF($AD44=9999,"(Sin sprint)",$AD44),"") -> (Sin sprint) | AF44: =IF($C44,AND($N44<>9999,$AD44<>$N44),FALSE) -> FALSE | AG44: =IF($AF44,$AO44,"") | AH44: =IF($AF44,IF(Sprints!$I44<>"",Sprints!$I44,"Comprometida y no completada al cierre del Sprint "&$N44),"") | AI44: =IF($AF44,$N44*100000+ROW(),"") | AJ44: =IF($C44,$AA44*1000000-MEDIAN(-9999,$K44,9999)*100+(300-ROW()),"") -> 53999556 | AK44: =IF($C44,IF($J44="Completado",0,IF($K44<0,1,IF($K44<=3,0.9,IF($K44<=7,0.7,IF($K44<=14,0.45,0.2))))),"") -> 0.7 | AL44: =IF($C44,IF($J44="Completado",0,MEDIAN(0,MAX(-$V44,$W44/30),1)),"") -> 0 | AM44: =IF($C44,IF($J44="Completado",0,IF($Z44,1,IF(AND($I44<0.5,$K44<=7),0.7,0.3))),"") -> 0.7 | AN44: =IF($C44,IF(OR($V44<-0.2,$W44>0),"ATRASO ","")&IF($Z44,"BLOQUEO ","")&IF($Y44>8,"SOBRECARGA ","")&IF($X44>0,"DESVÍO-PLAN ",""),"") -> SOBRECARGA | AO44: =IF($C44,IFERROR(INDEX(Sprints!$M$6:$M$13,MATCH($N44,Sprints!$K$6:$K$13,0)),""),"") | AP44: =IF($C44,IF(AND($N44<>9999,$AD44<>$N44,ISNUMBER($AO44)),TODAY()-$AO44,0),"") -> 0
A45: =ROW() -> 45 | B45: =ISTEXT('Proyecto Datos (OKR´s)'!$K45) -> FALSE | C45: =AND(LEN('Proyecto Datos (OKR´s)'!$G45)>0,NOT($B45),OR(ISNUMBER('Proyecto Datos (OKR´s)'!$F45),ISNUMBER('Proyecto Datos (OKR´s)'!$L45))) -> TRUE | D45: =IF($C45,IFERROR(LOOKUP(2,1/((ISTEXT('Proyecto Datos (OKR´s)'!$K$7:$K45))*(LEN('Proyecto Datos (OKR´s)'!$G$7:$G45)>0)),'Proyecto Datos (OKR´s)'!$G$7:$G45),""),"") -> 5- Tablero Control General - Op. Complejas | E45: =IF($C45,'Proyecto Datos (OKR´s)'!$E45,"") -> 0 | F45: =IF($C45,'Proyecto Datos (OKR´s)'!$G45,"") -> Locaciones Geográficas Op. Dedicadas | G45: =IF($C45,IF('Proyecto Datos (OKR´s)'!$I45="","(Sin asignar)",'Proyecto Datos (OKR´s)'!$I45),"") -> Santiago Alonso | H45: =IF($C45,IF(ISNUMBER('Proyecto Datos (OKR´s)'!$F45),'Proyecto Datos (OKR´s)'!$F45,'Proyecto Datos (OKR´s)'!$L45),"") -> 46206 | I45: =IF($C45,'Proyecto Datos (OKR´s)'!$J45,"") -> 0 | J45: =IF($C45,IF($I45>=1,"Completado",IF($H45<TODAY(),"Vencido",IF(($H45-TODAY())<='Entregas Próximas'!$M$3,"Próximo a vencer","En curso"))),"") -> En curso | K45: =IF($C45,$H45-TODAY(),"") -> 14 | L45: =IF($C45,$AD45*1000000+$H45+ROW()/100000,"") -> 9.9990462e+09 | M45: =IF($C45,IF($AD45=9999,"(Sin sprint)",$AD45),"") -> (Sin sprint) | N45: =IF($C45,IF('Proyecto Datos (OKR´s)'!$E45="",9999,'Proyecto Datos (OKR´s)'!$E45),"") -> 9999 | O45: =IF($C45,"T"&TEXT(ROW(),"000"),"") -> T045 | R45: =IF($C45,IF(ISNUMBER('Proyecto Datos (OKR´s)'!$L45),'Proyecto Datos (OKR´s)'!$L45,$H45),"") -> 46206 | S45: =IF($C45,$R45-'Proyecto Datos (OKR´s)'!$K45+1,"") -> 5 | T45: =IF($C45,MAX(0,TODAY()-'Proyecto Datos (OKR´s)'!$K45),"") -> 0 | U45: =IF($C45,MEDIAN(0,(TODAY()-'Proyecto Datos (OKR´s)'!$K45)/MAX(1,$R45-'Proyecto Datos (OKR´s)'!$K45),1),"") -> 0 | V45: =IF($C45,$I45-$U45,"") -> 0 | W45: =IF($C45,IF($J45="Completado",0,MAX(0,TODAY()-$H45)),"") -> 0 | X45: =IF($C45,IF(ISNUMBER($H45),$R45-$H45,0),"") -> 0 | Y45: =IF($C45,COUNTIFS($G$7:$G$200,$G45,$J$7:$J$200,"<>Completado",$J$7:$J$200,"<>"),"") -> 35 | Z45: =IF($C45,AND($I45=0,'Proyecto Datos (OKR´s)'!$K45<=TODAY(),$J45<>"Completado"),"") -> FALSE | AA45: =IF($C45,ROUND(100*(0.35*$AK45+0.3*$AL45+0.2*$AM45+0.15*MEDIAN(0,($Y45-4)/8,1)),0),"") -> 37 | AB45: =IF($C45,IF($J45="Completado","—",IF($AA45>=70,"Crítica",IF($AA45>=45,"Alta",IF($AA45>=25,"Media","Baja")))),"") -> Media | AC45: =IF($C45,IF(LEN(TRIM($AN45))=0,"—",TRIM($AN45)),"") -> SOBRECARGA | AD45: =IF($C45,IF($N45=9999,9999,IF($J45="Completado",$N45,MAX($N45,Sprints!$M$15))),"") -> 9999 | AE45: =IF($C45,IF($AD45=9999,"(Sin sprint)",$AD45),"") -> (Sin sprint) | AF45: =IF($C45,AND($N45<>9999,$AD45<>$N45),FALSE) -> FALSE | AG45: =IF($AF45,$AO45,"") | AH45: =IF($AF45,IF(Sprints!$I45<>"",Sprints!$I45,"Comprometida y no completada al cierre del Sprint "&$N45),"") | AI45: =IF($AF45,$N45*100000+ROW(),"") | AJ45: =IF($C45,$AA45*1000000-MEDIAN(-9999,$K45,9999)*100+(300-ROW()),"") -> 36998855 | AK45: =IF($C45,IF($J45="Completado",0,IF($K45<0,1,IF($K45<=3,0.9,IF($K45<=7,0.7,IF($K45<=14,0.45,0.2))))),"") -> 0.45 | AL45: =IF($C45,IF($J45="Completado",0,MEDIAN(0,MAX(-$V45,$W45/30),1)),"") -> 0 | AM45: =IF($C45,IF($J45="Completado",0,IF($Z45,1,IF(AND($I45<0.5,$K45<=7),0.7,0.3))),"") -> 0.3 | AN45: =IF($C45,IF(OR($V45<-0.2,$W45>0),"ATRASO ","")&IF($Z45,"BLOQUEO ","")&IF($Y45>8,"SOBRECARGA ","")&IF($X45>0,"DESVÍO-PLAN ",""),"") -> SOBRECARGA | AO45: =IF($C45,IFERROR(INDEX(Sprints!$M$6:$M$13,MATCH($N45,Sprints!$K$6:$K$13,0)),""),"") | AP45: =IF($C45,IF(AND($N45<>9999,$AD45<>$N45,ISNUMBER($AO45)),TODAY()-$AO45,0),"") -> 0
A46: =ROW() -> 46 | B46: =ISTEXT('Proyecto Datos (OKR´s)'!$K46) -> FALSE | C46: =AND(LEN('Proyecto Datos (OKR´s)'!$G46)>0,NOT($B46),OR(ISNUMBER('Proyecto Datos (OKR´s)'!$F46),ISNUMBER('Proyecto Datos (OKR´s)'!$L46))) -> TRUE | D46: =IF($C46,IFERROR(LOOKUP(2,1/((ISTEXT('Proyecto Datos (OKR´s)'!$K$7:$K46))*(LEN('Proyecto Datos (OKR´s)'!$G$7:$G46)>0)),'Proyecto Datos (OKR´s)'!$G$7:$G46),""),"") -> 5- Tablero Control General - Op. Complejas | E46: =IF($C46,'Proyecto Datos (OKR´s)'!$E46,"") -> 1 | F46: =IF($C46,'Proyecto Datos (OKR´s)'!$G46,"") -> Detalle Responsables (Comerciales + Analistas) | G46: =IF($C46,IF('Proyecto Datos (OKR´s)'!$I46="","(Sin asignar)",'Proyecto Datos (OKR´s)'!$I46),"") -> Santiago Alonso | H46: =IF($C46,IF(ISNUMBER('Proyecto Datos (OKR´s)'!$F46),'Proyecto Datos (OKR´s)'!$F46,'Proyecto Datos (OKR´s)'!$L46),"") -> 46185 | I46: =IF($C46,'Proyecto Datos (OKR´s)'!$J46,"") -> 0.5 | J46: =IF($C46,IF($I46>=1,"Completado",IF($H46<TODAY(),"Vencido",IF(($H46-TODAY())<='Entregas Próximas'!$M$3,"Próximo a vencer","En curso"))),"") -> Vencido | K46: =IF($C46,$H46-TODAY(),"") -> -7 | L46: =IF($C46,$AD46*1000000+$H46+ROW()/100000,"") -> 2046185 | M46: =IF($C46,IF($AD46=9999,"(Sin sprint)",$AD46),"") -> 2 | N46: =IF($C46,IF('Proyecto Datos (OKR´s)'!$E46="",9999,'Proyecto Datos (OKR´s)'!$E46),"") -> 1 | O46: =IF($C46,"T"&TEXT(ROW(),"000"),"") -> T046 | R46: =IF($C46,IF(ISNUMBER('Proyecto Datos (OKR´s)'!$L46),'Proyecto Datos (OKR´s)'!$L46,$H46),"") -> 46185 | S46: =IF($C46,$R46-'Proyecto Datos (OKR´s)'!$K46+1,"") -> -21 | T46: =IF($C46,MAX(0,TODAY()-'Proyecto Datos (OKR´s)'!$K46),"") -> 0 | U46: =IF($C46,MEDIAN(0,(TODAY()-'Proyecto Datos (OKR´s)'!$K46)/MAX(1,$R46-'Proyecto Datos (OKR´s)'!$K46),1),"") -> 0 | V46: =IF($C46,$I46-$U46,"") -> 0.5 | W46: =IF($C46,IF($J46="Completado",0,MAX(0,TODAY()-$H46)),"") -> 7 | X46: =IF($C46,IF(ISNUMBER($H46),$R46-$H46,0),"") -> 0 | Y46: =IF($C46,COUNTIFS($G$7:$G$200,$G46,$J$7:$J$200,"<>Completado",$J$7:$J$200,"<>"),"") -> 35 | Z46: =IF($C46,AND($I46=0,'Proyecto Datos (OKR´s)'!$K46<=TODAY(),$J46<>"Completado"),"") -> FALSE | AA46: =IF($C46,ROUND(100*(0.35*$AK46+0.3*$AL46+0.2*$AM46+0.15*MEDIAN(0,($Y46-4)/8,1)),0),"") -> 63 | AB46: =IF($C46,IF($J46="Completado","—",IF($AA46>=70,"Crítica",IF($AA46>=45,"Alta",IF($AA46>=25,"Media","Baja")))),"") -> Alta | AC46: =IF($C46,IF(LEN(TRIM($AN46))=0,"—",TRIM($AN46)),"") -> ATRASO SOBRECARGA | AD46: =IF($C46,IF($N46=9999,9999,IF($J46="Completado",$N46,MAX($N46,Sprints!$M$15))),"") -> 2 | AE46: =IF($C46,IF($AD46=9999,"(Sin sprint)",$AD46),"") -> 2 | AF46: =IF($C46,AND($N46<>9999,$AD46<>$N46),FALSE) -> TRUE | AG46: =IF($AF46,$AO46,"") -> 46186 | AH46: =IF($AF46,IF(Sprints!$I46<>"",Sprints!$I46,"Comprometida y no completada al cierre del Sprint "&$N46),"") -> Comprometida y no completada al cierre del Sprint 1 | AI46: =IF($AF46,$N46*100000+ROW(),"") -> 100046 | AJ46: =IF($C46,$AA46*1000000-MEDIAN(-9999,$K46,9999)*100+(300-ROW()),"") -> 63000954 | AK46: =IF($C46,IF($J46="Completado",0,IF($K46<0,1,IF($K46<=3,0.9,IF($K46<=7,0.7,IF($K46<=14,0.45,0.2))))),"") -> 1 | AL46: =IF($C46,IF($J46="Completado",0,MEDIAN(0,MAX(-$V46,$W46/30),1)),"") -> 0.23333333 | AM46: =IF($C46,IF($J46="Completado",0,IF($Z46,1,IF(AND($I46<0.5,$K46<=7),0.7,0.3))),"") -> 0.3 | AN46: =IF($C46,IF(OR($V46<-0.2,$W46>0),"ATRASO ","")&IF($Z46,"BLOQUEO ","")&IF($Y46>8,"SOBRECARGA ","")&IF($X46>0,"DESVÍO-PLAN ",""),"") -> ATRASO SOBRECARGA | AO46: =IF($C46,IFERROR(INDEX(Sprints!$M$6:$M$13,MATCH($N46,Sprints!$K$6:$K$13,0)),""),"") -> 46186 | AP46: =IF($C46,IF(AND($N46<>9999,$AD46<>$N46,ISNUMBER($AO46)),TODAY()-$AO46,0),"") -> 6
A47: =ROW() -> 47 | B47: =ISTEXT('Proyecto Datos (OKR´s)'!$K47) -> FALSE | C47: =AND(LEN('Proyecto Datos (OKR´s)'!$G47)>0,NOT($B47),OR(ISNUMBER('Proyecto Datos (OKR´s)'!$F47),ISNUMBER('Proyecto Datos (OKR´s)'!$L47))) -> TRUE | D47: =IF($C47,IFERROR(LOOKUP(2,1/((ISTEXT('Proyecto Datos (OKR´s)'!$K$7:$K47))*(LEN('Proyecto Datos (OKR´s)'!$G$7:$G47)>0)),'Proyecto Datos (OKR´s)'!$G$7:$G47),""),"") -> 5- Tablero Control General - Op. Complejas | E47: =IF($C47,'Proyecto Datos (OKR´s)'!$E47,"") -> 1 | F47: =IF($C47,'Proyecto Datos (OKR´s)'!$G47,"") -> Armado de Dashboard + Diseño | G47: =IF($C47,IF('Proyecto Datos (OKR´s)'!$I47="","(Sin asignar)",'Proyecto Datos (OKR´s)'!$I47),"") -> Santiago Alonso | H47: =IF($C47,IF(ISNUMBER('Proyecto Datos (OKR´s)'!$F47),'Proyecto Datos (OKR´s)'!$F47,'Proyecto Datos (OKR´s)'!$L47),"") -> 46185 | I47: =IF($C47,'Proyecto Datos (OKR´s)'!$J47,"") -> 0.5 | J47: =IF($C47,IF($I47>=1,"Completado",IF($H47<TODAY(),"Vencido",IF(($H47-TODAY())<='Entregas Próximas'!$M$3,"Próximo a vencer","En curso"))),"") -> Vencido | K47: =IF($C47,$H47-TODAY(),"") -> -7 | L47: =IF($C47,$AD47*1000000+$H47+ROW()/100000,"") -> 2046185 | M47: =IF($C47,IF($AD47=9999,"(Sin sprint)",$AD47),"") -> 2 | N47: =IF($C47,IF('Proyecto Datos (OKR´s)'!$E47="",9999,'Proyecto Datos (OKR´s)'!$E47),"") -> 1 | O47: =IF($C47,"T"&TEXT(ROW(),"000"),"") -> T047 | R47: =IF($C47,IF(ISNUMBER('Proyecto Datos (OKR´s)'!$L47),'Proyecto Datos (OKR´s)'!$L47,$H47),"") -> 46185 | S47: =IF($C47,$R47-'Proyecto Datos (OKR´s)'!$K47+1,"") -> 0 | T47: =IF($C47,MAX(0,TODAY()-'Proyecto Datos (OKR´s)'!$K47),"") -> 6 | U47: =IF($C47,MEDIAN(0,(TODAY()-'Proyecto Datos (OKR´s)'!$K47)/MAX(1,$R47-'Proyecto Datos (OKR´s)'!$K47),1),"") -> 1 | V47: =IF($C47,$I47-$U47,"") -> -0.5 | W47: =IF($C47,IF($J47="Completado",0,MAX(0,TODAY()-$H47)),"") -> 7 | X47: =IF($C47,IF(ISNUMBER($H47),$R47-$H47,0),"") -> 0 | Y47: =IF($C47,COUNTIFS($G$7:$G$200,$G47,$J$7:$J$200,"<>Completado",$J$7:$J$200,"<>"),"") -> 35 | Z47: =IF($C47,AND($I47=0,'Proyecto Datos (OKR´s)'!$K47<=TODAY(),$J47<>"Completado"),"") -> FALSE | AA47: =IF($C47,ROUND(100*(0.35*$AK47+0.3*$AL47+0.2*$AM47+0.15*MEDIAN(0,($Y47-4)/8,1)),0),"") -> 71 | AB47: =IF($C47,IF($J47="Completado","—",IF($AA47>=70,"Crítica",IF($AA47>=45,"Alta",IF($AA47>=25,"Media","Baja")))),"") -> Crítica | AC47: =IF($C47,IF(LEN(TRIM($AN47))=0,"—",TRIM($AN47)),"") -> ATRASO SOBRECARGA | AD47: =IF($C47,IF($N47=9999,9999,IF($J47="Completado",$N47,MAX($N47,Sprints!$M$15))),"") -> 2 | AE47: =IF($C47,IF($AD47=9999,"(Sin sprint)",$AD47),"") -> 2 | AF47: =IF($C47,AND($N47<>9999,$AD47<>$N47),FALSE) -> TRUE | AG47: =IF($AF47,$AO47,"") -> 46186 | AH47: =IF($AF47,IF(Sprints!$I47<>"",Sprints!$I47,"Comprometida y no completada al cierre del Sprint "&$N47),"") -> Comprometida y no completada al cierre del Sprint 1 | AI47: =IF($AF47,$N47*100000+ROW(),"") -> 100047 | AJ47: =IF($C47,$AA47*1000000-MEDIAN(-9999,$K47,9999)*100+(300-ROW()),"") -> 71000953 | AK47: =IF($C47,IF($J47="Completado",0,IF($K47<0,1,IF($K47<=3,0.9,IF($K47<=7,0.7,IF($K47<=14,0.45,0.2))))),"") -> 1 | AL47: =IF($C47,IF($J47="Completado",0,MEDIAN(0,MAX(-$V47,$W47/30),1)),"") -> 0.5 | AM47: =IF($C47,IF($J47="Completado",0,IF($Z47,1,IF(AND($I47<0.5,$K47<=7),0.7,0.3))),"") -> 0.3 | AN47: =IF($C47,IF(OR($V47<-0.2,$W47>0),"ATRASO ","")&IF($Z47,"BLOQUEO ","")&IF($Y47>8,"SOBRECARGA ","")&IF($X47>0,"DESVÍO-PLAN ",""),"") -> ATRASO SOBRECARGA | AO47: =IF($C47,IFERROR(INDEX(Sprints!$M$6:$M$13,MATCH($N47,Sprints!$K$6:$K$13,0)),""),"") -> 46186 | AP47: =IF($C47,IF(AND($N47<>9999,$AD47<>$N47,ISNUMBER($AO47)),TODAY()-$AO47,0),"") -> 6
A48: =ROW() -> 48 | B48: =ISTEXT('Proyecto Datos (OKR´s)'!$K48) -> TRUE | C48: =AND(LEN('Proyecto Datos (OKR´s)'!$G48)>0,NOT($B48),OR(ISNUMBER('Proyecto Datos (OKR´s)'!$F48),ISNUMBER('Proyecto Datos (OKR´s)'!$L48))) -> FALSE | D48: =IF($C48,IFERROR(LOOKUP(2,1/((ISTEXT('Proyecto Datos (OKR´s)'!$K$7:$K48))*(LEN('Proyecto Datos (OKR´s)'!$G$7:$G48)>0)),'Proyecto Datos (OKR´s)'!$G$7:$G48),""),"") | E48: =IF($C48,'Proyecto Datos (OKR´s)'!$E48,"") | F48: =IF($C48,'Proyecto Datos (OKR´s)'!$G48,"") | G48: =IF($C48,IF('Proyecto Datos (OKR´s)'!$I48="","(Sin asignar)",'Proyecto Datos (OKR´s)'!$I48),"") | H48: =IF($C48,IF(ISNUMBER('Proyecto Datos (OKR´s)'!$F48),'Proyecto Datos (OKR´s)'!$F48,'Proyecto Datos (OKR´s)'!$L48),"") | I48: =IF($C48,'Proyecto Datos (OKR´s)'!$J48,"") | J48: =IF($C48,IF($I48>=1,"Completado",IF($H48<TODAY(),"Vencido",IF(($H48-TODAY())<='Entregas Próximas'!$M$3,"Próximo a vencer","En curso"))),"") | K48: =IF($C48,$H48-TODAY(),"") | L48: =IF($C48,$AD48*1000000+$H48+ROW()/100000,"") | M48: =IF($C48,IF($AD48=9999,"(Sin sprint)",$AD48),"") | N48: =IF($C48,IF('Proyecto Datos (OKR´s)'!$E48="",9999,'Proyecto Datos (OKR´s)'!$E48),"") | O48: =IF($C48,"T"&TEXT(ROW(),"000"),"") | R48: =IF($C48,IF(ISNUMBER('Proyecto Datos (OKR´s)'!$L48),'Proyecto Datos (OKR´s)'!$L48,$H48),"") | S48: =IF($C48,$R48-'Proyecto Datos (OKR´s)'!$K48+1,"") | T48: =IF($C48,MAX(0,TODAY()-'Proyecto Datos (OKR´s)'!$K48),"") | U48: =IF($C48,MEDIAN(0,(TODAY()-'Proyecto Datos (OKR´s)'!$K48)/MAX(1,$R48-'Proyecto Datos (OKR´s)'!$K48),1),"") | V48: =IF($C48,$I48-$U48,"") | W48: =IF($C48,IF($J48="Completado",0,MAX(0,TODAY()-$H48)),"") | X48: =IF($C48,IF(ISNUMBER($H48),$R48-$H48,0),"") | Y48: =IF($C48,COUNTIFS($G$7:$G$200,$G48,$J$7:$J$200,"<>Completado",$J$7:$J$200,"<>"),"") | Z48: =IF($C48,AND($I48=0,'Proyecto Datos (OKR´s)'!$K48<=TODAY(),$J48<>"Completado"),"") | AA48: =IF($C48,ROUND(100*(0.35*$AK48+0.3*$AL48+0.2*$AM48+0.15*MEDIAN(0,($Y48-4)/8,1)),0),"") | AB48: =IF($C48,IF($J48="Completado","—",IF($AA48>=70,"Crítica",IF($AA48>=45,"Alta",IF($AA48>=25,"Media","Baja")))),"") | AC48: =IF($C48,IF(LEN(TRIM($AN48))=0,"—",TRIM($AN48)),"") | AD48: =IF($C48,IF($N48=9999,9999,IF($J48="Completado",$N48,MAX($N48,Sprints!$M$15))),"") | AE48: =IF($C48,IF($AD48=9999,"(Sin sprint)",$AD48),"") | AF48: =IF($C48,AND($N48<>9999,$AD48<>$N48),FALSE) -> FALSE | AG48: =IF($AF48,$AO48,"") | AH48: =IF($AF48,IF(Sprints!$I48<>"",Sprints!$I48,"Comprometida y no completada al cierre del Sprint "&$N48),"") | AI48: =IF($AF48,$N48*100000+ROW(),"") | AJ48: =IF($C48,$AA48*1000000-MEDIAN(-9999,$K48,9999)*100+(300-ROW()),"") | AK48: =IF($C48,IF($J48="Completado",0,IF($K48<0,1,IF($K48<=3,0.9,IF($K48<=7,0.7,IF($K48<=14,0.45,0.2))))),"") | AL48: =IF($C48,IF($J48="Completado",0,MEDIAN(0,MAX(-$V48,$W48/30),1)),"") | AM48: =IF($C48,IF($J48="Completado",0,IF($Z48,1,IF(AND($I48<0.5,$K48<=7),0.7,0.3))),"") | AN48: =IF($C48,IF(OR($V48<-0.2,$W48>0),"ATRASO ","")&IF($Z48,"BLOQUEO ","")&IF($Y48>8,"SOBRECARGA ","")&IF($X48>0,"DESVÍO-PLAN ",""),"") | AO48: =IF($C48,IFERROR(INDEX(Sprints!$M$6:$M$13,MATCH($N48,Sprints!$K$6:$K$13,0)),""),"") | AP48: =IF($C48,IF(AND($N48<>9999,$AD48<>$N48,ISNUMBER($AO48)),TODAY()-$AO48,0),"")
A49: =ROW() -> 49 | B49: =ISTEXT('Proyecto Datos (OKR´s)'!$K49) -> FALSE | C49: =AND(LEN('Proyecto Datos (OKR´s)'!$G49)>0,NOT($B49),OR(ISNUMBER('Proyecto Datos (OKR´s)'!$F49),ISNUMBER('Proyecto Datos (OKR´s)'!$L49))) -> TRUE | D49: =IF($C49,IFERROR(LOOKUP(2,1/((ISTEXT('Proyecto Datos (OKR´s)'!$K$7:$K49))*(LEN('Proyecto Datos (OKR´s)'!$G$7:$G49)>0)),'Proyecto Datos (OKR´s)'!$G$7:$G49),""),"") -> 6- Automatización de procesos: certificación, provisión,polinómicas | E49: =IF($C49,'Proyecto Datos (OKR´s)'!$E49,"") -> 0 | F49: =IF($C49,'Proyecto Datos (OKR´s)'!$G49,"") -> Polinómicas y tarifario automático | G49: =IF($C49,IF('Proyecto Datos (OKR´s)'!$I49="","(Sin asignar)",'Proyecto Datos (OKR´s)'!$I49),"") -> Santiago Alonso | H49: =IF($C49,IF(ISNUMBER('Proyecto Datos (OKR´s)'!$F49),'Proyecto Datos (OKR´s)'!$F49,'Proyecto Datos (OKR´s)'!$L49),"") -> 46213 | I49: =IF($C49,'Proyecto Datos (OKR´s)'!$J49,"") -> 0.35 | J49: =IF($C49,IF($I49>=1,"Completado",IF($H49<TODAY(),"Vencido",IF(($H49-TODAY())<='Entregas Próximas'!$M$3,"Próximo a vencer","En curso"))),"") -> En curso | K49: =IF($C49,$H49-TODAY(),"") -> 21 | L49: =IF($C49,$AD49*1000000+$H49+ROW()/100000,"") -> 9.9990462e+09 | M49: =IF($C49,IF($AD49=9999,"(Sin sprint)",$AD49),"") -> (Sin sprint) | N49: =IF($C49,IF('Proyecto Datos (OKR´s)'!$E49="",9999,'Proyecto Datos (OKR´s)'!$E49),"") -> 9999 | O49: =IF($C49,"T"&TEXT(ROW(),"000"),"") -> T049 | R49: =IF($C49,IF(ISNUMBER('Proyecto Datos (OKR´s)'!$L49),'Proyecto Datos (OKR´s)'!$L49,$H49),"") -> 46213 | S49: =IF($C49,$R49-'Proyecto Datos (OKR´s)'!$K49+1,"") -> 256 | T49: =IF($C49,MAX(0,TODAY()-'Proyecto Datos (OKR´s)'!$K49),"") -> 234 | U49: =IF($C49,MEDIAN(0,(TODAY()-'Proyecto Datos (OKR´s)'!$K49)/MAX(1,$R49-'Proyecto Datos (OKR´s)'!$K49),1),"") -> 0.91764706 | V49: =IF($C49,$I49-$U49,"") -> -0.56764706 | W49: =IF($C49,IF($J49="Completado",0,MAX(0,TODAY()-$H49)),"") -> 0 | X49: =IF($C49,IF(ISNUMBER($H49),$R49-$H49,0),"") -> 0 | Y49: =IF($C49,COUNTIFS($G$7:$G$200,$G49,$J$7:$J$200,"<>Completado",$J$7:$J$200,"<>"),"") -> 35 | Z49: =IF($C49,AND($I49=0,'Proyecto Datos (OKR´s)'!$K49<=TODAY(),$J49<>"Completado"),"") -> FALSE | AA49: =IF($C49,ROUND(100*(0.35*$AK49+0.3*$AL49+0.2*$AM49+0.15*MEDIAN(0,($Y49-4)/8,1)),0),"") -> 45 | AB49: =IF($C49,IF($J49="Completado","—",IF($AA49>=70,"Crítica",IF($AA49>=45,"Alta",IF($AA49>=25,"Media","Baja")))),"") -> Alta | AC49: =IF($C49,IF(LEN(TRIM($AN49))=0,"—",TRIM($AN49)),"") -> ATRASO SOBRECARGA | AD49: =IF($C49,IF($N49=9999,9999,IF($J49="Completado",$N49,MAX($N49,Sprints!$M$15))),"") -> 9999 | AE49: =IF($C49,IF($AD49=9999,"(Sin sprint)",$AD49),"") -> (Sin sprint) | AF49: =IF($C49,AND($N49<>9999,$AD49<>$N49),FALSE) -> FALSE | AG49: =IF($AF49,$AO49,"") | AH49: =IF($AF49,IF(Sprints!$I49<>"",Sprints!$I49,"Comprometida y no completada al cierre del Sprint "&$N49),"") | AI49: =IF($AF49,$N49*100000+ROW(),"") | AJ49: =IF($C49,$AA49*1000000-MEDIAN(-9999,$K49,9999)*100+(300-ROW()),"") -> 44998151 | AK49: =IF($C49,IF($J49="Completado",0,IF($K49<0,1,IF($K49<=3,0.9,IF($K49<=7,0.7,IF($K49<=14,0.45,0.2))))),"") -> 0.2 | AL49: =IF($C49,IF($J49="Completado",0,MEDIAN(0,MAX(-$V49,$W49/30),1)),"") -> 0.56764706 | AM49: =IF($C49,IF($J49="Completado",0,IF($Z49,1,IF(AND($I49<0.5,$K49<=7),0.7,0.3))),"") -> 0.3 | AN49: =IF($C49,IF(OR($V49<-0.2,$W49>0),"ATRASO ","")&IF($Z49,"BLOQUEO ","")&IF($Y49>8,"SOBRECARGA ","")&IF($X49>0,"DESVÍO-PLAN ",""),"") -> ATRASO SOBRECARGA | AO49: =IF($C49,IFERROR(INDEX(Sprints!$M$6:$M$13,MATCH($N49,Sprints!$K$6:$K$13,0)),""),"") | AP49: =IF($C49,IF(AND($N49<>9999,$AD49<>$N49,ISNUMBER($AO49)),TODAY()-$AO49,0),"") -> 0
... A200: =ROW() -> 200 | B200: =ISTEXT('Proyecto Datos (OKR´s)'!$K200) -> FALSE | C200: =AND(LEN('Proyecto Datos (OKR´s)'!$G200)>0,NOT($B200),OR(ISNUMBER('Proyecto Datos (OKR´s)'!$F200),ISNUMBER('Proyecto Datos (OKR´s)'!$L200))) -> FALSE | D200: =IF($C200,IFERROR(LOOKUP(2,1/((ISTEXT('Proyecto Datos (OKR´s)'!$K$7:$K200))*(LEN('Proyecto Datos (OKR´s)'!$G$7:$G200)>0)),'Proyecto Datos (OKR´s)'!$G$7:$G200),""),"") | E200: =IF($C200,'Proyecto Datos (OKR´s)'!$E200,"") | F200: =IF($C200,'Proyecto Datos (OKR´s)'!$G200,"") | G200: =IF($C200,IF('Proyecto Datos (OKR´s)'!$I200="","(Sin asignar)",'Proyecto Datos (OKR´s)'!$I200),"") | H200: =IF($C200,IF(ISNUMBER('Proyecto Datos (OKR´s)'!$F200),'Proyecto Datos (OKR´s)'!$F200,'Proyecto Datos (OKR´s)'!$L200),"") | I200: =IF($C200,'Proyecto Datos (OKR´s)'!$J200,"") | J200: =IF($C200,IF($I200>=1,"Completado",IF($H200<TODAY(),"Vencido",IF(($H200-TODAY())<='Entregas Próximas'!$M$3,"Próximo a vencer","En curso"))),"") | K200: =IF($C200,$H200-TODAY(),"") | L200: =IF($C200,$AD200*1000000+$H200+ROW()/100000,"") | M200: =IF($C200,IF($AD200=9999,"(Sin sprint)",$AD200),"") | N200: =IF($C200,IF('Proyecto Datos (OKR´s)'!$E200="",9999,'Proyecto Datos (OKR´s)'!$E200),"") | O200: =IF($C200,"T"&TEXT(ROW(),"000"),"") | R200: =IF($C200,IF(ISNUMBER('Proyecto Datos (OKR´s)'!$L200),'Proyecto Datos (OKR´s)'!$L200,$H200),"") | S200: =IF($C200,$R200-'Proyecto Datos (OKR´s)'!$K200+1,"") | T200: =IF($C200,MAX(0,TODAY()-'Proyecto Datos (OKR´s)'!$K200),"") | U200: =IF($C200,MEDIAN(0,(TODAY()-'Proyecto Datos (OKR´s)'!$K200)/MAX(1,$R200-'Proyecto Datos (OKR´s)'!$K200),1),"") | V200: =IF($C200,$I200-$U200,"") | W200: =IF($C200,IF($J200="Completado",0,MAX(0,TODAY()-$H200)),"") | X200: =IF($C200,IF(ISNUMBER($H200),$R200-$H200,0),"") | Y200: =IF($C200,COUNTIFS($G$7:$G$200,$G200,$J$7:$J$200,"<>Completado",$J$7:$J$200,"<>"),"") | Z200: =IF($C200,AND($I200=0,'Proyecto Datos (OKR´s)'!$K200<=TODAY(),$J200<>"Completado"),"") | AA200: =IF($C200,ROUND(100*(0.35*$AK200+0.3*$AL200+0.2*$AM200+0.15*MEDIAN(0,($Y200-4)/8,1)),0),"") | AB200: =IF($C200,IF($J200="Completado","—",IF($AA200>=70,"Crítica",IF($AA200>=45,"Alta",IF($AA200>=25,"Media","Baja")))),"") | AC200: =IF($C200,IF(LEN(TRIM($AN200))=0,"—",TRIM($AN200)),"") | AD200: =IF($C200,IF($N200=9999,9999,IF($J200="Completado",$N200,MAX($N200,Sprints!$M$15))),"") | AE200: =IF($C200,IF($AD200=9999,"(Sin sprint)",$AD200),"") | AF200: =IF($C200,AND($N200<>9999,$AD200<>$N200),FALSE) -> FALSE | AG200: =IF($AF200,$AO200,"") | AH200: =IF($AF200,IF(Sprints!$I200<>"",Sprints!$I200,"Comprometida y no completada al cierre del Sprint "&$N200),"") | AI200: =IF($AF200,$N200*100000+ROW(),"") | AJ200: =IF($C200,$AA200*1000000-MEDIAN(-9999,$K200,9999)*100+(300-ROW()),"") | AK200: =IF($C200,IF($J200="Completado",0,IF($K200<0,1,IF($K200<=3,0.9,IF($K200<=7,0.7,IF($K200<=14,0.45,0.2))))),"") | AL200: =IF($C200,IF($J200="Completado",0,MEDIAN(0,MAX(-$V200,$W200/30),1)),"") | AM200: =IF($C200,IF($J200="Completado",0,IF($Z200,1,IF(AND($I200<0.5,$K200<=7),0.7,0.3))),"") | AN200: =IF($C200,IF(OR($V200<-0.2,$W200>0),"ATRASO ","")&IF($Z200,"BLOQUEO ","")&IF($Y200>8,"SOBRECARGA ","")&IF($X200>0,"DESVÍO-PLAN ",""),"") | AO200: =IF($C200,IFERROR(INDEX(Sprints!$M$6:$M$13,MATCH($N200,Sprints!$K$6:$K$13,0)),""),"") | AP200: =IF($C200,IF(AND($N200<>9999,$AD200<>$N200,ISNUMBER($AO200)),TODAY()-$AO200,0),"")
